[
  {
    "id": "d6595c56-e9e2-4947-b7d0-e7cff6cce59a",
    "matchId": "2390266",
    "logText": "8Juho8 kr1vda",
    "killerName": "8Juho8",
    "victimName": "kr1vda",
    "assistName": null,
    "weapon": "ak47",
    "isHeadshot": true,
    "isWallbang": false,
    "isThroughSmoke": false,
    "isBlindKill": false,
    "isNoScope": false,
    "isSuicide": false,
    "eventType": "kill",
    "mapNumber": 1,
    "roundNumber": 1,
    "eventHash": "5121f2de272714fbcb627d3f4605575c",
    "timestamp": "2026-02-25T15:02:18.750Z"
  },
  {
    "id": "9db877e4-c24f-43be-9924-e52a94e7fe85",
    "matchId": "2390266",
    "logText": "8Juho8 maggent",
    "killerName": "8Juho8",
    "victimName": "maggent",
    "assistName": null,
    "weapon": "ak47",
    "isHeadshot": true,
    "isWallbang": false,
    "isThroughSmoke": false,
    "isBlindKill": false,
    "isNoScope": false,
    "isSuicide": false,
    "eventType": "kill",
    "mapNumber": 1,
    "roundNumber": 1,
    "eventHash": "2365f98fdc0a93c51f5719ce7bc31b31",
    "timestamp": "2026-02-25T15:02:18.760Z"
  },
  {
    "id": "edf7920c-feee-43ab-ac26-1c352472b250",
    "matchId": "2390266",
    "logText": "maggent melty",
    "killerName": "maggent",
    "victimName": "melty",
    "assistName": null,
    "weapon": "ak47",
    "isHeadshot": true,
    "isWallbang": false,
    "isThroughSmoke": false,
    "isBlindKill": false,
    "isNoScope": false,
    "isSuicide": false,
    "eventType": "kill",
    "mapNumber": 1,
    "roundNumber": 1,
    "eventHash": "d0a4a0b85aa9714ee130d989983aa8db",
    "timestamp": "2026-02-25T15:02:18.770Z"
  },
  {
    "id": "96529bc6-28d0-4f51-bc6a-6b3e84bd7870",
    "matchId": "2390266",
    "logText": "maggent oopee",
    "killerName": "maggent",
    "victimName": "oopee",
    "assistName": null,
    "weapon": "m4a1_silencer",
    "isHeadshot": false,
    "isWallbang": false,
    "isThroughSmoke": false,
    "isBlindKill": false,
    "isNoScope": false,
    "isSuicide": false,
    "eventType": "kill",
    "mapNumber": 1,
    "roundNumber": 1,
    "eventHash": "ec5ba268c456fce007a8c9eb37f1e628",
    "timestamp": "2026-02-25T15:02:18.780Z"
  },
  {
    "id": "fa94e42c-7846-48bd-ba84-142b9002f498",
    "matchId": "2390266",
    "logText": "maggent 8Juho8",
    "killerName": "maggent",
    "victimName": "8Juho8",
    "assistName": null,
    "weapon": "m4a1_silencer",
    "isHeadshot": false,
    "isWallbang": false,
    "isThroughSmoke": false,
    "isBlindKill": false,
    "isNoScope": false,
    "isSuicide": false,
    "eventType": "kill",
    "mapNumber": 1,
    "roundNumber": 1,
    "eventHash": "f6d685e18fe9e0dc4a9f9e9191c845f2",
    "timestamp": "2026-02-25T15:02:18.791Z"
  },
  {
    "id": "83b50c3f-1db2-49f1-829e-097989c502eb",
    "matchId": "2390266",
    "logText": "kr1vda melty",
    "killerName": "kr1vda",
    "victimName": "melty",
    "assistName": null,
    "weapon": "ak47",
    "isHeadshot": true,
    "isWallbang": false,
    "isThroughSmoke": false,
    "isBlindKill": false,
    "isNoScope": false,
    "isSuicide": false,
    "eventType": "kill",
    "mapNumber": 1,
    "roundNumber": 1,
    "eventHash": "92bb2c59babae5aaa2afc6e0f961f43c",
    "timestamp": "2026-02-25T15:02:18.803Z"
  },
  {
    "id": "2dd7f3fc-b72e-4233-9a29-524c0e6aa0d9",
    "matchId": "2390266",
    "logText": "kr1vda 8Juho8",
    "killerName": "kr1vda",
    "victimName": "8Juho8",
    "assistName": null,
    "weapon": "ak47",
    "isHeadshot": true,
    "isWallbang": false,
    "isThroughSmoke": false,
    "isBlindKill": false,
    "isNoScope": false,
    "isSuicide": false,
    "eventType": "kill",
    "mapNumber": 1,
    "roundNumber": 1,
    "eventHash": "ce1daa7ec111b90d8aba427fd27137c4",
    "timestamp": "2026-02-25T15:02:18.814Z"
  },
  {
    "id": "18918234-91a2-445f-a35f-902862138926",
    "matchId": "2390266",
    "logText": "fakerealityy oopee",
    "killerName": "fakerealityy",
    "victimName": "oopee",
    "assistName": null,
    "weapon": "m4a1_silencer",
    "isHeadshot": false,
    "isWallbang": false,
    "isThroughSmoke": false,
    "isBlindKill": false,
    "isNoScope": false,
    "isSuicide": false,
    "eventType": "kill",
    "mapNumber": 1,
    "roundNumber": 1,
    "eventHash": "c1b56e7ac96aa509c05aa053c9f8ff62",
    "timestamp": "2026-02-25T15:02:18.823Z"
  },
  {
    "id": "518cb3e5-81ce-46de-be84-ff5511defa0a",
    "matchId": "2390266",
    "logText": "oopee maggent",
    "killerName": "oopee",
    "victimName": "maggent",
    "assistName": null,
    "weapon": "ak47",
    "isHeadshot": false,
    "isWallbang": false,
    "isThroughSmoke": false,
    "isBlindKill": false,
    "isNoScope": false,
    "isSuicide": false,
    "eventType": "kill",
    "mapNumber": 1,
    "roundNumber": 1,
    "eventHash": "a0180e5ba4827a505ddae3677c7b3164",
    "timestamp": "2026-02-25T15:02:18.833Z"
  },
  {
    "id": "b9d3c041-109f-4bc6-a3af-55d342028418",
    "matchId": "2390266",
    "logText": "kr1vda Myggis",
    "killerName": "kr1vda",
    "victimName": "Myggis",
    "assistName": null,
    "weapon": "ak47",
    "isHeadshot": true,
    "isWallbang": false,
    "isThroughSmoke": false,
    "isBlindKill": false,
    "isNoScope": false,
    "isSuicide": false,
    "eventType": "kill",
    "mapNumber": 1,
    "roundNumber": 1,
    "eventHash": "5d39cf397dce471ee5194b8d8930ff5f",
    "timestamp": "2026-02-25T15:02:18.846Z"
  },
  {
    "id": "da33b981-1b8f-4560-af14-9ff98c22135a",
    "matchId": "2390266",
    "logText": "kr1vda oopee",
    "killerName": "kr1vda",
    "victimName": "oopee",
    "assistName": null,
    "weapon": "deagle",
    "isHeadshot": false,
    "isWallbang": false,
    "isThroughSmoke": false,
    "isBlindKill": false,
    "isNoScope": false,
    "isSuicide": false,
    "eventType": "kill",
    "mapNumber": 1,
    "roundNumber": 1,
    "eventHash": "00b9f8ab02e56dee93981e1502e08979",
    "timestamp": "2026-02-25T15:02:18.856Z"
  },
  {
    "id": "cb13625f-100c-4591-a38d-57663d21e99d",
    "matchId": "2390266",
    "logText": "oopee kr1vda",
    "killerName": "oopee",
    "victimName": "kr1vda",
    "assistName": null,
    "weapon": "ak47",
    "isHeadshot": false,
    "isWallbang": false,
    "isThroughSmoke": false,
    "isBlindKill": false,
    "isNoScope": false,
    "isSuicide": false,
    "eventType": "kill",
    "mapNumber": 1,
    "roundNumber": 1,
    "eventHash": "f4990320c8983fa1097467f52108c6b9",
    "timestamp": "2026-02-25T15:02:18.867Z"
  },
  {
    "id": "00c3ddea-c649-47ce-a880-1bd57a940a14",
    "matchId": "2390266",
    "logText": "Myggis kr1vda",
    "killerName": "Myggis",
    "victimName": "kr1vda",
    "assistName": null,
    "weapon": "g3sg1",
    "isHeadshot": false,
    "isWallbang": false,
    "isThroughSmoke": false,
    "isBlindKill": false,
    "isNoScope": false,
    "isSuicide": false,
    "eventType": "kill",
    "mapNumber": 1,
    "roundNumber": 1,
    "eventHash": "e66eae641d5ab9afe51577e9142aec94",
    "timestamp": "2026-02-25T15:02:18.877Z"
  },
  {
    "id": "6f40c8d6-74bc-4ae4-973e-4477705e5f29",
    "matchId": "2390266",
    "logText": "fakerealityy 8Juho8",
    "killerName": "fakerealityy",
    "victimName": "8Juho8",
    "assistName": null,
    "weapon": "m4a1_silencer",
    "isHeadshot": true,
    "isWallbang": false,
    "isThroughSmoke": false,
    "isBlindKill": false,
    "isNoScope": false,
    "isSuicide": false,
    "eventType": "kill",
    "mapNumber": 1,
    "roundNumber": 1,
    "eventHash": "c90c0d20b1ffc7e115d90cd3803f52c8",
    "timestamp": "2026-02-25T15:02:21.652Z"
  },
  {
    "id": "7dfd504b-4ea7-434e-9ebf-4ca7435a6cca",
    "matchId": "2390266",
    "logText": "kr1vda oopee",
    "killerName": "kr1vda",
    "victimName": "oopee",
    "assistName": null,
    "weapon": "ak47",
    "isHeadshot": true,
    "isWallbang": false,
    "isThroughSmoke": false,
    "isBlindKill": false,
    "isNoScope": false,
    "isSuicide": false,
    "eventType": "kill",
    "mapNumber": 1,
    "roundNumber": 1,
    "eventHash": "47389eef05338fb820723917aa8ce3ee",
    "timestamp": "2026-02-25T15:02:21.662Z"
  },
  {
    "id": "e1a81918-2097-4807-87b8-24cf62a46254",
    "matchId": "2390266",
    "logText": "kr1vda 8Juho8",
    "killerName": "kr1vda",
    "victimName": "8Juho8",
    "assistName": null,
    "weapon": "ak47",
    "isHeadshot": false,
    "isWallbang": false,
    "isThroughSmoke": false,
    "isBlindKill": false,
    "isNoScope": false,
    "isSuicide": false,
    "eventType": "kill",
    "mapNumber": 1,
    "roundNumber": 1,
    "eventHash": "8c725cefb8588a683a9fd389ff56db73",
    "timestamp": "2026-02-25T15:02:21.673Z"
  },
  {
    "id": "79e959cf-4f9f-42ec-976f-5e5ff3d7b155",
    "matchId": "2390266",
    "logText": "oopee maggent",
    "killerName": "oopee",
    "victimName": "maggent",
    "assistName": null,
    "weapon": "ak47",
    "isHeadshot": true,
    "isWallbang": false,
    "isThroughSmoke": false,
    "isBlindKill": false,
    "isNoScope": false,
    "isSuicide": false,
    "eventType": "kill",
    "mapNumber": 1,
    "roundNumber": 1,
    "eventHash": "0887facf6704e50583efefb825ec621a",
    "timestamp": "2026-02-25T15:02:21.684Z"
  },
  {
    "id": "1bd457b3-103a-4b25-8f1f-d1fa09ec31c4",
    "matchId": "2390266",
    "logText": "kr1vda oopee",
    "killerName": "kr1vda",
    "victimName": "oopee",
    "assistName": null,
    "weapon": "m4a1_silencer",
    "isHeadshot": false,
    "isWallbang": false,
    "isThroughSmoke": false,
    "isBlindKill": false,
    "isNoScope": false,
    "isSuicide": false,
    "eventType": "kill",
    "mapNumber": 1,
    "roundNumber": 1,
    "eventHash": "e98b8203afd7df964636becc513b7433",
    "timestamp": "2026-02-25T15:02:21.693Z"
  },
  {
    "id": "7274179f-b927-4e98-ad58-ac8cd1bb200f",
    "matchId": "2390266",
    "logText": "8Juho8 fakerealityy",
    "killerName": "8Juho8",
    "victimName": "fakerealityy",
    "assistName": null,
    "weapon": "ak47",
    "isHeadshot": true,
    "isWallbang": false,
    "isThroughSmoke": false,
    "isBlindKill": false,
    "isNoScope": false,
    "isSuicide": false,
    "eventType": "kill",
    "mapNumber": 1,
    "roundNumber": 1,
    "eventHash": "93a5ba5abac6e323b99aa8141e0b6e14",
    "timestamp": "2026-02-25T15:02:21.709Z"
  },
  {
    "id": "056d674c-a3d9-4f68-993b-0a13fee69eed",
    "matchId": "2390266",
    "logText": "8Juho8 maggent",
    "killerName": "8Juho8",
    "victimName": "maggent",
    "assistName": null,
    "weapon": "ak47",
    "isHeadshot": false,
    "isWallbang": false,
    "isThroughSmoke": false,
    "isBlindKill": false,
    "isNoScope": false,
    "isSuicide": false,
    "eventType": "kill",
    "mapNumber": 1,
    "roundNumber": 1,
    "eventHash": "54c4242e25d966a34fff3dd0ff66114b",
    "timestamp": "2026-02-25T15:02:21.721Z"
  },
  {
    "id": "37fa34bf-b5ad-409f-ae0b-2241ede57d80",
    "matchId": "2390266",
    "logText": "maggent oopee",
    "killerName": "maggent",
    "victimName": "oopee",
    "assistName": null,
    "weapon": "deagle",
    "isHeadshot": true,
    "isWallbang": false,
    "isThroughSmoke": false,
    "isBlindKill": false,
    "isNoScope": false,
    "isSuicide": false,
    "eventType": "kill",
    "mapNumber": 1,
    "roundNumber": 1,
    "eventHash": "b57cfa7d0fabb283045ee709d0d459c3",
    "timestamp": "2026-02-25T15:02:21.734Z"
  },
  {
    "id": "83b8c83f-06a0-4002-b48b-2eb395d295db",
    "matchId": "2390266",
    "logText": "oopee kr1vda",
    "killerName": "oopee",
    "victimName": "kr1vda",
    "assistName": null,
    "weapon": "ak47",
    "isHeadshot": true,
    "isWallbang": false,
    "isThroughSmoke": false,
    "isBlindKill": false,
    "isNoScope": false,
    "isSuicide": false,
    "eventType": "kill",
    "mapNumber": 1,
    "roundNumber": 1,
    "eventHash": "0be3101a241e5155c88d0978fd3b4d88",
    "timestamp": "2026-02-25T15:02:21.745Z"
  },
  {
    "id": "06e6c33e-d318-4863-953f-42fc785af156",
    "matchId": "2390266",
    "logText": "oopee maggent",
    "killerName": "oopee",
    "victimName": "maggent",
    "assistName": null,
    "weapon": "deagle",
    "isHeadshot": true,
    "isWallbang": false,
    "isThroughSmoke": false,
    "isBlindKill": false,
    "isNoScope": false,
    "isSuicide": false,
    "eventType": "kill",
    "mapNumber": 1,
    "roundNumber": 1,
    "eventHash": "c2052990938608ad4c90aad72468ca57",
    "timestamp": "2026-02-25T15:02:21.757Z"
  },
  {
    "id": "43534754-4ea5-4b8c-b86b-3cc0063e3c68",
    "matchId": "2390266",
    "logText": "oopee fakerealityy",
    "killerName": "oopee",
    "victimName": "fakerealityy",
    "assistName": null,
    "weapon": "deagle",
    "isHeadshot": true,
    "isWallbang": false,
    "isThroughSmoke": false,
    "isBlindKill": false,
    "isNoScope": false,
    "isSuicide": false,
    "eventType": "kill",
    "mapNumber": 1,
    "roundNumber": 1,
    "eventHash": "ba6421b7945d35bbf598507d51e61014",
    "timestamp": "2026-02-25T15:02:21.769Z"
  },
  {
    "id": "ee8f734e-9305-4574-b6c9-767e1128c65a",
    "matchId": "2390266",
    "logText": "maggent Myggis",
    "killerName": "maggent",
    "victimName": "Myggis",
    "assistName": null,
    "weapon": "deagle",
    "isHeadshot": true,
    "isWallbang": false,
    "isThroughSmoke": false,
    "isBlindKill": false,
    "isNoScope": false,
    "isSuicide": false,
    "eventType": "kill",
    "mapNumber": 1,
    "roundNumber": 1,
    "eventHash": "aa70efeb2314785dcfa238682c161813",
    "timestamp": "2026-02-25T15:02:21.779Z"
  },
  {
    "id": "a06b9e98-6db0-4869-9da2-d23d57567af6",
    "matchId": "2390266",
    "logText": "fakerealityy oopee",
    "killerName": "fakerealityy",
    "victimName": "oopee",
    "assistName": null,
    "weapon": "m4a1_silencer",
    "isHeadshot": true,
    "isWallbang": false,
    "isThroughSmoke": false,
    "isBlindKill": false,
    "isNoScope": false,
    "isSuicide": false,
    "eventType": "kill",
    "mapNumber": 1,
    "roundNumber": 1,
    "eventHash": "0c7e54c352628f9fe4fae1d680badc56",
    "timestamp": "2026-02-25T15:02:21.790Z"
  },
  {
    "id": "1b8466a9-1886-4117-978b-5077724ece29",
    "matchId": "2390266",
    "logText": "oopee fakerealityy",
    "killerName": "oopee",
    "victimName": "fakerealityy",
    "assistName": null,
    "weapon": "awp",
    "isHeadshot": false,
    "isWallbang": false,
    "isThroughSmoke": false,
    "isBlindKill": false,
    "isNoScope": false,
    "isSuicide": false,
    "eventType": "kill",
    "mapNumber": 1,
    "roundNumber": 1,
    "eventHash": "624b4a4324aa7fb349320833a2077384",
    "timestamp": "2026-02-25T15:02:22.651Z"
  },
  {
    "id": "66cddade-1e9d-4fbe-a090-8a723ef2fef5",
    "matchId": "2390266",
    "logText": "oopee maggent",
    "killerName": "oopee",
    "victimName": "maggent",
    "assistName": null,
    "weapon": "awp",
    "isHeadshot": false,
    "isWallbang": false,
    "isThroughSmoke": false,
    "isBlindKill": false,
    "isNoScope": false,
    "isSuicide": false,
    "eventType": "kill",
    "mapNumber": 1,
    "roundNumber": 1,
    "eventHash": "54888e70154825a5bdee8a2da97435fa",
    "timestamp": "2026-02-25T15:02:26.270Z"
  },
  {
    "id": "d5915f63-c046-41a8-8bc4-203f1e349349",
    "matchId": "2390266",
    "logText": "kr1vda + maggent oopee",
    "killerName": "kr1vda",
    "victimName": "oopee",
    "assistName": "maggent",
    "weapon": "p250",
    "isHeadshot": true,
    "isWallbang": false,
    "isThroughSmoke": false,
    "isBlindKill": false,
    "isNoScope": false,
    "isSuicide": false,
    "eventType": "kill",
    "mapNumber": 1,
    "roundNumber": 1,
    "eventHash": "b0512ba3065c3baa306f6ba2129c01bc",
    "timestamp": "2026-02-25T15:02:29.694Z"
  },
  {
    "id": "54042631-927e-4343-9cf0-2a15140f0166",
    "matchId": "2390266",
    "logText": "maggent 8Juho8",
    "killerName": "maggent",
    "victimName": "8Juho8",
    "assistName": null,
    "weapon": "m4a1_silencer",
    "isHeadshot": true,
    "isWallbang": false,
    "isThroughSmoke": false,
    "isBlindKill": false,
    "isNoScope": false,
    "isSuicide": false,
    "eventType": "kill",
    "mapNumber": 1,
    "roundNumber": 1,
    "eventHash": "63ae69399db9fed5a135ec47d90f96a6",
    "timestamp": "2026-02-25T15:02:34.571Z"
  },
  {
    "id": "9d1bfa2c-b4e6-4708-8cc4-48cc5032786c",
    "matchId": "2390266",
    "logText": "maggent oopee",
    "killerName": "maggent",
    "victimName": "oopee",
    "assistName": null,
    "weapon": "m4a1_silencer",
    "isHeadshot": true,
    "isWallbang": false,
    "isThroughSmoke": false,
    "isBlindKill": false,
    "isNoScope": false,
    "isSuicide": false,
    "eventType": "kill",
    "mapNumber": 1,
    "roundNumber": 1,
    "eventHash": "821294f267a78ac390604cb82f397ed7",
    "timestamp": "2026-02-25T15:02:40.578Z"
  },
  {
    "id": "d52d0fc8-17f6-4ac6-a4de-abd2f01eb614",
    "matchId": "2390266",
    "logText": "kr1vda 8Juho8",
    "killerName": "kr1vda",
    "victimName": "8Juho8",
    "assistName": null,
    "weapon": "m4a1_silencer",
    "isHeadshot": true,
    "isWallbang": false,
    "isThroughSmoke": false,
    "isBlindKill": false,
    "isNoScope": false,
    "isSuicide": false,
    "eventType": "kill",
    "mapNumber": 1,
    "roundNumber": 1,
    "eventHash": "77667031e48c4d58ea2ca93f9472d464",
    "timestamp": "2026-02-25T15:02:59.217Z"
  },
  {
    "id": "0006329c-816e-4432-84a0-dd230ea29c05",
    "matchId": "2390266",
    "logText": "fakerealityy Myggis",
    "killerName": "fakerealityy",
    "victimName": "Myggis",
    "assistName": null,
    "weapon": "m4a1_silencer",
    "isHeadshot": true,
    "isWallbang": false,
    "isThroughSmoke": false,
    "isBlindKill": false,
    "isNoScope": false,
    "isSuicide": false,
    "eventType": "kill",
    "mapNumber": 1,
    "roundNumber": 1,
    "eventHash": "9dc93b9e63da02a5cc1b4cf11464e463",
    "timestamp": "2026-02-25T15:02:59.228Z"
  },
  {
    "id": "164b80ff-f59e-41c2-bd7b-832bf0ed99e3",
    "matchId": "2390266",
    "logText": "kr1vda 8Juho8",
    "killerName": "kr1vda",
    "victimName": "8Juho8",
    "assistName": null,
    "weapon": "m4a1_silencer",
    "isHeadshot": false,
    "isWallbang": false,
    "isThroughSmoke": false,
    "isBlindKill": false,
    "isNoScope": false,
    "isSuicide": false,
    "eventType": "kill",
    "mapNumber": 1,
    "roundNumber": 1,
    "eventHash": "0b7b130c5dfad99ca65216fcaf15097c",
    "timestamp": "2026-02-25T15:02:59.239Z"
  },
  {
    "id": "54ff8321-c67b-4ab9-90ea-7fcafe4bf65c",
    "matchId": "2390266",
    "logText": "8Juho8 kr1vda",
    "killerName": "8Juho8",
    "victimName": "kr1vda",
    "assistName": null,
    "weapon": "deagle",
    "isHeadshot": true,
    "isWallbang": false,
    "isThroughSmoke": false,
    "isBlindKill": false,
    "isNoScope": false,
    "isSuicide": false,
    "eventType": "kill",
    "mapNumber": 1,
    "roundNumber": 1,
    "eventHash": "65137b97a7014014d99fd7e1674534ed",
    "timestamp": "2026-02-25T15:03:04.711Z"
  },
  {
    "id": "ad2dd7c7-611a-41ab-b3eb-e7f5ab790c40",
    "matchId": "2390266",
    "logText": "fakerealityy 8Juho8",
    "killerName": "fakerealityy",
    "victimName": "8Juho8",
    "assistName": null,
    "weapon": "m4a1_silencer",
    "isHeadshot": false,
    "isWallbang": false,
    "isThroughSmoke": false,
    "isBlindKill": false,
    "isNoScope": false,
    "isSuicide": false,
    "eventType": "kill",
    "mapNumber": 1,
    "roundNumber": 1,
    "eventHash": "77b44823a29237aad3971292b316033d",
    "timestamp": "2026-02-25T15:03:14.860Z"
  },
  {
    "id": "3290acf7-43ca-44c3-8166-4cbe5eb74ec1",
    "matchId": "2390266",
    "logText": "oopee kr1vda",
    "killerName": "oopee",
    "victimName": "kr1vda",
    "assistName": null,
    "weapon": "awp",
    "isHeadshot": false,
    "isWallbang": false,
    "isThroughSmoke": false,
    "isBlindKill": false,
    "isNoScope": false,
    "isSuicide": false,
    "eventType": "kill",
    "mapNumber": 1,
    "roundNumber": 1,
    "eventHash": "d08949c59f58df635deec2b8687ea921",
    "timestamp": "2026-02-25T15:03:29.522Z"
  },
  {
    "id": "0be8fed0-d063-4f5a-8c64-5ca27803a0bc",
    "matchId": "2390266",
    "logText": "fakerealityy + maggent 8Juho8",
    "killerName": "fakerealityy",
    "victimName": "8Juho8",
    "assistName": "maggent",
    "weapon": "m4a1_silencer",
    "isHeadshot": false,
    "isWallbang": false,
    "isThroughSmoke": false,
    "isBlindKill": false,
    "isNoScope": false,
    "isSuicide": false,
    "eventType": "kill",
    "mapNumber": 1,
    "roundNumber": 1,
    "eventHash": "4491f005ce13d5e9d0e5c6a34afeb1ba",
    "timestamp": "2026-02-25T15:03:43.697Z"
  },
  {
    "id": "36ea75e3-008a-4c37-a2e9-9a15a26f635e",
    "matchId": "2390266",
    "logText": "kr1vda arvid",
    "killerName": "kr1vda",
    "victimName": "arvid",
    "assistName": null,
    "weapon": "m4a1_silencer",
    "isHeadshot": false,
    "isWallbang": false,
    "isThroughSmoke": false,
    "isBlindKill": false,
    "isNoScope": false,
    "isSuicide": false,
    "eventType": "kill",
    "mapNumber": 1,
    "roundNumber": 1,
    "eventHash": "521d1fd8f41c399fa59628408b922134",
    "timestamp": "2026-02-25T15:03:46.603Z"
  },
  {
    "id": "2f82a0db-829f-4168-8b82-f35c368a1bad",
    "matchId": "2390266",
    "logText": "kr1vda 8Juho8",
    "killerName": "kr1vda",
    "victimName": "8Juho8",
    "assistName": null,
    "weapon": "awp",
    "isHeadshot": false,
    "isWallbang": false,
    "isThroughSmoke": false,
    "isBlindKill": false,
    "isNoScope": false,
    "isSuicide": false,
    "eventType": "kill",
    "mapNumber": 1,
    "roundNumber": 1,
    "eventHash": "f5c83543bf57c4d101c6002c886c6df5",
    "timestamp": "2026-02-25T15:03:49.596Z"
  },
  {
    "id": "561a93ee-0b05-429e-bee7-b5647480d8ba",
    "matchId": "2390266",
    "logText": "fakerealityy arvid",
    "killerName": "fakerealityy",
    "victimName": "arvid",
    "assistName": null,
    "weapon": "m4a1_silencer",
    "isHeadshot": true,
    "isWallbang": false,
    "isThroughSmoke": false,
    "isBlindKill": false,
    "isNoScope": false,
    "isSuicide": false,
    "eventType": "kill",
    "mapNumber": 1,
    "roundNumber": 1,
    "eventHash": "c78d45b860f45bf35f44a288cddb801d",
    "timestamp": "2026-02-25T15:03:59.117Z"
  },
  {
    "id": "98091fee-ee63-4f69-9576-b04e0056e828",
    "matchId": "2390266",
    "logText": "kr1vda arvid",
    "killerName": "kr1vda",
    "victimName": "arvid",
    "assistName": null,
    "weapon": "awp",
    "isHeadshot": false,
    "isWallbang": false,
    "isThroughSmoke": false,
    "isBlindKill": false,
    "isNoScope": false,
    "isSuicide": false,
    "eventType": "kill",
    "mapNumber": 1,
    "roundNumber": 1,
    "eventHash": "75aa99392fd27af6e33bf61981548fb8",
    "timestamp": "2026-02-25T15:04:02.424Z"
  },
  {
    "id": "cfc66f36-ce83-4221-ad16-8b441a654f77",
    "matchId": "2390266",
    "logText": "arvid maggent",
    "killerName": "arvid",
    "victimName": "maggent",
    "assistName": null,
    "weapon": "ak47",
    "isHeadshot": true,
    "isWallbang": false,
    "isThroughSmoke": false,
    "isBlindKill": false,
    "isNoScope": false,
    "isSuicide": false,
    "eventType": "kill",
    "mapNumber": 1,
    "roundNumber": 1,
    "eventHash": "38343e07d1c83a71512d350825cf915d",
    "timestamp": "2026-02-25T15:04:02.434Z"
  },
  {
    "id": "7b0fe51e-985a-49f9-a41d-a780ad74dc7d",
    "matchId": "2390266",
    "logText": "arvid + oopee kr1vda",
    "killerName": "arvid",
    "victimName": "kr1vda",
    "assistName": "oopee",
    "weapon": "ak47",
    "isHeadshot": true,
    "isWallbang": false,
    "isThroughSmoke": false,
    "isBlindKill": false,
    "isNoScope": false,
    "isSuicide": false,
    "eventType": "kill",
    "mapNumber": 1,
    "roundNumber": 1,
    "eventHash": "d89e54a5ee5daad677c4aed99e2e2a33",
    "timestamp": "2026-02-25T15:04:07.951Z"
  },
  {
    "id": "88ccffca-3a6b-4858-a362-16ea456e45f7",
    "matchId": "2390266",
    "logText": "Myggis Tr0ublE",
    "killerName": "Myggis",
    "victimName": "Tr0ublE",
    "assistName": null,
    "weapon": "deagle",
    "isHeadshot": true,
    "isWallbang": false,
    "isThroughSmoke": false,
    "isBlindKill": false,
    "isNoScope": false,
    "isSuicide": false,
    "eventType": "kill",
    "mapNumber": 1,
    "roundNumber": 1,
    "eventHash": "2bd0f0d4b7036f3fd1ef2d332b8d3379",
    "timestamp": "2026-02-25T15:04:11.148Z"
  },
  {
    "id": "18a43863-c0e6-453c-9a95-2a8cb50558b0",
    "matchId": "2390266",
    "logText": "Myggis maggent",
    "killerName": "Myggis",
    "victimName": "maggent",
    "assistName": null,
    "weapon": "deagle",
    "isHeadshot": true,
    "isWallbang": false,
    "isThroughSmoke": false,
    "isBlindKill": false,
    "isNoScope": false,
    "isSuicide": false,
    "eventType": "kill",
    "mapNumber": 1,
    "roundNumber": 1,
    "eventHash": "df8b21de9f2684d18377b6ca8cc4d250",
    "timestamp": "2026-02-25T15:04:11.158Z"
  },
  {
    "id": "fbc4c470-3509-49d5-bc89-ece7a50035ec",
    "matchId": "2390266",
    "logText": "Myggis kr1vda",
    "killerName": "Myggis",
    "victimName": "kr1vda",
    "assistName": null,
    "weapon": "deagle",
    "isHeadshot": true,
    "isWallbang": false,
    "isThroughSmoke": false,
    "isBlindKill": false,
    "isNoScope": false,
    "isSuicide": false,
    "eventType": "kill",
    "mapNumber": 1,
    "roundNumber": 1,
    "eventHash": "7db84503e274aac76a54ccf24aa9f06b",
    "timestamp": "2026-02-25T15:04:11.168Z"
  },
  {
    "id": "76543a56-0c87-42df-bdd7-06b277c4dbd7",
    "matchId": "2390266",
    "logText": "arvid fakerealityy",
    "killerName": "arvid",
    "victimName": "fakerealityy",
    "assistName": null,
    "weapon": "ak47",
    "isHeadshot": false,
    "isWallbang": false,
    "isThroughSmoke": false,
    "isBlindKill": false,
    "isNoScope": false,
    "isSuicide": false,
    "eventType": "kill",
    "mapNumber": 1,
    "roundNumber": 1,
    "eventHash": "1f03299c5b5176d34f40b33e0efbe702",
    "timestamp": "2026-02-25T15:04:14.558Z"
  },
  {
    "id": "ae2cba72-a36d-4cbe-afbc-c1879616a121",
    "matchId": "2390266",
    "logText": "maggent arvid",
    "killerName": "maggent",
    "victimName": "arvid",
    "assistName": null,
    "weapon": "m4a1_silencer",
    "isHeadshot": true,
    "isWallbang": false,
    "isThroughSmoke": false,
    "isBlindKill": false,
    "isNoScope": false,
    "isSuicide": false,
    "eventType": "kill",
    "mapNumber": 1,
    "roundNumber": 1,
    "eventHash": "0127080d05fe3d55f01e5ce79f3b6419",
    "timestamp": "2026-02-25T15:04:25.782Z"
  },
  {
    "id": "0b1c06f6-292a-466a-a287-28925c38b36f",
    "matchId": "2390266",
    "logText": "fakerealityy Myggis",
    "killerName": "fakerealityy",
    "victimName": "Myggis",
    "assistName": null,
    "weapon": "m4a1",
    "isHeadshot": false,
    "isWallbang": false,
    "isThroughSmoke": false,
    "isBlindKill": false,
    "isNoScope": false,
    "isSuicide": false,
    "eventType": "kill",
    "mapNumber": 1,
    "roundNumber": 1,
    "eventHash": "fd3cefb7bb84e47e77f4b043cbef1acd",
    "timestamp": "2026-02-25T15:04:29.008Z"
  },
  {
    "id": "a88b1347-0b92-497f-bb5c-8408e6c0ef62",
    "matchId": "2390266",
    "logText": "kr1vda oopee",
    "killerName": "kr1vda",
    "victimName": "oopee",
    "assistName": null,
    "weapon": "m4a1_silencer",
    "isHeadshot": true,
    "isWallbang": false,
    "isThroughSmoke": false,
    "isBlindKill": false,
    "isNoScope": false,
    "isSuicide": false,
    "eventType": "kill",
    "mapNumber": 1,
    "roundNumber": 1,
    "eventHash": "62420479fdafb66dfad1f121f76af21e",
    "timestamp": "2026-02-25T15:04:29.019Z"
  },
  {
    "id": "a370fa10-67cf-4962-9eb8-e6b2282b5e61",
    "matchId": "2390266",
    "logText": "maggent 8Juho8",
    "killerName": "maggent",
    "victimName": "8Juho8",
    "assistName": null,
    "weapon": "fiveseven",
    "isHeadshot": true,
    "isWallbang": false,
    "isThroughSmoke": false,
    "isBlindKill": false,
    "isNoScope": false,
    "isSuicide": false,
    "eventType": "kill",
    "mapNumber": 1,
    "roundNumber": 1,
    "eventHash": "aa988d3c1c8333b2ce0411c97b38a69d",
    "timestamp": "2026-02-25T15:04:35.420Z"
  },
  {
    "id": "6788491f-2217-4fa7-8526-4d215614751a",
    "matchId": "2390266",
    "logText": "8Juho8 OWNER",
    "killerName": "8Juho8",
    "victimName": "OWNER",
    "assistName": null,
    "weapon": "ak47",
    "isHeadshot": true,
    "isWallbang": false,
    "isThroughSmoke": false,
    "isBlindKill": false,
    "isNoScope": false,
    "isSuicide": false,
    "eventType": "kill",
    "mapNumber": 1,
    "roundNumber": 1,
    "eventHash": "dfb2e4446ff0783ce37d897af9b53a69",
    "timestamp": "2026-02-25T15:04:35.430Z"
  },
  {
    "id": "210dcabc-6cff-4b52-862e-11add9f92346",
    "matchId": "2390266",
    "logText": "arvid kr1vda",
    "killerName": "arvid",
    "victimName": "kr1vda",
    "assistName": null,
    "weapon": "ak47",
    "isHeadshot": true,
    "isWallbang": false,
    "isThroughSmoke": false,
    "isBlindKill": false,
    "isNoScope": false,
    "isSuicide": false,
    "eventType": "kill",
    "mapNumber": 1,
    "roundNumber": 1,
    "eventHash": "b213ae5d18cb098d1ec3d3ff80d6e6a3",
    "timestamp": "2026-02-25T15:04:40.844Z"
  },
  {
    "id": "e179f4f4-065e-44b4-a8a8-56e4ad602a4c",
    "matchId": "2390266",
    "logText": "Tr0ublE oopee",
    "killerName": "Tr0ublE",
    "victimName": "oopee",
    "assistName": null,
    "weapon": "awp",
    "isHeadshot": false,
    "isWallbang": false,
    "isThroughSmoke": false,
    "isBlindKill": false,
    "isNoScope": false,
    "isSuicide": false,
    "eventType": "kill",
    "mapNumber": 1,
    "roundNumber": 1,
    "eventHash": "3075ce21691e75a5740093b878b82cd7",
    "timestamp": "2026-02-25T15:04:43.721Z"
  },
  {
    "id": "f51b4afe-1b07-4c03-9159-144940e43f36",
    "matchId": "2390266",
    "logText": "Tr0ublE 8Juho8",
    "killerName": "Tr0ublE",
    "victimName": "8Juho8",
    "assistName": null,
    "weapon": "awp",
    "isHeadshot": false,
    "isWallbang": false,
    "isThroughSmoke": false,
    "isBlindKill": false,
    "isNoScope": false,
    "isSuicide": false,
    "eventType": "kill",
    "mapNumber": 1,
    "roundNumber": 1,
    "eventHash": "51d0c7b05e6dd36d6ae379b9c7028b9c",
    "timestamp": "2026-02-25T15:04:46.718Z"
  },
  {
    "id": "113a4b53-14cf-4ca2-b992-15bbdb3cbd46",
    "matchId": "2390266",
    "logText": "Tr0ublE arvid",
    "killerName": "Tr0ublE",
    "victimName": "arvid",
    "assistName": null,
    "weapon": "awp",
    "isHeadshot": false,
    "isWallbang": false,
    "isThroughSmoke": false,
    "isBlindKill": false,
    "isNoScope": false,
    "isSuicide": false,
    "eventType": "kill",
    "mapNumber": 1,
    "roundNumber": 1,
    "eventHash": "62462d3f7a185d606128dce21842973e",
    "timestamp": "2026-02-25T15:04:52.596Z"
  },
  {
    "id": "500d373e-3f6f-4572-b965-eaba0bb122d0",
    "matchId": "2390266",
    "logText": "oopee Tr0ublE",
    "killerName": "oopee",
    "victimName": "Tr0ublE",
    "assistName": null,
    "weapon": "glock",
    "isHeadshot": true,
    "isWallbang": false,
    "isThroughSmoke": false,
    "isBlindKill": false,
    "isNoScope": false,
    "isSuicide": false,
    "eventType": "kill",
    "mapNumber": 1,
    "roundNumber": 1,
    "eventHash": "d0b71e4ae1d2642b145ddead464ffbd2",
    "timestamp": "2026-02-25T15:05:37.726Z"
  },
  {
    "id": "f91a4b56-fee9-4b3f-a661-4a9d4f99e651",
    "matchId": "2390266",
    "logText": "arvid OWNER",
    "killerName": "arvid",
    "victimName": "OWNER",
    "assistName": null,
    "weapon": "glock",
    "isHeadshot": true,
    "isWallbang": false,
    "isThroughSmoke": false,
    "isBlindKill": false,
    "isNoScope": false,
    "isSuicide": false,
    "eventType": "kill",
    "mapNumber": 1,
    "roundNumber": 1,
    "eventHash": "de1f217e8e8169f84bf2910d17280a51",
    "timestamp": "2026-02-25T15:05:46.885Z"
  },
  {
    "id": "b8a8f18d-6d29-4da8-9997-aed52d14c64e",
    "matchId": "2390266",
    "logText": "fakerealityy Myggis",
    "killerName": "fakerealityy",
    "victimName": "Myggis",
    "assistName": null,
    "weapon": "elite",
    "isHeadshot": true,
    "isWallbang": false,
    "isThroughSmoke": false,
    "isBlindKill": false,
    "isNoScope": false,
    "isSuicide": false,
    "eventType": "kill",
    "mapNumber": 1,
    "roundNumber": 1,
    "eventHash": "a6dc38926ead311156f9abb8d7e24920",
    "timestamp": "2026-02-25T15:05:49.774Z"
  },
  {
    "id": "2ca039a7-8765-480c-baf2-59777e84ceaf",
    "matchId": "2390266",
    "logText": "arvid planted the bomb on B (4on3)",
    "killerName": "arvid",
    "victimName": null,
    "assistName": null,
    "weapon": "bomb",
    "isHeadshot": false,
    "isWallbang": false,
    "isThroughSmoke": false,
    "isBlindKill": false,
    "isNoScope": false,
    "isSuicide": false,
    "eventType": "bomb_plant",
    "mapNumber": 1,
    "roundNumber": 1,
    "eventHash": "f4f253bff9b18cfbfbc9561d1970fa60",
    "timestamp": "2026-02-25T15:05:52.768Z"
  },
  {
    "id": "1ffc3000-feed-460c-a04b-43fe2dbd2ee7",
    "matchId": "2390266",
    "logText": "oopee maggent",
    "killerName": "oopee",
    "victimName": "maggent",
    "assistName": null,
    "weapon": "glock",
    "isHeadshot": true,
    "isWallbang": false,
    "isThroughSmoke": false,
    "isBlindKill": false,
    "isNoScope": false,
    "isSuicide": false,
    "eventType": "kill",
    "mapNumber": 1,
    "roundNumber": 1,
    "eventHash": "234e5f8347d1fe075f09c4f66546ab48",
    "timestamp": "2026-02-25T15:06:02.519Z"
  },
  {
    "id": "ccf286e9-bf9d-4911-b976-1a816192a1b7",
    "matchId": "2390266",
    "logText": "oopee kr1vda",
    "killerName": "oopee",
    "victimName": "kr1vda",
    "assistName": null,
    "weapon": "glock",
    "isHeadshot": true,
    "isWallbang": true,
    "isThroughSmoke": false,
    "isBlindKill": false,
    "isNoScope": false,
    "isSuicide": false,
    "eventType": "kill",
    "mapNumber": 1,
    "roundNumber": 1,
    "eventHash": "073c4a9e659777351ed814cdbe0b14c0",
    "timestamp": "2026-02-25T15:06:08.083Z"
  },
  {
    "id": "10d3eab3-dac3-45da-96af-41f0f0e76ce0",
    "matchId": "2390266",
    "logText": "melty + arvid fakerealityy",
    "killerName": "melty",
    "victimName": "fakerealityy",
    "assistName": "arvid",
    "weapon": "glock",
    "isHeadshot": false,
    "isWallbang": false,
    "isThroughSmoke": false,
    "isBlindKill": false,
    "isNoScope": false,
    "isSuicide": false,
    "eventType": "kill",
    "mapNumber": 1,
    "roundNumber": 1,
    "eventHash": "f53b6b2973a450e27b0c8a9ab1b4a770",
    "timestamp": "2026-02-25T15:06:10.599Z"
  },
  {
    "id": "e948af05-ac8f-4133-8b97-f3e0c0bb60b3",
    "matchId": "2390266",
    "logText": "arvid OWNER",
    "killerName": "arvid",
    "victimName": "OWNER",
    "assistName": null,
    "weapon": "ak47",
    "isHeadshot": false,
    "isWallbang": false,
    "isThroughSmoke": false,
    "isBlindKill": false,
    "isNoScope": false,
    "isSuicide": false,
    "eventType": "kill",
    "mapNumber": 1,
    "roundNumber": 1,
    "eventHash": "1623fbbf33d810d16b5b5e60a890f360",
    "timestamp": "2026-02-25T15:08:02.094Z"
  },
  {
    "id": "c27c04b4-3e7c-47f6-b929-5157126ce460",
    "matchId": "2390266",
    "logText": "kr1vda + OWNER arvid",
    "killerName": "kr1vda",
    "victimName": "arvid",
    "assistName": "OWNER",
    "weapon": "hegrenade",
    "isHeadshot": false,
    "isWallbang": false,
    "isThroughSmoke": false,
    "isBlindKill": false,
    "isNoScope": false,
    "isSuicide": false,
    "eventType": "kill",
    "mapNumber": 1,
    "roundNumber": 1,
    "eventHash": "7fbbf5276ca309423e7ef3fe1eabb9ae",
    "timestamp": "2026-02-25T15:08:07.549Z"
  },
  {
    "id": "8e1d438e-28b9-46f4-b16b-d85ba676c324",
    "matchId": "2390266",
    "logText": "arvid Tr0ublE",
    "killerName": "arvid",
    "victimName": "Tr0ublE",
    "assistName": null,
    "weapon": "ak47",
    "isHeadshot": false,
    "isWallbang": false,
    "isThroughSmoke": true,
    "isBlindKill": false,
    "isNoScope": false,
    "isSuicide": false,
    "eventType": "kill",
    "mapNumber": 1,
    "roundNumber": 1,
    "eventHash": "a75828c7e8523de1c1f000a57bcc1d55",
    "timestamp": "2026-02-25T15:08:07.948Z"
  },
  {
    "id": "d17ed87a-0154-44f2-bb4c-ac087caa65ed",
    "matchId": "2390266",
    "logText": "8Juho8 planted the bomb on B (4on3)",
    "killerName": "8Juho8",
    "victimName": null,
    "assistName": null,
    "weapon": "bomb",
    "isHeadshot": false,
    "isWallbang": false,
    "isThroughSmoke": false,
    "isBlindKill": false,
    "isNoScope": false,
    "isSuicide": false,
    "eventType": "bomb_plant",
    "mapNumber": 1,
    "roundNumber": 1,
    "eventHash": "40796776089edc6988041615ab620cfa",
    "timestamp": "2026-02-25T15:08:10.611Z"
  },
  {
    "id": "8e18f28b-3766-45b1-a836-cb5c0c14096d",
    "matchId": "2390266",
    "logText": "Myggis + melty fakerealityy",
    "killerName": "Myggis",
    "victimName": "fakerealityy",
    "assistName": "melty",
    "weapon": "mac10",
    "isHeadshot": true,
    "isWallbang": false,
    "isThroughSmoke": false,
    "isBlindKill": false,
    "isNoScope": false,
    "isSuicide": false,
    "eventType": "kill",
    "mapNumber": 1,
    "roundNumber": 1,
    "eventHash": "7adb42e3107a0949f9315345137d7a4b",
    "timestamp": "2026-02-25T15:08:35.915Z"
  },
  {
    "id": "abfce9ac-ac8c-43ab-b6ac-d5a5f2625986",
    "matchId": "2390266",
    "logText": "Round over - Winner: T (2 - 0) - Target bombed",
    "killerName": null,
    "victimName": null,
    "assistName": null,
    "weapon": null,
    "isHeadshot": false,
    "isWallbang": false,
    "isThroughSmoke": false,
    "isBlindKill": false,
    "isNoScope": false,
    "isSuicide": false,
    "eventType": "round_end",
    "mapNumber": 1,
    "roundNumber": 1,
    "eventHash": "5cacbeb9439a29761d7db7db03214a34",
    "timestamp": "2026-02-25T15:08:50.078Z"
  },
  {
    "id": "fae843d9-b8d2-4329-95dc-e164b7d0546b",
    "matchId": "2390266",
    "logText": "melty OWNER",
    "killerName": "melty",
    "victimName": "OWNER",
    "assistName": null,
    "weapon": "mac10",
    "isHeadshot": true,
    "isWallbang": false,
    "isThroughSmoke": false,
    "isBlindKill": false,
    "isNoScope": false,
    "isSuicide": false,
    "eventType": "kill",
    "mapNumber": 1,
    "roundNumber": 1,
    "eventHash": "c94ace572ef7770664cfa7011d3a0c2d",
    "timestamp": "2026-02-25T15:10:05.670Z"
  },
  {
    "id": "6fd8a806-deb2-4275-b396-43389b1d1947",
    "matchId": "2390266",
    "logText": "arvid maggent",
    "killerName": "arvid",
    "victimName": "maggent",
    "assistName": null,
    "weapon": "ak47",
    "isHeadshot": false,
    "isWallbang": false,
    "isThroughSmoke": false,
    "isBlindKill": false,
    "isNoScope": false,
    "isSuicide": false,
    "eventType": "kill",
    "mapNumber": 1,
    "roundNumber": 1,
    "eventHash": "8fb7150eedc1c9ff465d42d9bf8fde0b",
    "timestamp": "2026-02-25T15:10:08.621Z"
  },
  {
    "id": "43be6765-1543-4e6f-86e1-8ead269a4dce",
    "matchId": "2390266",
    "logText": "arvid Tr0ublE",
    "killerName": "arvid",
    "victimName": "Tr0ublE",
    "assistName": null,
    "weapon": "ak47",
    "isHeadshot": false,
    "isWallbang": false,
    "isThroughSmoke": false,
    "isBlindKill": false,
    "isNoScope": false,
    "isSuicide": false,
    "eventType": "kill",
    "mapNumber": 1,
    "roundNumber": 1,
    "eventHash": "41c84207e1cd54d9d0f1e44160c86f7c",
    "timestamp": "2026-02-25T15:10:08.630Z"
  },
  {
    "id": "9d7fa4fb-23b8-4cc1-8fd2-fc94bfed723d",
    "matchId": "2390266",
    "logText": "arvid + melty fakerealityy",
    "killerName": "arvid",
    "victimName": "fakerealityy",
    "assistName": "melty",
    "weapon": "ak47",
    "isHeadshot": false,
    "isWallbang": false,
    "isThroughSmoke": false,
    "isBlindKill": false,
    "isNoScope": false,
    "isSuicide": false,
    "eventType": "kill",
    "mapNumber": 1,
    "roundNumber": 1,
    "eventHash": "3fe29403f40fb65522cd173d438db41a",
    "timestamp": "2026-02-25T15:10:08.639Z"
  },
  {
    "id": "d029987e-1a96-4461-a83e-8d27d4b3e4f4",
    "matchId": "2390266",
    "logText": "maggent + fakerealityy melty",
    "killerName": "maggent",
    "victimName": "melty",
    "assistName": "fakerealityy",
    "weapon": "usp_silencer",
    "isHeadshot": true,
    "isWallbang": false,
    "isThroughSmoke": false,
    "isBlindKill": false,
    "isNoScope": false,
    "isSuicide": false,
    "eventType": "kill",
    "mapNumber": 1,
    "roundNumber": 1,
    "eventHash": "71d932d210759dbb8d8196f455f31eb2",
    "timestamp": "2026-02-25T15:10:08.648Z"
  },
  {
    "id": "d9fe65bd-d1ea-4aaf-a8a1-3a6a4b8288e1",
    "matchId": "2390266",
    "logText": "arvid planted the bomb on A (3on1)",
    "killerName": "arvid",
    "victimName": null,
    "assistName": null,
    "weapon": "bomb",
    "isHeadshot": false,
    "isWallbang": false,
    "isThroughSmoke": false,
    "isBlindKill": false,
    "isNoScope": false,
    "isSuicide": false,
    "eventType": "bomb_plant",
    "mapNumber": 1,
    "roundNumber": 1,
    "eventHash": "37a864e721eee3bd921abf5139ee8062",
    "timestamp": "2026-02-25T15:10:29.923Z"
  },
  {
    "id": "d026a473-5d7b-4790-a017-48c0fa8796da",
    "matchId": "2390266",
    "logText": "kr1vda oopee",
    "killerName": "kr1vda",
    "victimName": "oopee",
    "assistName": null,
    "weapon": "deagle",
    "isHeadshot": true,
    "isWallbang": false,
    "isThroughSmoke": false,
    "isBlindKill": false,
    "isNoScope": false,
    "isSuicide": false,
    "eventType": "kill",
    "mapNumber": 1,
    "roundNumber": 1,
    "eventHash": "4d6405c6812a725d92d112a9585a46ca",
    "timestamp": "2026-02-25T15:10:29.933Z"
  },
  {
    "id": "a533a749-5976-4c63-8787-e137b8bc33fd",
    "matchId": "2390266",
    "logText": "Round over - Winner: T (3 - 0) - Enemy eliminated",
    "killerName": null,
    "victimName": null,
    "assistName": null,
    "weapon": null,
    "isHeadshot": false,
    "isWallbang": false,
    "isThroughSmoke": false,
    "isBlindKill": false,
    "isNoScope": false,
    "isSuicide": false,
    "eventType": "round_end",
    "mapNumber": 1,
    "roundNumber": 1,
    "eventHash": "50e62534ef72393c8a5b8a737dcf9255",
    "timestamp": "2026-02-25T15:10:31.608Z"
  },
  {
    "id": "698a2861-1a34-49d8-bec7-01b15ad230e7",
    "matchId": "2390266",
    "logText": "Myggis kr1vda",
    "killerName": "Myggis",
    "victimName": "kr1vda",
    "assistName": null,
    "weapon": "ak47",
    "isHeadshot": false,
    "isWallbang": false,
    "isThroughSmoke": false,
    "isBlindKill": false,
    "isNoScope": false,
    "isSuicide": false,
    "eventType": "kill",
    "mapNumber": 1,
    "roundNumber": 1,
    "eventHash": "c09372198c783bd07929f645745e52cb",
    "timestamp": "2026-02-25T15:10:31.695Z"
  },
  {
    "id": "142c294f-cb3a-42a9-a395-c2aea8652c4d",
    "matchId": "2390266",
    "logText": "maggent oopee",
    "killerName": "maggent",
    "victimName": "oopee",
    "assistName": null,
    "weapon": "m4a1_silencer",
    "isHeadshot": false,
    "isWallbang": true,
    "isThroughSmoke": false,
    "isBlindKill": false,
    "isNoScope": false,
    "isSuicide": false,
    "eventType": "kill",
    "mapNumber": 1,
    "roundNumber": 1,
    "eventHash": "5df119efaeefaccb861b32e73c7afc4a",
    "timestamp": "2026-02-25T15:12:23.684Z"
  },
  {
    "id": "8a275e87-06b9-4ab2-bab8-6cae953e56a4",
    "matchId": "2390266",
    "logText": "maggent melty",
    "killerName": "maggent",
    "victimName": "melty",
    "assistName": null,
    "weapon": "m4a1_silencer",
    "isHeadshot": false,
    "isWallbang": false,
    "isThroughSmoke": false,
    "isBlindKill": false,
    "isNoScope": false,
    "isSuicide": false,
    "eventType": "kill",
    "mapNumber": 1,
    "roundNumber": 1,
    "eventHash": "f5a978bfaa96c39446f93ca71238de8a",
    "timestamp": "2026-02-25T15:12:23.693Z"
  },
  {
    "id": "431a5456-c4e6-4d24-b094-05fa5ef61200",
    "matchId": "2390266",
    "logText": "Myggis + oopee maggent",
    "killerName": "Myggis",
    "victimName": "maggent",
    "assistName": "oopee",
    "weapon": "ak47",
    "isHeadshot": false,
    "isWallbang": false,
    "isThroughSmoke": false,
    "isBlindKill": false,
    "isNoScope": false,
    "isSuicide": false,
    "eventType": "kill",
    "mapNumber": 1,
    "roundNumber": 1,
    "eventHash": "fc73cf54efb6b0c580f1ac212d69b95d",
    "timestamp": "2026-02-25T15:12:25.653Z"
  },
  {
    "id": "eed980ef-9c2b-48dd-acaf-f99c86fdeeef",
    "matchId": "2390266",
    "logText": "Myggis planted the bomb on A (2on3)",
    "killerName": "Myggis",
    "victimName": null,
    "assistName": null,
    "weapon": "bomb",
    "isHeadshot": false,
    "isWallbang": false,
    "isThroughSmoke": false,
    "isBlindKill": false,
    "isNoScope": false,
    "isSuicide": false,
    "eventType": "bomb_plant",
    "mapNumber": 1,
    "roundNumber": 1,
    "eventHash": "4b7c9ff9d86b445fab6d632e3424aee1",
    "timestamp": "2026-02-25T15:12:37.668Z"
  },
  {
    "id": "35a6233e-9fa8-4a86-964e-86044a9ece8e",
    "matchId": "2390266",
    "logText": "Myggis OWNER",
    "killerName": "Myggis",
    "victimName": "OWNER",
    "assistName": null,
    "weapon": "awp",
    "isHeadshot": false,
    "isWallbang": false,
    "isThroughSmoke": false,
    "isBlindKill": false,
    "isNoScope": false,
    "isSuicide": false,
    "eventType": "kill",
    "mapNumber": 1,
    "roundNumber": 1,
    "eventHash": "2f17655bf97395394a5c40305bedaf88",
    "timestamp": "2026-02-25T15:12:56.924Z"
  },
  {
    "id": "ef685b5d-67d8-4917-8954-e808bc222dd2",
    "matchId": "2390266",
    "logText": "kr1vda + Tr0ublE Myggis",
    "killerName": "kr1vda",
    "victimName": "Myggis",
    "assistName": "Tr0ublE",
    "weapon": "m4a1_silencer",
    "isHeadshot": false,
    "isWallbang": false,
    "isThroughSmoke": false,
    "isBlindKill": false,
    "isNoScope": false,
    "isSuicide": false,
    "eventType": "kill",
    "mapNumber": 1,
    "roundNumber": 1,
    "eventHash": "6e79a27231a6ab007f2c8d28b0b516e0",
    "timestamp": "2026-02-25T15:13:03.829Z"
  },
  {
    "id": "ef629e24-3252-4fc7-b86f-b28c731ba60b",
    "matchId": "2390266",
    "logText": "Round over - Winner: CT (3 - 1) - Bomb defused",
    "killerName": null,
    "victimName": null,
    "assistName": null,
    "weapon": null,
    "isHeadshot": false,
    "isWallbang": false,
    "isThroughSmoke": false,
    "isBlindKill": false,
    "isNoScope": false,
    "isSuicide": false,
    "eventType": "round_end",
    "mapNumber": 1,
    "roundNumber": 1,
    "eventHash": "01672e6a3948b89bded627da6b45ad65",
    "timestamp": "2026-02-25T15:13:07.626Z"
  },
  {
    "id": "25069883-42b7-4a02-854f-6902a5530e69",
    "matchId": "2390266",
    "logText": "Myggis + 8Juho8 fakerealityy",
    "killerName": "Myggis",
    "victimName": "fakerealityy",
    "assistName": "8Juho8",
    "weapon": "ak47",
    "isHeadshot": true,
    "isWallbang": false,
    "isThroughSmoke": false,
    "isBlindKill": false,
    "isNoScope": false,
    "isSuicide": false,
    "eventType": "kill",
    "mapNumber": 1,
    "roundNumber": 1,
    "eventHash": "6417bdf6564a3b22fced91a6a622eba3",
    "timestamp": "2026-02-25T15:13:44.090Z"
  },
  {
    "id": "2b2b7eb4-e924-4a3f-9a36-4a69a8da6727",
    "matchId": "2390266",
    "logText": "Myggis maggent",
    "killerName": "Myggis",
    "victimName": "maggent",
    "assistName": null,
    "weapon": "ak47",
    "isHeadshot": true,
    "isWallbang": false,
    "isThroughSmoke": true,
    "isBlindKill": false,
    "isNoScope": false,
    "isSuicide": false,
    "eventType": "kill",
    "mapNumber": 1,
    "roundNumber": 1,
    "eventHash": "590b7c5d69524fdbaf9cbb99a149658e",
    "timestamp": "2026-02-25T15:13:49.270Z"
  },
  {
    "id": "85adb51d-bff0-49f2-9b6a-9c04317759dd",
    "matchId": "2390266",
    "logText": "Myggis Tr0ublE",
    "killerName": "Myggis",
    "victimName": "Tr0ublE",
    "assistName": null,
    "weapon": "ak47",
    "isHeadshot": true,
    "isWallbang": false,
    "isThroughSmoke": false,
    "isBlindKill": false,
    "isNoScope": false,
    "isSuicide": false,
    "eventType": "kill",
    "mapNumber": 1,
    "roundNumber": 1,
    "eventHash": "c653a5f8609e44ed46091e2cffb3cfab",
    "timestamp": "2026-02-25T15:13:55.531Z"
  },
  {
    "id": "8d36350d-b575-406e-8080-d851752e1040",
    "matchId": "2390266",
    "logText": "OWNER oopee",
    "killerName": "OWNER",
    "victimName": "oopee",
    "assistName": null,
    "weapon": "m4a1_silencer",
    "isHeadshot": false,
    "isWallbang": true,
    "isThroughSmoke": true,
    "isBlindKill": false,
    "isNoScope": false,
    "isSuicide": false,
    "eventType": "kill",
    "mapNumber": 1,
    "roundNumber": 1,
    "eventHash": "f985082b179fbbaefcf0c12a88ab09fb",
    "timestamp": "2026-02-25T15:14:05.396Z"
  },
  {
    "id": "e3ff7446-0537-4c9a-a90d-aa8f9bd1bba7",
    "matchId": "2390266",
    "logText": "melty planted the bomb on A (4on2)",
    "killerName": "melty",
    "victimName": null,
    "assistName": null,
    "weapon": "bomb",
    "isHeadshot": false,
    "isWallbang": false,
    "isThroughSmoke": false,
    "isBlindKill": false,
    "isNoScope": false,
    "isSuicide": false,
    "eventType": "bomb_plant",
    "mapNumber": 1,
    "roundNumber": 1,
    "eventHash": "1594d5597d2b62ee6eb145320dfe1145",
    "timestamp": "2026-02-25T15:14:21.567Z"
  },
  {
    "id": "07bf6385-238b-4d53-85a5-d726b59a0ff3",
    "matchId": "2390266",
    "logText": "Round over - Winner: T (4 - 1) - Target bombed",
    "killerName": null,
    "victimName": null,
    "assistName": null,
    "weapon": null,
    "isHeadshot": false,
    "isWallbang": false,
    "isThroughSmoke": false,
    "isBlindKill": false,
    "isNoScope": false,
    "isSuicide": false,
    "eventType": "round_end",
    "mapNumber": 1,
    "roundNumber": 1,
    "eventHash": "87597dd8b861d6495e18f61298804062",
    "timestamp": "2026-02-25T15:15:12.035Z"
  },
  {
    "id": "0625fd67-0008-4e5c-a8b5-21d154d74c10",
    "matchId": "2390266",
    "logText": "Round over - Winner: T (5 - 2) - Enemy eliminated",
    "killerName": null,
    "victimName": null,
    "assistName": null,
    "weapon": null,
    "isHeadshot": false,
    "isWallbang": false,
    "isThroughSmoke": false,
    "isBlindKill": false,
    "isNoScope": false,
    "isSuicide": false,
    "eventType": "round_end",
    "mapNumber": 1,
    "roundNumber": 1,
    "eventHash": "6339ef814e8ed0c8c731eb050443846a",
    "timestamp": "2026-02-25T15:19:40.793Z"
  },
  {
    "id": "311d42c8-21f4-4a19-9f8e-ef2a86b43f5f",
    "matchId": "2390266",
    "logText": "melty maggent",
    "killerName": "melty",
    "victimName": "maggent",
    "assistName": null,
    "weapon": "awp",
    "isHeadshot": false,
    "isWallbang": false,
    "isThroughSmoke": false,
    "isBlindKill": false,
    "isNoScope": false,
    "isSuicide": false,
    "eventType": "kill",
    "mapNumber": 1,
    "roundNumber": 1,
    "eventHash": "dc7ede2166a5c3742372d30a960a1d09",
    "timestamp": "2026-02-25T15:19:40.803Z"
  },
  {
    "id": "45972db7-0994-4e5a-b7db-1dd54e40e2ce",
    "matchId": "2390266",
    "logText": "melty Tr0ublE",
    "killerName": "melty",
    "victimName": "Tr0ublE",
    "assistName": null,
    "weapon": "glock",
    "isHeadshot": false,
    "isWallbang": false,
    "isThroughSmoke": false,
    "isBlindKill": false,
    "isNoScope": false,
    "isSuicide": false,
    "eventType": "kill",
    "mapNumber": 1,
    "roundNumber": 1,
    "eventHash": "6ea06bf204ad16a07da62d43681e88f8",
    "timestamp": "2026-02-25T15:19:40.813Z"
  },
  {
    "id": "4cfd8dc5-5f9a-4bdc-8815-3563d0106110",
    "matchId": "2390266",
    "logText": "melty + oopee kr1vda",
    "killerName": "melty",
    "victimName": "kr1vda",
    "assistName": "oopee",
    "weapon": "glock",
    "isHeadshot": false,
    "isWallbang": false,
    "isThroughSmoke": false,
    "isBlindKill": false,
    "isNoScope": false,
    "isSuicide": false,
    "eventType": "kill",
    "mapNumber": 1,
    "roundNumber": 1,
    "eventHash": "cd5386aa27242d4aa768411d827074c5",
    "timestamp": "2026-02-25T15:19:40.821Z"
  },
  {
    "id": "3947c951-9dcc-4dde-9c4d-9f1d798720fb",
    "matchId": "2390266",
    "logText": "Tr0ublE + kr1vda oopee",
    "killerName": "Tr0ublE",
    "victimName": "oopee",
    "assistName": "kr1vda",
    "weapon": "m4a1_silencer",
    "isHeadshot": false,
    "isWallbang": false,
    "isThroughSmoke": false,
    "isBlindKill": false,
    "isNoScope": false,
    "isSuicide": false,
    "eventType": "kill",
    "mapNumber": 1,
    "roundNumber": 1,
    "eventHash": "e8aee6f6a38a06cbd2016ca6862d4782",
    "timestamp": "2026-02-25T15:19:40.830Z"
  },
  {
    "id": "175a5fb6-80b1-48ac-a25f-1aa107928d81",
    "matchId": "2390266",
    "logText": "oopee + arvid OWNER",
    "killerName": "oopee",
    "victimName": "OWNER",
    "assistName": "arvid",
    "weapon": "ak47",
    "isHeadshot": true,
    "isWallbang": false,
    "isThroughSmoke": false,
    "isBlindKill": false,
    "isNoScope": false,
    "isSuicide": false,
    "eventType": "kill",
    "mapNumber": 1,
    "roundNumber": 1,
    "eventHash": "8c2abf3cf5fc6c9af086a4c01092f184",
    "timestamp": "2026-02-25T15:19:40.840Z"
  },
  {
    "id": "12a9f6d7-833f-4456-8065-5f1ad7620aae",
    "matchId": "2390266",
    "logText": "OWNER arvid",
    "killerName": "OWNER",
    "victimName": "arvid",
    "assistName": null,
    "weapon": "m4a1_silencer",
    "isHeadshot": false,
    "isWallbang": false,
    "isThroughSmoke": false,
    "isBlindKill": false,
    "isNoScope": false,
    "isSuicide": false,
    "eventType": "kill",
    "mapNumber": 1,
    "roundNumber": 1,
    "eventHash": "b612b8b2a19ba05a88dd697ee4ecf348",
    "timestamp": "2026-02-25T15:19:40.849Z"
  },
  {
    "id": "fd556b40-056d-4c04-9a13-57425504d8b0",
    "matchId": "2390266",
    "logText": "maggent + fakerealityy 8Juho8",
    "killerName": "maggent",
    "victimName": "8Juho8",
    "assistName": "fakerealityy",
    "weapon": "hegrenade",
    "isHeadshot": false,
    "isWallbang": false,
    "isThroughSmoke": false,
    "isBlindKill": false,
    "isNoScope": false,
    "isSuicide": false,
    "eventType": "kill",
    "mapNumber": 1,
    "roundNumber": 1,
    "eventHash": "9c3195adce89e32ed5b888aa6a5be4e3",
    "timestamp": "2026-02-25T15:19:40.858Z"
  },
  {
    "id": "2b8b1db2-1d5d-478d-a78e-6e5fcf1a2cc7",
    "matchId": "2390266",
    "logText": "melty + 8Juho8 maggent",
    "killerName": "melty",
    "victimName": "maggent",
    "assistName": "8Juho8",
    "weapon": "awp",
    "isHeadshot": false,
    "isWallbang": false,
    "isThroughSmoke": false,
    "isBlindKill": false,
    "isNoScope": false,
    "isSuicide": false,
    "eventType": "kill",
    "mapNumber": 1,
    "roundNumber": 1,
    "eventHash": "05077220a6c0eb554c38263d52953c53",
    "timestamp": "2026-02-25T15:19:40.868Z"
  },
  {
    "id": "503da42c-61d7-403c-b0c4-440f8907ecb2",
    "matchId": "2390266",
    "logText": "Round over - Winner: CT (4 - 2) - Target saved",
    "killerName": null,
    "victimName": null,
    "assistName": null,
    "weapon": null,
    "isHeadshot": false,
    "isWallbang": false,
    "isThroughSmoke": false,
    "isBlindKill": false,
    "isNoScope": false,
    "isSuicide": false,
    "eventType": "round_end",
    "mapNumber": 1,
    "roundNumber": 1,
    "eventHash": "abc7bdde3185e25c4b84161e45a903a0",
    "timestamp": "2026-02-25T15:19:40.877Z"
  },
  {
    "id": "cfffee64-2bbf-4742-9351-fe5e3c265264",
    "matchId": "2390266",
    "logText": "Tr0ublE Myggis",
    "killerName": "Tr0ublE",
    "victimName": "Myggis",
    "assistName": null,
    "weapon": "awp",
    "isHeadshot": false,
    "isWallbang": false,
    "isThroughSmoke": false,
    "isBlindKill": false,
    "isNoScope": false,
    "isSuicide": false,
    "eventType": "kill",
    "mapNumber": 1,
    "roundNumber": 1,
    "eventHash": "5609293f27a624a2f6dad00862a33df5",
    "timestamp": "2026-02-25T15:26:44.483Z"
  },
  {
    "id": "27d8ae36-9ca4-4c56-bced-e78429c92409",
    "matchId": "2390266",
    "logText": "Round over - Winner: T (8 - 3) - Enemy eliminated",
    "killerName": null,
    "victimName": null,
    "assistName": null,
    "weapon": null,
    "isHeadshot": false,
    "isWallbang": false,
    "isThroughSmoke": false,
    "isBlindKill": false,
    "isNoScope": false,
    "isSuicide": false,
    "eventType": "round_end",
    "mapNumber": 1,
    "roundNumber": 11,
    "eventHash": "9ee4fc2ff8ea9461cc0d04f8d3292907",
    "timestamp": "2026-02-25T15:26:44.501Z"
  },
  {
    "id": "183f0ec7-8db3-45af-b6d4-5694b67f89d7",
    "matchId": "2390266",
    "logText": "arvid + Myggis Tr0ublE",
    "killerName": "arvid",
    "victimName": "Tr0ublE",
    "assistName": "Myggis",
    "weapon": "ak47",
    "isHeadshot": true,
    "isWallbang": false,
    "isThroughSmoke": false,
    "isBlindKill": false,
    "isNoScope": false,
    "isSuicide": false,
    "eventType": "kill",
    "mapNumber": 1,
    "roundNumber": 11,
    "eventHash": "19877650e68852ab46abfab24f5a0b1d",
    "timestamp": "2026-02-25T15:26:44.511Z"
  },
  {
    "id": "eec60554-7e9d-4f24-abc2-f313f671e8f8",
    "matchId": "2390266",
    "logText": "arvid maggent",
    "killerName": "arvid",
    "victimName": "maggent",
    "assistName": null,
    "weapon": "ak47",
    "isHeadshot": false,
    "isWallbang": true,
    "isThroughSmoke": false,
    "isBlindKill": false,
    "isNoScope": false,
    "isSuicide": false,
    "eventType": "kill",
    "mapNumber": 1,
    "roundNumber": 11,
    "eventHash": "9c5667132b69e5dce32af870966ded2f",
    "timestamp": "2026-02-25T15:26:44.520Z"
  },
  {
    "id": "78aba06a-a8c9-44a4-8cb5-c10448235cd3",
    "matchId": "2390266",
    "logText": "melty kr1vda",
    "killerName": "melty",
    "victimName": "kr1vda",
    "assistName": null,
    "weapon": "awp",
    "isHeadshot": false,
    "isWallbang": false,
    "isThroughSmoke": false,
    "isBlindKill": false,
    "isNoScope": false,
    "isSuicide": false,
    "eventType": "kill",
    "mapNumber": 1,
    "roundNumber": 11,
    "eventHash": "24e81ce49eca0ae4f7be9a4901183cd6",
    "timestamp": "2026-02-25T15:26:44.532Z"
  },
  {
    "id": "7e291a65-7555-4255-a442-a75a113f1238",
    "matchId": "2390266",
    "logText": "oopee OWNER",
    "killerName": "oopee",
    "victimName": "OWNER",
    "assistName": null,
    "weapon": "ak47",
    "isHeadshot": false,
    "isWallbang": false,
    "isThroughSmoke": false,
    "isBlindKill": false,
    "isNoScope": false,
    "isSuicide": false,
    "eventType": "kill",
    "mapNumber": 1,
    "roundNumber": 11,
    "eventHash": "f86889f56d05c5d226ebcb03b958e233",
    "timestamp": "2026-02-25T15:26:44.542Z"
  },
  {
    "id": "81c2e2f2-ad5e-4063-9e61-dffaf0bddd4a",
    "matchId": "2390266",
    "logText": "arvid + oopee fakerealityy",
    "killerName": "arvid",
    "victimName": "fakerealityy",
    "assistName": "oopee",
    "weapon": "ak47",
    "isHeadshot": true,
    "isWallbang": false,
    "isThroughSmoke": false,
    "isBlindKill": false,
    "isNoScope": false,
    "isSuicide": false,
    "eventType": "kill",
    "mapNumber": 1,
    "roundNumber": 11,
    "eventHash": "998f1253122d6be8323e9e49cfdaf379",
    "timestamp": "2026-02-25T15:26:44.550Z"
  },
  {
    "id": "858a9081-cd93-4e70-afcb-750ca4a15538",
    "matchId": "2390266",
    "logText": "Round started",
    "killerName": null,
    "victimName": null,
    "assistName": null,
    "weapon": null,
    "isHeadshot": false,
    "isWallbang": false,
    "isThroughSmoke": false,
    "isBlindKill": false,
    "isNoScope": false,
    "isSuicide": false,
    "eventType": "round_start",
    "mapNumber": 1,
    "roundNumber": 11,
    "eventHash": "570c95e9183dccc0886a1e2b5cb2bde2",
    "timestamp": "2026-02-25T15:26:44.560Z"
  },
  {
    "id": "7e129f90-9dd2-41d9-a23d-55fb4bb8bc80",
    "matchId": "2390266",
    "logText": "Round over - Winner: T (7 - 3) - Target bombed",
    "killerName": null,
    "victimName": null,
    "assistName": null,
    "weapon": null,
    "isHeadshot": false,
    "isWallbang": false,
    "isThroughSmoke": false,
    "isBlindKill": false,
    "isNoScope": false,
    "isSuicide": false,
    "eventType": "round_end",
    "mapNumber": 1,
    "roundNumber": 10,
    "eventHash": "c8cc7452317fbbe0026e1358ad34a3db",
    "timestamp": "2026-02-25T15:26:44.571Z"
  },
  {
    "id": "a6d916ae-902b-422a-a0f0-cef3dd7fe28e",
    "matchId": "2390266",
    "logText": "melty planted the bomb on B (5on2)",
    "killerName": "melty",
    "victimName": null,
    "assistName": null,
    "weapon": "bomb",
    "isHeadshot": false,
    "isWallbang": false,
    "isThroughSmoke": false,
    "isBlindKill": false,
    "isNoScope": false,
    "isSuicide": false,
    "eventType": "bomb_plant",
    "mapNumber": 1,
    "roundNumber": 10,
    "eventHash": "296c9c1eff188862291f28cdbb38765a",
    "timestamp": "2026-02-25T15:26:44.586Z"
  },
  {
    "id": "8087729f-dcf0-467d-af42-ee8ba5b34270",
    "matchId": "2390266",
    "logText": "oopee OWNER",
    "killerName": "oopee",
    "victimName": "OWNER",
    "assistName": null,
    "weapon": "mac10",
    "isHeadshot": true,
    "isWallbang": false,
    "isThroughSmoke": false,
    "isBlindKill": false,
    "isNoScope": false,
    "isSuicide": false,
    "eventType": "kill",
    "mapNumber": 1,
    "roundNumber": 10,
    "eventHash": "18c98df7b655a7eb9a21f20e64bded3b",
    "timestamp": "2026-02-25T15:26:44.599Z"
  },
  {
    "id": "7d896d92-ae92-48b3-a5b8-fa80d8c9d190",
    "matchId": "2390266",
    "logText": "Myggis + 8Juho8 + arvidmaggent",
    "killerName": "Myggis",
    "victimName": "maggent",
    "assistName": "8Juho8",
    "weapon": "mac10",
    "isHeadshot": false,
    "isWallbang": false,
    "isThroughSmoke": false,
    "isBlindKill": true,
    "isNoScope": false,
    "isSuicide": false,
    "eventType": "kill",
    "mapNumber": 1,
    "roundNumber": 10,
    "eventHash": "727b1f44953944928ddaa48333bf99d3",
    "timestamp": "2026-02-25T15:26:44.611Z"
  },
  {
    "id": "0b505754-856a-4441-810e-5652650ccc66",
    "matchId": "2390266",
    "logText": "Myggis + 8Juho8 + meltyfakerealityy",
    "killerName": "Myggis",
    "victimName": "fakerealityy",
    "assistName": "8Juho8",
    "weapon": "mac10",
    "isHeadshot": false,
    "isWallbang": false,
    "isThroughSmoke": false,
    "isBlindKill": true,
    "isNoScope": false,
    "isSuicide": false,
    "eventType": "kill",
    "mapNumber": 1,
    "roundNumber": 10,
    "eventHash": "a6c708d05db9afc597fdd9b4e32c57d0",
    "timestamp": "2026-02-25T15:26:44.623Z"
  },
  {
    "id": "be62b7bd-0a85-46f3-b399-3f623be1fee0",
    "matchId": "2390266",
    "logText": "oopee kr1vda",
    "killerName": "oopee",
    "victimName": "kr1vda",
    "assistName": null,
    "weapon": "ak47",
    "isHeadshot": false,
    "isWallbang": false,
    "isThroughSmoke": false,
    "isBlindKill": false,
    "isNoScope": false,
    "isSuicide": false,
    "eventType": "kill",
    "mapNumber": 1,
    "roundNumber": 1,
    "eventHash": "ce46a4c32f6f76b5417ae8c9347ffc34",
    "timestamp": "2026-02-25T15:26:50.487Z"
  },
  {
    "id": "e9b74bba-d58a-417d-877f-0c58ddb59199",
    "matchId": "2390266",
    "logText": "oopee OWNER",
    "killerName": "oopee",
    "victimName": "OWNER",
    "assistName": null,
    "weapon": "ak47",
    "isHeadshot": true,
    "isWallbang": false,
    "isThroughSmoke": false,
    "isBlindKill": false,
    "isNoScope": false,
    "isSuicide": false,
    "eventType": "kill",
    "mapNumber": 1,
    "roundNumber": 1,
    "eventHash": "5e4f58c0d86fd4d54b3bfb006bac7b7c",
    "timestamp": "2026-02-25T15:26:53.497Z"
  },
  {
    "id": "dc9cf8ca-928d-4f86-8ac0-24fa4c6a58dd",
    "matchId": "2390266",
    "logText": "melty planted the bomb on B (4on3)",
    "killerName": "melty",
    "victimName": null,
    "assistName": null,
    "weapon": "bomb",
    "isHeadshot": false,
    "isWallbang": false,
    "isThroughSmoke": false,
    "isBlindKill": false,
    "isNoScope": false,
    "isSuicide": false,
    "eventType": "bomb_plant",
    "mapNumber": 1,
    "roundNumber": 1,
    "eventHash": "539d9d9d5ac806461371ca1b5707244c",
    "timestamp": "2026-02-25T15:26:59.509Z"
  },
  {
    "id": "399ed895-2d9a-4838-ad97-65f67d5b4c48",
    "matchId": "2390266",
    "logText": "oopee maggent",
    "killerName": "oopee",
    "victimName": "maggent",
    "assistName": null,
    "weapon": "ak47",
    "isHeadshot": true,
    "isWallbang": false,
    "isThroughSmoke": false,
    "isBlindKill": false,
    "isNoScope": false,
    "isSuicide": false,
    "eventType": "kill",
    "mapNumber": 1,
    "roundNumber": 1,
    "eventHash": "fa9b24db911a6617661950b76311331d",
    "timestamp": "2026-02-25T15:27:02.509Z"
  },
  {
    "id": "ea1a2e50-cae2-4fbe-be31-7884875000a2",
    "matchId": "2390266",
    "logText": "fakerealityy + OWNER oopee",
    "killerName": "fakerealityy",
    "victimName": "oopee",
    "assistName": "OWNER",
    "weapon": "m4a1_silencer",
    "isHeadshot": true,
    "isWallbang": false,
    "isThroughSmoke": false,
    "isBlindKill": false,
    "isNoScope": false,
    "isSuicide": false,
    "eventType": "kill",
    "mapNumber": 1,
    "roundNumber": 1,
    "eventHash": "b24ec20dff1f572677e711182e29c1eb",
    "timestamp": "2026-02-25T15:27:11.533Z"
  },
  {
    "id": "94fdfe83-993b-4b74-bc33-4207900f8fbe",
    "matchId": "2390266",
    "logText": "fakerealityy + maggent melty",
    "killerName": "fakerealityy",
    "victimName": "melty",
    "assistName": "maggent",
    "weapon": "hegrenade",
    "isHeadshot": false,
    "isWallbang": false,
    "isThroughSmoke": false,
    "isBlindKill": false,
    "isNoScope": false,
    "isSuicide": false,
    "eventType": "kill",
    "mapNumber": 1,
    "roundNumber": 1,
    "eventHash": "f03218ec92bfb68b8a6ec29dcaa1ec17",
    "timestamp": "2026-02-25T15:27:20.539Z"
  },
  {
    "id": "c0e5fc3b-5422-46f3-b120-3eec77901f43",
    "matchId": "2390266",
    "logText": "fakerealityy arvid",
    "killerName": "fakerealityy",
    "victimName": "arvid",
    "assistName": null,
    "weapon": "m4a1_silencer",
    "isHeadshot": true,
    "isWallbang": false,
    "isThroughSmoke": false,
    "isBlindKill": false,
    "isNoScope": false,
    "isSuicide": false,
    "eventType": "kill",
    "mapNumber": 1,
    "roundNumber": 1,
    "eventHash": "7cf6c12192cd414d4d2a7ddef41c9bd2",
    "timestamp": "2026-02-25T15:27:20.559Z"
  },
  {
    "id": "1563db0d-7245-41c6-9edd-ec0b1d13923f",
    "matchId": "2390266",
    "logText": "8Juho8 Tr0ublE",
    "killerName": "8Juho8",
    "victimName": "Tr0ublE",
    "assistName": null,
    "weapon": "ak47",
    "isHeadshot": false,
    "isWallbang": false,
    "isThroughSmoke": false,
    "isBlindKill": false,
    "isNoScope": false,
    "isSuicide": false,
    "eventType": "kill",
    "mapNumber": 1,
    "roundNumber": 1,
    "eventHash": "e31748e1cade870e50c51f7dfb5bc1d9",
    "timestamp": "2026-02-25T15:27:26.554Z"
  },
  {
    "id": "c0150595-246f-440d-876b-82b7b3d104ce",
    "matchId": "2390266",
    "logText": "fakerealityy 8Juho8",
    "killerName": "fakerealityy",
    "victimName": "8Juho8",
    "assistName": null,
    "weapon": "m4a1_silencer",
    "isHeadshot": false,
    "isWallbang": false,
    "isThroughSmoke": false,
    "isBlindKill": false,
    "isNoScope": false,
    "isSuicide": false,
    "eventType": "kill",
    "mapNumber": 1,
    "roundNumber": 1,
    "eventHash": "d0976bf04d731e80c0ee7e7ef5e4dce4",
    "timestamp": "2026-02-25T15:27:29.556Z"
  },
  {
    "id": "318fe637-446e-4bf7-aab2-cc65b418f2a1",
    "matchId": "2390266",
    "logText": "fakerealityy committed suicide",
    "killerName": "fakerealityy",
    "victimName": "fakerealityy",
    "assistName": null,
    "weapon": null,
    "isHeadshot": false,
    "isWallbang": false,
    "isThroughSmoke": false,
    "isBlindKill": false,
    "isNoScope": false,
    "isSuicide": true,
    "eventType": "suicide",
    "mapNumber": 1,
    "roundNumber": 1,
    "eventHash": "e1fb73abb98d53534553e38733030f3e",
    "timestamp": "2026-02-25T15:27:38.590Z"
  },
  {
    "id": "6c9081c7-0954-4fdf-9d8a-86d7d85a7db6",
    "matchId": "2390266",
    "logText": "Round over - Winner: T (9 - 3) - Target bombed",
    "killerName": null,
    "victimName": null,
    "assistName": null,
    "weapon": null,
    "isHeadshot": false,
    "isWallbang": false,
    "isThroughSmoke": false,
    "isBlindKill": false,
    "isNoScope": false,
    "isSuicide": false,
    "eventType": "round_end",
    "mapNumber": 1,
    "roundNumber": 12,
    "eventHash": "e91d372eae0fee1ef01b190bfa567247",
    "timestamp": "2026-02-25T15:27:38.601Z"
  },
  {
    "id": "c311c9ad-298f-4cb0-9475-d3f28b8f1002",
    "matchId": "2390266",
    "logText": "fakerealityy 8Juho8",
    "killerName": "fakerealityy",
    "victimName": "8Juho8",
    "assistName": null,
    "weapon": "m4a1_silencer",
    "isHeadshot": false,
    "isWallbang": false,
    "isThroughSmoke": false,
    "isBlindKill": false,
    "isNoScope": false,
    "isSuicide": false,
    "eventType": "kill",
    "mapNumber": 1,
    "roundNumber": 12,
    "eventHash": "c8f0f9c9064d35e71e6b7f5799deb55b",
    "timestamp": "2026-02-25T15:27:38.612Z"
  },
  {
    "id": "33ed8b7a-3bf7-47b8-aeb0-308b0c67fab5",
    "matchId": "2390266",
    "logText": "8Juho8 Tr0ublE",
    "killerName": "8Juho8",
    "victimName": "Tr0ublE",
    "assistName": null,
    "weapon": "ak47",
    "isHeadshot": false,
    "isWallbang": false,
    "isThroughSmoke": false,
    "isBlindKill": false,
    "isNoScope": false,
    "isSuicide": false,
    "eventType": "kill",
    "mapNumber": 1,
    "roundNumber": 12,
    "eventHash": "ef5398f3b5ef30c5de2f3d99c7729397",
    "timestamp": "2026-02-25T15:27:38.624Z"
  },
  {
    "id": "07807a16-e232-4e64-9bf1-41a5f66bbe66",
    "matchId": "2390266",
    "logText": "fakerealityy + maggent melty",
    "killerName": "fakerealityy",
    "victimName": "melty",
    "assistName": "maggent",
    "weapon": "hegrenade",
    "isHeadshot": false,
    "isWallbang": false,
    "isThroughSmoke": false,
    "isBlindKill": false,
    "isNoScope": false,
    "isSuicide": false,
    "eventType": "kill",
    "mapNumber": 1,
    "roundNumber": 12,
    "eventHash": "673e32cdb06482f4c4657e68ad9c739d",
    "timestamp": "2026-02-25T15:27:38.637Z"
  },
  {
    "id": "c4b14df2-de42-457c-ad8d-851699afda8b",
    "matchId": "2390266",
    "logText": "fakerealityy arvid",
    "killerName": "fakerealityy",
    "victimName": "arvid",
    "assistName": null,
    "weapon": "m4a1_silencer",
    "isHeadshot": true,
    "isWallbang": false,
    "isThroughSmoke": false,
    "isBlindKill": false,
    "isNoScope": false,
    "isSuicide": false,
    "eventType": "kill",
    "mapNumber": 1,
    "roundNumber": 12,
    "eventHash": "142f1d75960881803acff1a249c22e79",
    "timestamp": "2026-02-25T15:27:38.647Z"
  },
  {
    "id": "a3fb0eb6-c598-4a3e-b7d6-90a1adf0a6cc",
    "matchId": "2390266",
    "logText": "fakerealityy + OWNER oopee",
    "killerName": "fakerealityy",
    "victimName": "oopee",
    "assistName": "OWNER",
    "weapon": "m4a1_silencer",
    "isHeadshot": true,
    "isWallbang": false,
    "isThroughSmoke": false,
    "isBlindKill": false,
    "isNoScope": false,
    "isSuicide": false,
    "eventType": "kill",
    "mapNumber": 1,
    "roundNumber": 12,
    "eventHash": "bc5b628191b6602d9141b56820eba5c9",
    "timestamp": "2026-02-25T15:27:38.656Z"
  },
  {
    "id": "776a4092-ca40-46fd-a16e-3a6a756a8ec7",
    "matchId": "2390266",
    "logText": "oopee maggent",
    "killerName": "oopee",
    "victimName": "maggent",
    "assistName": null,
    "weapon": "ak47",
    "isHeadshot": true,
    "isWallbang": false,
    "isThroughSmoke": false,
    "isBlindKill": false,
    "isNoScope": false,
    "isSuicide": false,
    "eventType": "kill",
    "mapNumber": 1,
    "roundNumber": 12,
    "eventHash": "13c246853e09db8f5ace2480a24aca5a",
    "timestamp": "2026-02-25T15:27:38.672Z"
  },
  {
    "id": "9a005e1c-10f7-40bc-97ec-24190ea0ca0b",
    "matchId": "2390266",
    "logText": "melty planted the bomb on B (4on3)",
    "killerName": "melty",
    "victimName": null,
    "assistName": null,
    "weapon": "bomb",
    "isHeadshot": false,
    "isWallbang": false,
    "isThroughSmoke": false,
    "isBlindKill": false,
    "isNoScope": false,
    "isSuicide": false,
    "eventType": "bomb_plant",
    "mapNumber": 1,
    "roundNumber": 12,
    "eventHash": "567c41682632d83ef5f94c394a0df378",
    "timestamp": "2026-02-25T15:27:38.682Z"
  },
  {
    "id": "d32878e8-63c5-4882-b617-4e2d61e984f8",
    "matchId": "2390266",
    "logText": "oopee OWNER",
    "killerName": "oopee",
    "victimName": "OWNER",
    "assistName": null,
    "weapon": "ak47",
    "isHeadshot": true,
    "isWallbang": false,
    "isThroughSmoke": false,
    "isBlindKill": false,
    "isNoScope": false,
    "isSuicide": false,
    "eventType": "kill",
    "mapNumber": 1,
    "roundNumber": 12,
    "eventHash": "3face2dd2bb08a3e68c7039fd73478d8",
    "timestamp": "2026-02-25T15:27:38.692Z"
  },
  {
    "id": "45358c8f-47c2-4c88-b322-92d88b96707b",
    "matchId": "2390266",
    "logText": "oopee kr1vda",
    "killerName": "oopee",
    "victimName": "kr1vda",
    "assistName": null,
    "weapon": "ak47",
    "isHeadshot": false,
    "isWallbang": false,
    "isThroughSmoke": false,
    "isBlindKill": false,
    "isNoScope": false,
    "isSuicide": false,
    "eventType": "kill",
    "mapNumber": 1,
    "roundNumber": 12,
    "eventHash": "ec773224e1cb397e7ac6b024d246c93b",
    "timestamp": "2026-02-25T15:27:38.702Z"
  },
  {
    "id": "6e2a5351-47b6-4c7e-bcf8-10acfa1ca698",
    "matchId": "2390266",
    "logText": "Tr0ublE Myggis",
    "killerName": "Tr0ublE",
    "victimName": "Myggis",
    "assistName": null,
    "weapon": "awp",
    "isHeadshot": false,
    "isWallbang": false,
    "isThroughSmoke": false,
    "isBlindKill": false,
    "isNoScope": false,
    "isSuicide": false,
    "eventType": "kill",
    "mapNumber": 1,
    "roundNumber": 12,
    "eventHash": "d8d0572f96f80da68de3f7a2aa849ca8",
    "timestamp": "2026-02-25T15:27:38.711Z"
  },
  {
    "id": "d3670fd0-bb6a-40ad-942f-4859dc3bfe7e",
    "matchId": "2390266",
    "logText": "Tr0ublE + kr1vdaarvid",
    "killerName": "Tr0ublE",
    "victimName": "arvid",
    "assistName": null,
    "weapon": "glock",
    "isHeadshot": true,
    "isWallbang": false,
    "isThroughSmoke": false,
    "isBlindKill": true,
    "isNoScope": false,
    "isSuicide": false,
    "eventType": "kill",
    "mapNumber": 1,
    "roundNumber": 1,
    "eventHash": "8ee72c95cf1cb5ece758197cb7280961",
    "timestamp": "2026-02-25T15:28:26.669Z"
  },
  {
    "id": "b4d5af7c-2520-4e22-b725-806875a2b22b",
    "matchId": "2390266",
    "logText": "oopee + meltyTr0ublE",
    "killerName": "oopee",
    "victimName": "Tr0ublE",
    "assistName": null,
    "weapon": "elite",
    "isHeadshot": true,
    "isWallbang": true,
    "isThroughSmoke": false,
    "isBlindKill": true,
    "isNoScope": false,
    "isSuicide": false,
    "eventType": "kill",
    "mapNumber": 1,
    "roundNumber": 1,
    "eventHash": "011ecf8c577371d744b5b35b6172f879",
    "timestamp": "2026-02-25T15:28:29.665Z"
  },
  {
    "id": "1bcdd655-ca06-4545-ae68-5483c2e39e6e",
    "matchId": "2390266",
    "logText": "OWNER oopee",
    "killerName": "OWNER",
    "victimName": "oopee",
    "assistName": null,
    "weapon": "glock",
    "isHeadshot": true,
    "isWallbang": true,
    "isThroughSmoke": false,
    "isBlindKill": false,
    "isNoScope": false,
    "isSuicide": false,
    "eventType": "kill",
    "mapNumber": 1,
    "roundNumber": 1,
    "eventHash": "e909eb67e075a092962749ee6af43616",
    "timestamp": "2026-02-25T15:28:32.671Z"
  },
  {
    "id": "d9174ee0-d8f2-44a8-ac7a-3b5e2ae4fc65",
    "matchId": "2390266",
    "logText": "fakerealityy planted the bomb on B (4on3)",
    "killerName": "fakerealityy",
    "victimName": null,
    "assistName": null,
    "weapon": "bomb",
    "isHeadshot": false,
    "isWallbang": false,
    "isThroughSmoke": false,
    "isBlindKill": false,
    "isNoScope": false,
    "isSuicide": false,
    "eventType": "bomb_plant",
    "mapNumber": 1,
    "roundNumber": 1,
    "eventHash": "67bbe4282b7aa559fffc730519b5deec",
    "timestamp": "2026-02-25T15:28:38.686Z"
  }
]