[
  {
    "id": "d82c7990-9747-4ab6-9900-7b32f92d6b4f",
    "matchId": "2390782",
    "logText": "Boye shield",
    "killerName": "Boye",
    "victimName": "shield",
    "assistName": null,
    "weapon": "ssg08",
    "isHeadshot": true,
    "isWallbang": false,
    "isThroughSmoke": false,
    "isBlindKill": false,
    "isNoScope": true,
    "isSuicide": false,
    "eventType": "kill",
    "mapNumber": 2,
    "roundNumber": 1,
    "eventHash": "935df6459e3723c18365d15803e400eb",
    "timestamp": "2026-02-26T10:11:48.606Z"
  },
  {
    "id": "719208f7-7128-485f-bf51-f535007f3444",
    "matchId": "2390782",
    "logText": "cej0t Boye",
    "killerName": "cej0t",
    "victimName": "Boye",
    "assistName": null,
    "weapon": "knife_butterfly",
    "isHeadshot": false,
    "isWallbang": false,
    "isThroughSmoke": false,
    "isBlindKill": false,
    "isNoScope": false,
    "isSuicide": false,
    "eventType": "kill",
    "mapNumber": 2,
    "roundNumber": 1,
    "eventHash": "6a70022be5f7c796be8a9c975d74dd77",
    "timestamp": "2026-02-26T10:11:51.598Z"
  },
  {
    "id": "07359a72-72b1-488a-98f2-cc5e95a9f6b8",
    "matchId": "2390782",
    "logText": "leakz + Boye bnox",
    "killerName": "leakz",
    "victimName": "bnox",
    "assistName": "Boye",
    "weapon": "m4a1_silencer",
    "isHeadshot": false,
    "isWallbang": false,
    "isThroughSmoke": false,
    "isBlindKill": false,
    "isNoScope": false,
    "isSuicide": false,
    "eventType": "kill",
    "mapNumber": 2,
    "roundNumber": 1,
    "eventHash": "4f6af09588e85141a92b83fb9399b25c",
    "timestamp": "2026-02-26T10:12:21.629Z"
  },
  {
    "id": "342493f3-905d-48e9-bb1a-58383e8563d6",
    "matchId": "2390782",
    "logText": "cej0t Boye",
    "killerName": "cej0t",
    "victimName": "Boye",
    "assistName": null,
    "weapon": "ak47",
    "isHeadshot": true,
    "isWallbang": false,
    "isThroughSmoke": true,
    "isBlindKill": false,
    "isNoScope": false,
    "isSuicide": false,
    "eventType": "kill",
    "mapNumber": 2,
    "roundNumber": 1,
    "eventHash": "8419fae153d5bfb0443ef7b2cf28eab1",
    "timestamp": "2026-02-26T10:12:27.640Z"
  },
  {
    "id": "8b6f1a80-7664-474d-9883-057014cd6f84",
    "matchId": "2390782",
    "logText": "bnox leakz",
    "killerName": "bnox",
    "victimName": "leakz",
    "assistName": null,
    "weapon": "ak47",
    "isHeadshot": true,
    "isWallbang": false,
    "isThroughSmoke": false,
    "isBlindKill": false,
    "isNoScope": false,
    "isSuicide": false,
    "eventType": "kill",
    "mapNumber": 2,
    "roundNumber": 1,
    "eventHash": "0e74f0c7581ee2783b8e4469a7d29171",
    "timestamp": "2026-02-26T10:12:39.654Z"
  },
  {
    "id": "4ea22b5b-83e7-41ef-9b1c-a311cc7a9d94",
    "matchId": "2390782",
    "logText": "Boye bnox",
    "killerName": "Boye",
    "victimName": "bnox",
    "assistName": null,
    "weapon": "deagle",
    "isHeadshot": true,
    "isWallbang": false,
    "isThroughSmoke": false,
    "isBlindKill": false,
    "isNoScope": false,
    "isSuicide": false,
    "eventType": "kill",
    "mapNumber": 2,
    "roundNumber": 1,
    "eventHash": "496a770aae7dab7b3641794cc122f4e2",
    "timestamp": "2026-02-26T10:12:42.669Z"
  },
  {
    "id": "a71e91b4-a3e9-4b71-905d-06ca111dd3be",
    "matchId": "2390782",
    "logText": "raalz salazar",
    "killerName": "raalz",
    "victimName": "salazar",
    "assistName": null,
    "weapon": "ak47",
    "isHeadshot": true,
    "isWallbang": false,
    "isThroughSmoke": false,
    "isBlindKill": false,
    "isNoScope": false,
    "isSuicide": false,
    "eventType": "kill",
    "mapNumber": 2,
    "roundNumber": 1,
    "eventHash": "6821f33e79108f3847203053c5aac516",
    "timestamp": "2026-02-26T10:12:45.683Z"
  },
  {
    "id": "253caeeb-d475-4d1f-9faa-a7f76851d1c6",
    "matchId": "2390782",
    "logText": "Boye raalz",
    "killerName": "Boye",
    "victimName": "raalz",
    "assistName": null,
    "weapon": "deagle",
    "isHeadshot": true,
    "isWallbang": true,
    "isThroughSmoke": false,
    "isBlindKill": false,
    "isNoScope": false,
    "isSuicide": false,
    "eventType": "kill",
    "mapNumber": 2,
    "roundNumber": 1,
    "eventHash": "0517941c21ab007b93e442416e877e87",
    "timestamp": "2026-02-26T10:12:51.696Z"
  },
  {
    "id": "c633b6ec-d8c4-459c-b86d-749b80579360",
    "matchId": "2390782",
    "logText": "leakz bnox",
    "killerName": "leakz",
    "victimName": "bnox",
    "assistName": null,
    "weapon": "deagle",
    "isHeadshot": true,
    "isWallbang": false,
    "isThroughSmoke": false,
    "isBlindKill": false,
    "isNoScope": false,
    "isSuicide": false,
    "eventType": "kill",
    "mapNumber": 2,
    "roundNumber": 1,
    "eventHash": "a8c90c7ccc6a379eac40df864ccfebcd",
    "timestamp": "2026-02-26T10:12:54.704Z"
  },
  {
    "id": "c7ff21ba-524f-405b-8723-69a84a7f7f1c",
    "matchId": "2390782",
    "logText": "salazar shield",
    "killerName": "salazar",
    "victimName": "shield",
    "assistName": null,
    "weapon": "m4a1_silencer",
    "isHeadshot": true,
    "isWallbang": false,
    "isThroughSmoke": false,
    "isBlindKill": false,
    "isNoScope": false,
    "isSuicide": false,
    "eventType": "kill",
    "mapNumber": 2,
    "roundNumber": 1,
    "eventHash": "86e4c97bf0d5c7deefd08e3c21061b51",
    "timestamp": "2026-02-26T10:13:03.729Z"
  },
  {
    "id": "3fcad7e0-7763-4ee5-b3d1-9cb0a5d76f56",
    "matchId": "2390782",
    "logText": "salazar bnox",
    "killerName": "salazar",
    "victimName": "bnox",
    "assistName": null,
    "weapon": "m4a1_silencer",
    "isHeadshot": true,
    "isWallbang": false,
    "isThroughSmoke": false,
    "isBlindKill": false,
    "isNoScope": false,
    "isSuicide": false,
    "eventType": "kill",
    "mapNumber": 2,
    "roundNumber": 1,
    "eventHash": "86653c2868bd7653ec9bb21c9167a396",
    "timestamp": "2026-02-26T10:13:06.731Z"
  },
  {
    "id": "0820cc9d-4abe-4915-a6fa-be320f1822c4",
    "matchId": "2390782",
    "logText": "leakz kraghen",
    "killerName": "leakz",
    "victimName": "kraghen",
    "assistName": null,
    "weapon": "deagle",
    "isHeadshot": true,
    "isWallbang": false,
    "isThroughSmoke": false,
    "isBlindKill": false,
    "isNoScope": false,
    "isSuicide": false,
    "eventType": "kill",
    "mapNumber": 2,
    "roundNumber": 1,
    "eventHash": "2f83d336776a510a89ba768a135f52b5",
    "timestamp": "2026-02-26T10:13:09.761Z"
  },
  {
    "id": "56b27b3e-5ff7-4b61-b396-d0d48843aee2",
    "matchId": "2390782",
    "logText": "salazar kraghen",
    "killerName": "salazar",
    "victimName": "kraghen",
    "assistName": null,
    "weapon": "m4a1_silencer",
    "isHeadshot": true,
    "isWallbang": false,
    "isThroughSmoke": false,
    "isBlindKill": false,
    "isNoScope": false,
    "isSuicide": false,
    "eventType": "kill",
    "mapNumber": 2,
    "roundNumber": 1,
    "eventHash": "234f004784d4cd9c475df68dfb6a7568",
    "timestamp": "2026-02-26T10:13:15.753Z"
  },
  {
    "id": "559414fc-cf46-4acf-8c6c-f4c083d2dabe",
    "matchId": "2390782",
    "logText": "bnox salazar",
    "killerName": "bnox",
    "victimName": "salazar",
    "assistName": null,
    "weapon": "ak47",
    "isHeadshot": false,
    "isWallbang": false,
    "isThroughSmoke": false,
    "isBlindKill": false,
    "isNoScope": false,
    "isSuicide": false,
    "eventType": "kill",
    "mapNumber": 2,
    "roundNumber": 1,
    "eventHash": "5987ec0977ae055c1f0dadb81aba5f04",
    "timestamp": "2026-02-26T10:13:18.890Z"
  },
  {
    "id": "dcc24c38-2373-4b89-9e26-a706364ed310",
    "matchId": "2390782",
    "logText": "leakz raalz",
    "killerName": "leakz",
    "victimName": "raalz",
    "assistName": null,
    "weapon": "m4a1_silencer",
    "isHeadshot": false,
    "isWallbang": false,
    "isThroughSmoke": false,
    "isBlindKill": false,
    "isNoScope": false,
    "isSuicide": false,
    "eventType": "kill",
    "mapNumber": 2,
    "roundNumber": 1,
    "eventHash": "d59a5e6477fb31cf12dbc5d29bf9e119",
    "timestamp": "2026-02-26T10:13:21.761Z"
  },
  {
    "id": "6f77e5a4-99b9-4ad9-a265-ab449f618532",
    "matchId": "2390782",
    "logText": "kraghen + bnox Boye",
    "killerName": "kraghen",
    "victimName": "Boye",
    "assistName": "bnox",
    "weapon": "ak47",
    "isHeadshot": true,
    "isWallbang": false,
    "isThroughSmoke": false,
    "isBlindKill": false,
    "isNoScope": false,
    "isSuicide": false,
    "eventType": "kill",
    "mapNumber": 2,
    "roundNumber": 1,
    "eventHash": "53282f8dc2b6cd4a81720a71562d06f8",
    "timestamp": "2026-02-26T10:13:21.770Z"
  },
  {
    "id": "e808b02e-ed70-417a-b178-bf6db703e3d1",
    "matchId": "2390782",
    "logText": "IceBerg kraghen",
    "killerName": "IceBerg",
    "victimName": "kraghen",
    "assistName": null,
    "weapon": "m4a1_silencer",
    "isHeadshot": false,
    "isWallbang": false,
    "isThroughSmoke": false,
    "isBlindKill": false,
    "isNoScope": false,
    "isSuicide": false,
    "eventType": "kill",
    "mapNumber": 2,
    "roundNumber": 1,
    "eventHash": "9ea05ff2856b425e570dda006b24a13c",
    "timestamp": "2026-02-26T10:13:24.773Z"
  },
  {
    "id": "0b910b69-eb62-4f93-818c-7bb5bac80023",
    "matchId": "2390782",
    "logText": "kraghen NickyB",
    "killerName": "kraghen",
    "victimName": "NickyB",
    "assistName": null,
    "weapon": "ak47",
    "isHeadshot": false,
    "isWallbang": true,
    "isThroughSmoke": false,
    "isBlindKill": false,
    "isNoScope": false,
    "isSuicide": false,
    "eventType": "kill",
    "mapNumber": 2,
    "roundNumber": 1,
    "eventHash": "bfdbc28d96364dbe952a3a18c05bcf57",
    "timestamp": "2026-02-26T10:13:30.776Z"
  },
  {
    "id": "480fa1e5-ec27-4cd6-9c02-ac235552d31c",
    "matchId": "2390782",
    "logText": "bnox + kraghen IceBerg",
    "killerName": "bnox",
    "victimName": "IceBerg",
    "assistName": "kraghen",
    "weapon": "ak47",
    "isHeadshot": false,
    "isWallbang": false,
    "isThroughSmoke": false,
    "isBlindKill": false,
    "isNoScope": false,
    "isSuicide": false,
    "eventType": "kill",
    "mapNumber": 2,
    "roundNumber": 1,
    "eventHash": "45803b2f38098da2499c8d694aca416d",
    "timestamp": "2026-02-26T10:13:33.809Z"
  },
  {
    "id": "140e8c84-6330-4077-a80c-d10192a478ff",
    "matchId": "2390782",
    "logText": "NickyB cej0t",
    "killerName": "NickyB",
    "victimName": "cej0t",
    "assistName": null,
    "weapon": "m4a1",
    "isHeadshot": false,
    "isWallbang": false,
    "isThroughSmoke": false,
    "isBlindKill": false,
    "isNoScope": false,
    "isSuicide": false,
    "eventType": "kill",
    "mapNumber": 2,
    "roundNumber": 1,
    "eventHash": "c7e5b986eb8061118f6629839cff3cc8",
    "timestamp": "2026-02-26T10:13:36.793Z"
  },
  {
    "id": "5e25afe8-9b6d-43cf-82db-a46193730111",
    "matchId": "2390782",
    "logText": "salazar kraghen",
    "killerName": "salazar",
    "victimName": "kraghen",
    "assistName": null,
    "weapon": "hegrenade",
    "isHeadshot": false,
    "isWallbang": false,
    "isThroughSmoke": false,
    "isBlindKill": false,
    "isNoScope": false,
    "isSuicide": false,
    "eventType": "kill",
    "mapNumber": 2,
    "roundNumber": 1,
    "eventHash": "b69d2a8fa99d2aeda7ad3b5c4a21034f",
    "timestamp": "2026-02-26T10:13:36.803Z"
  },
  {
    "id": "66e78b0d-a885-459b-9c5a-22009cc33c0c",
    "matchId": "2390782",
    "logText": "Boye bnox",
    "killerName": "Boye",
    "victimName": "bnox",
    "assistName": null,
    "weapon": "m4a1",
    "isHeadshot": false,
    "isWallbang": false,
    "isThroughSmoke": false,
    "isBlindKill": false,
    "isNoScope": false,
    "isSuicide": false,
    "eventType": "kill",
    "mapNumber": 2,
    "roundNumber": 1,
    "eventHash": "95c004cb027c993e83dedab03ee2588a",
    "timestamp": "2026-02-26T10:13:36.815Z"
  },
  {
    "id": "f49c26ab-0b34-4780-b74a-123364cde174",
    "matchId": "2390782",
    "logText": "leakz bnox",
    "killerName": "leakz",
    "victimName": "bnox",
    "assistName": null,
    "weapon": "m4a1_silencer",
    "isHeadshot": false,
    "isWallbang": false,
    "isThroughSmoke": false,
    "isBlindKill": false,
    "isNoScope": false,
    "isSuicide": false,
    "eventType": "kill",
    "mapNumber": 2,
    "roundNumber": 1,
    "eventHash": "2c0b55377f523ab2d016fb35d77f4349",
    "timestamp": "2026-02-26T10:13:42.809Z"
  },
  {
    "id": "2cff8a08-d524-4f90-8b72-0419ae178008",
    "matchId": "2390782",
    "logText": "cej0t + kraghen salazar",
    "killerName": "cej0t",
    "victimName": "salazar",
    "assistName": "kraghen",
    "weapon": "ak47",
    "isHeadshot": true,
    "isWallbang": false,
    "isThroughSmoke": false,
    "isBlindKill": false,
    "isNoScope": false,
    "isSuicide": false,
    "eventType": "kill",
    "mapNumber": 2,
    "roundNumber": 1,
    "eventHash": "f89c961e17bacd2d05881aab7e3ba40d",
    "timestamp": "2026-02-26T10:13:45.813Z"
  },
  {
    "id": "8c781a5c-f86c-4191-b11e-e2a6147cf7ce",
    "matchId": "2390782",
    "logText": "leakz + salazar kraghen",
    "killerName": "leakz",
    "victimName": "kraghen",
    "assistName": "salazar",
    "weapon": "m4a1_silencer",
    "isHeadshot": true,
    "isWallbang": false,
    "isThroughSmoke": false,
    "isBlindKill": false,
    "isNoScope": false,
    "isSuicide": false,
    "eventType": "kill",
    "mapNumber": 2,
    "roundNumber": 1,
    "eventHash": "d4968eb508fe2f0debdc502a3c752dfa",
    "timestamp": "2026-02-26T10:13:45.825Z"
  },
  {
    "id": "9bf04053-b081-44b6-9c1f-4796f811e2e9",
    "matchId": "2390782",
    "logText": "cej0t leakz",
    "killerName": "cej0t",
    "victimName": "leakz",
    "assistName": null,
    "weapon": "ak47",
    "isHeadshot": true,
    "isWallbang": false,
    "isThroughSmoke": false,
    "isBlindKill": false,
    "isNoScope": false,
    "isSuicide": false,
    "eventType": "kill",
    "mapNumber": 2,
    "roundNumber": 1,
    "eventHash": "4ecadd7467ffff2a734fe404a961481b",
    "timestamp": "2026-02-26T10:13:48.832Z"
  },
  {
    "id": "7170f622-3f29-483a-8901-842864766c37",
    "matchId": "2390782",
    "logText": "bnox NickyB",
    "killerName": "bnox",
    "victimName": "NickyB",
    "assistName": null,
    "weapon": "deagle",
    "isHeadshot": true,
    "isWallbang": false,
    "isThroughSmoke": false,
    "isBlindKill": false,
    "isNoScope": false,
    "isSuicide": false,
    "eventType": "kill",
    "mapNumber": 2,
    "roundNumber": 1,
    "eventHash": "8cd2e343dbb0291b1ca81bf9e240ba7f",
    "timestamp": "2026-02-26T10:13:54.835Z"
  },
  {
    "id": "c57b7297-85bd-45a8-a9c1-8e92dc2bcadb",
    "matchId": "2390782",
    "logText": "kraghen IceBerg",
    "killerName": "kraghen",
    "victimName": "IceBerg",
    "assistName": null,
    "weapon": "ak47",
    "isHeadshot": true,
    "isWallbang": false,
    "isThroughSmoke": false,
    "isBlindKill": false,
    "isNoScope": false,
    "isSuicide": false,
    "eventType": "kill",
    "mapNumber": 2,
    "roundNumber": 1,
    "eventHash": "f1e42e1d23179703106e8d5fa618fe58",
    "timestamp": "2026-02-26T10:13:57.848Z"
  },
  {
    "id": "eca7aa97-b813-4cf5-8b12-06166ec80eb4",
    "matchId": "2390782",
    "logText": "IceBerg bnox",
    "killerName": "IceBerg",
    "victimName": "bnox",
    "assistName": null,
    "weapon": "m4a1_silencer",
    "isHeadshot": true,
    "isWallbang": false,
    "isThroughSmoke": false,
    "isBlindKill": false,
    "isNoScope": false,
    "isSuicide": false,
    "eventType": "kill",
    "mapNumber": 2,
    "roundNumber": 1,
    "eventHash": "ad18a08f30de5ae2059409829625c4c0",
    "timestamp": "2026-02-26T10:13:58.181Z"
  },
  {
    "id": "c8e3a725-e7ea-4c3b-b99e-17db46563b4e",
    "matchId": "2390782",
    "logText": "Boye cej0t",
    "killerName": "Boye",
    "victimName": "cej0t",
    "assistName": null,
    "weapon": "m4a1",
    "isHeadshot": true,
    "isWallbang": false,
    "isThroughSmoke": false,
    "isBlindKill": false,
    "isNoScope": false,
    "isSuicide": false,
    "eventType": "kill",
    "mapNumber": 2,
    "roundNumber": 1,
    "eventHash": "8faba6aeabe6d1f335db44bcc4b40ba9",
    "timestamp": "2026-02-26T10:14:00.861Z"
  },
  {
    "id": "7b412003-0f41-4a21-8831-e64e921f61ee",
    "matchId": "2390782",
    "logText": "salazar + IceBerg kraghen",
    "killerName": "salazar",
    "victimName": "kraghen",
    "assistName": "IceBerg",
    "weapon": "m4a1_silencer",
    "isHeadshot": true,
    "isWallbang": false,
    "isThroughSmoke": false,
    "isBlindKill": false,
    "isNoScope": false,
    "isSuicide": false,
    "eventType": "kill",
    "mapNumber": 2,
    "roundNumber": 1,
    "eventHash": "7fd43eeae4eabf553bdfff4601f313d2",
    "timestamp": "2026-02-26T10:14:00.873Z"
  },
  {
    "id": "6e4fd985-22c9-4ef0-9116-4aadf7e5b4fa",
    "matchId": "2390782",
    "logText": "kraghen + bnox Boye",
    "killerName": "kraghen",
    "victimName": "Boye",
    "assistName": "bnox",
    "weapon": "galilar",
    "isHeadshot": true,
    "isWallbang": false,
    "isThroughSmoke": false,
    "isBlindKill": false,
    "isNoScope": false,
    "isSuicide": false,
    "eventType": "kill",
    "mapNumber": 2,
    "roundNumber": 1,
    "eventHash": "17bb8e0c1080433b103557d631d560cb",
    "timestamp": "2026-02-26T10:14:03.865Z"
  },
  {
    "id": "3d0f084e-4b08-4939-a698-628efd90cd38",
    "matchId": "2390782",
    "logText": "salazar kraghen",
    "killerName": "salazar",
    "victimName": "kraghen",
    "assistName": null,
    "weapon": "m4a1_silencer",
    "isHeadshot": false,
    "isWallbang": false,
    "isThroughSmoke": false,
    "isBlindKill": false,
    "isNoScope": false,
    "isSuicide": false,
    "eventType": "kill",
    "mapNumber": 2,
    "roundNumber": 1,
    "eventHash": "5b1463ad612e841f53d4a27131cf9e8f",
    "timestamp": "2026-02-26T10:14:09.874Z"
  },
  {
    "id": "bf018dff-387f-4c28-9787-e367861a10fe",
    "matchId": "2390782",
    "logText": "NickyB + leakz bnox",
    "killerName": "NickyB",
    "victimName": "bnox",
    "assistName": "leakz",
    "weapon": "m4a1",
    "isHeadshot": false,
    "isWallbang": false,
    "isThroughSmoke": false,
    "isBlindKill": false,
    "isNoScope": false,
    "isSuicide": false,
    "eventType": "kill",
    "mapNumber": 2,
    "roundNumber": 1,
    "eventHash": "3408a7ea75f0e4661551429700226de8",
    "timestamp": "2026-02-26T10:14:12.871Z"
  },
  {
    "id": "33f2d012-3bc9-45c5-bf41-4d2551018e70",
    "matchId": "2390782",
    "logText": "bnox leakz",
    "killerName": "bnox",
    "victimName": "leakz",
    "assistName": null,
    "weapon": "galilar",
    "isHeadshot": true,
    "isWallbang": false,
    "isThroughSmoke": false,
    "isBlindKill": false,
    "isNoScope": false,
    "isSuicide": false,
    "eventType": "kill",
    "mapNumber": 2,
    "roundNumber": 1,
    "eventHash": "b4430ead77de69793507b5a9203a7904",
    "timestamp": "2026-02-26T10:14:12.880Z"
  },
  {
    "id": "a7cfe0dc-5043-4731-b35a-2e1e2ffa9bcf",
    "matchId": "2390782",
    "logText": "salazar raalz",
    "killerName": "salazar",
    "victimName": "raalz",
    "assistName": null,
    "weapon": "m4a1_silencer",
    "isHeadshot": true,
    "isWallbang": false,
    "isThroughSmoke": false,
    "isBlindKill": false,
    "isNoScope": false,
    "isSuicide": false,
    "eventType": "kill",
    "mapNumber": 2,
    "roundNumber": 1,
    "eventHash": "4d88b78fc10ad6e1636cf4fe544d2e0d",
    "timestamp": "2026-02-26T10:14:15.886Z"
  },
  {
    "id": "ecabb454-4256-455b-a333-40589673c32e",
    "matchId": "2390782",
    "logText": "salazar + NickyB shield",
    "killerName": "salazar",
    "victimName": "shield",
    "assistName": "NickyB",
    "weapon": "m4a1_silencer",
    "isHeadshot": true,
    "isWallbang": false,
    "isThroughSmoke": false,
    "isBlindKill": false,
    "isNoScope": false,
    "isSuicide": false,
    "eventType": "kill",
    "mapNumber": 2,
    "roundNumber": 1,
    "eventHash": "4f659441cc8b1d06dd6847ba26f40518",
    "timestamp": "2026-02-26T10:14:15.894Z"
  },
  {
    "id": "53fadccd-71d6-450d-ac5a-f9e5296a682d",
    "matchId": "2390782",
    "logText": "NickyB kraghen",
    "killerName": "NickyB",
    "victimName": "kraghen",
    "assistName": null,
    "weapon": "m4a1",
    "isHeadshot": false,
    "isWallbang": false,
    "isThroughSmoke": false,
    "isBlindKill": false,
    "isNoScope": false,
    "isSuicide": false,
    "eventType": "kill",
    "mapNumber": 2,
    "roundNumber": 1,
    "eventHash": "032864ca9f4fcdc9a9e0321f323d87f6",
    "timestamp": "2026-02-26T10:14:15.902Z"
  },
  {
    "id": "47e434b5-5cd0-4672-9226-2e2e23fd63c1",
    "matchId": "2390782",
    "logText": "cej0t salazar",
    "killerName": "cej0t",
    "victimName": "salazar",
    "assistName": null,
    "weapon": "galilar",
    "isHeadshot": true,
    "isWallbang": false,
    "isThroughSmoke": false,
    "isBlindKill": false,
    "isNoScope": false,
    "isSuicide": false,
    "eventType": "kill",
    "mapNumber": 2,
    "roundNumber": 1,
    "eventHash": "c9e4a2e50feeece7c18eb5c5512ce38f",
    "timestamp": "2026-02-26T10:14:19.155Z"
  },
  {
    "id": "eec5b88d-8e6a-45e1-9264-db1cf8393704",
    "matchId": "2390782",
    "logText": "Boye bnox",
    "killerName": "Boye",
    "victimName": "bnox",
    "assistName": null,
    "weapon": "ssg08",
    "isHeadshot": true,
    "isWallbang": false,
    "isThroughSmoke": false,
    "isBlindKill": false,
    "isNoScope": false,
    "isSuicide": false,
    "eventType": "kill",
    "mapNumber": 2,
    "roundNumber": 1,
    "eventHash": "4e5725410687ba1130fe10f9fe5a3cb0",
    "timestamp": "2026-02-26T10:14:21.907Z"
  },
  {
    "id": "696c5949-b3cb-4477-8d18-6648b3adb602",
    "matchId": "2390782",
    "logText": "cej0t NickyB",
    "killerName": "cej0t",
    "victimName": "NickyB",
    "assistName": null,
    "weapon": "galilar",
    "isHeadshot": true,
    "isWallbang": false,
    "isThroughSmoke": false,
    "isBlindKill": false,
    "isNoScope": false,
    "isSuicide": false,
    "eventType": "kill",
    "mapNumber": 2,
    "roundNumber": 1,
    "eventHash": "aeb34a075839a18e0858ae12beb33533",
    "timestamp": "2026-02-26T10:14:21.917Z"
  },
  {
    "id": "f298c00b-d170-44b1-a5bc-482ad5f40115",
    "matchId": "2390782",
    "logText": "Boye kraghen",
    "killerName": "Boye",
    "victimName": "kraghen",
    "assistName": null,
    "weapon": "ssg08",
    "isHeadshot": true,
    "isWallbang": false,
    "isThroughSmoke": true,
    "isBlindKill": false,
    "isNoScope": false,
    "isSuicide": false,
    "eventType": "kill",
    "mapNumber": 2,
    "roundNumber": 1,
    "eventHash": "4583538358c0be282efca59e09d630a4",
    "timestamp": "2026-02-26T10:14:27.917Z"
  },
  {
    "id": "8d8093fa-c490-4fd7-a34d-57104e281238",
    "matchId": "2390782",
    "logText": "bnox leakz",
    "killerName": "bnox",
    "victimName": "leakz",
    "assistName": null,
    "weapon": "tec9",
    "isHeadshot": true,
    "isWallbang": false,
    "isThroughSmoke": false,
    "isBlindKill": false,
    "isNoScope": false,
    "isSuicide": false,
    "eventType": "kill",
    "mapNumber": 2,
    "roundNumber": 1,
    "eventHash": "0c1cbe93c0c2eea9c89a07cbcac129f4",
    "timestamp": "2026-02-26T10:14:30.929Z"
  },
  {
    "id": "20da1d3a-55c9-4732-975a-34cc04ab4bd2",
    "matchId": "2390782",
    "logText": "kraghen + bnox salazar",
    "killerName": "kraghen",
    "victimName": "salazar",
    "assistName": "bnox",
    "weapon": "deagle",
    "isHeadshot": false,
    "isWallbang": false,
    "isThroughSmoke": true,
    "isBlindKill": false,
    "isNoScope": false,
    "isSuicide": false,
    "eventType": "kill",
    "mapNumber": 2,
    "roundNumber": 1,
    "eventHash": "4633a16b3f1357eb7b76ab6fa8bf1583",
    "timestamp": "2026-02-26T10:14:33.931Z"
  },
  {
    "id": "d7393763-9acc-4d05-bf0d-a9042a00f555",
    "matchId": "2390782",
    "logText": "bnox Boye",
    "killerName": "bnox",
    "victimName": "Boye",
    "assistName": null,
    "weapon": "tec9",
    "isHeadshot": true,
    "isWallbang": false,
    "isThroughSmoke": false,
    "isBlindKill": false,
    "isNoScope": false,
    "isSuicide": false,
    "eventType": "kill",
    "mapNumber": 2,
    "roundNumber": 1,
    "eventHash": "cbb7996bf7749e011804743f29e2bd1c",
    "timestamp": "2026-02-26T10:14:33.940Z"
  },
  {
    "id": "d6887d9d-7123-49f8-a3ab-71dff14ebb78",
    "matchId": "2390782",
    "logText": "IceBerg cej0t",
    "killerName": "IceBerg",
    "victimName": "cej0t",
    "assistName": null,
    "weapon": "m4a1_silencer",
    "isHeadshot": false,
    "isWallbang": false,
    "isThroughSmoke": false,
    "isBlindKill": false,
    "isNoScope": false,
    "isSuicide": false,
    "eventType": "kill",
    "mapNumber": 2,
    "roundNumber": 1,
    "eventHash": "9befc2108c6acf67f87d3a3b322c3fca",
    "timestamp": "2026-02-26T10:14:33.949Z"
  },
  {
    "id": "77844266-f9d1-4d91-8e8f-56534bf87890",
    "matchId": "2390782",
    "logText": "cej0t + raalz IceBerg",
    "killerName": "cej0t",
    "victimName": "IceBerg",
    "assistName": "raalz",
    "weapon": "ak47",
    "isHeadshot": true,
    "isWallbang": false,
    "isThroughSmoke": false,
    "isBlindKill": false,
    "isNoScope": false,
    "isSuicide": false,
    "eventType": "kill",
    "mapNumber": 2,
    "roundNumber": 1,
    "eventHash": "c2000dd08c375173d60642ce9fd46b2c",
    "timestamp": "2026-02-26T10:14:36.946Z"
  },
  {
    "id": "591b3b86-2923-4de7-bc06-70e4ae704e1f",
    "matchId": "2390782",
    "logText": "IceBerg raalz",
    "killerName": "IceBerg",
    "victimName": "raalz",
    "assistName": null,
    "weapon": "m4a1_silencer",
    "isHeadshot": false,
    "isWallbang": false,
    "isThroughSmoke": false,
    "isBlindKill": false,
    "isNoScope": false,
    "isSuicide": false,
    "eventType": "kill",
    "mapNumber": 2,
    "roundNumber": 1,
    "eventHash": "edec6be11a946412c3bbf473e67a8e5a",
    "timestamp": "2026-02-26T10:14:36.956Z"
  },
  {
    "id": "6c254ac0-9f61-4924-9701-62a15aada9c5",
    "matchId": "2390782",
    "logText": "IceBerg + salazar kraghen",
    "killerName": "IceBerg",
    "victimName": "kraghen",
    "assistName": "salazar",
    "weapon": "m4a1_silencer",
    "isHeadshot": false,
    "isWallbang": false,
    "isThroughSmoke": false,
    "isBlindKill": false,
    "isNoScope": false,
    "isSuicide": false,
    "eventType": "kill",
    "mapNumber": 2,
    "roundNumber": 1,
    "eventHash": "7930ff9e4bc38968e444bc65acd8c164",
    "timestamp": "2026-02-26T10:14:36.966Z"
  },
  {
    "id": "48518d18-39bb-4c66-b3af-4ba0442f312c",
    "matchId": "2390782",
    "logText": "NickyB bnox",
    "killerName": "NickyB",
    "victimName": "bnox",
    "assistName": null,
    "weapon": "usp_silencer",
    "isHeadshot": true,
    "isWallbang": false,
    "isThroughSmoke": false,
    "isBlindKill": false,
    "isNoScope": false,
    "isSuicide": false,
    "eventType": "kill",
    "mapNumber": 2,
    "roundNumber": 1,
    "eventHash": "7a8b03ea731e77c593d69fa2d4775cad",
    "timestamp": "2026-02-26T10:14:39.965Z"
  },
  {
    "id": "6507da1a-d9e6-4b7c-96b7-448385f0fdfb",
    "matchId": "2390782",
    "logText": "leakz bnox",
    "killerName": "leakz",
    "victimName": "bnox",
    "assistName": null,
    "weapon": "m4a1",
    "isHeadshot": false,
    "isWallbang": false,
    "isThroughSmoke": false,
    "isBlindKill": false,
    "isNoScope": false,
    "isSuicide": false,
    "eventType": "kill",
    "mapNumber": 2,
    "roundNumber": 1,
    "eventHash": "24a560d0c6803b7ed8edce5bd52c0b76",
    "timestamp": "2026-02-26T10:14:54.967Z"
  },
  {
    "id": "bdb701a2-5298-4ac4-931e-a88be8df0860",
    "matchId": "2390782",
    "logText": "cej0t IceBerg",
    "killerName": "cej0t",
    "victimName": "IceBerg",
    "assistName": null,
    "weapon": "ak47",
    "isHeadshot": true,
    "isWallbang": false,
    "isThroughSmoke": false,
    "isBlindKill": false,
    "isNoScope": false,
    "isSuicide": false,
    "eventType": "kill",
    "mapNumber": 2,
    "roundNumber": 1,
    "eventHash": "9812d5e196d6cf15cc12929e2d6481a0",
    "timestamp": "2026-02-26T10:14:57.974Z"
  },
  {
    "id": "33636ccf-314e-4f61-bddb-616c3c4c22f6",
    "matchId": "2390782",
    "logText": "leakz cej0t",
    "killerName": "leakz",
    "victimName": "cej0t",
    "assistName": null,
    "weapon": "m4a1",
    "isHeadshot": true,
    "isWallbang": false,
    "isThroughSmoke": false,
    "isBlindKill": false,
    "isNoScope": false,
    "isSuicide": false,
    "eventType": "kill",
    "mapNumber": 2,
    "roundNumber": 1,
    "eventHash": "9366c0c37594f6c894ddefbb68deaba5",
    "timestamp": "2026-02-26T10:15:00.972Z"
  },
  {
    "id": "f21eb69f-deae-4b1e-a47a-d10ecf6f6508",
    "matchId": "2390782",
    "logText": "cej0t NickyB",
    "killerName": "cej0t",
    "victimName": "NickyB",
    "assistName": null,
    "weapon": "ak47",
    "isHeadshot": true,
    "isWallbang": false,
    "isThroughSmoke": false,
    "isBlindKill": false,
    "isNoScope": false,
    "isSuicide": false,
    "eventType": "kill",
    "mapNumber": 2,
    "roundNumber": 1,
    "eventHash": "601a2d221b7478a3e9af4f1a5f201c25",
    "timestamp": "2026-02-26T10:15:01.221Z"
  },
  {
    "id": "bc6dd650-ca88-45fc-b4dd-9fa0d996ce0f",
    "matchId": "2390782",
    "logText": "leakz raalz",
    "killerName": "leakz",
    "victimName": "raalz",
    "assistName": null,
    "weapon": "m4a1",
    "isHeadshot": true,
    "isWallbang": false,
    "isThroughSmoke": false,
    "isBlindKill": false,
    "isNoScope": false,
    "isSuicide": false,
    "eventType": "kill",
    "mapNumber": 2,
    "roundNumber": 1,
    "eventHash": "0485da0e48e4270191d83be57b27afa8",
    "timestamp": "2026-02-26T10:15:03.974Z"
  },
  {
    "id": "ce1e7042-e289-46ba-a2fd-29cc82e21365",
    "matchId": "2390782",
    "logText": "cej0t salazar",
    "killerName": "cej0t",
    "victimName": "salazar",
    "assistName": null,
    "weapon": "ak47",
    "isHeadshot": true,
    "isWallbang": false,
    "isThroughSmoke": false,
    "isBlindKill": false,
    "isNoScope": false,
    "isSuicide": false,
    "eventType": "kill",
    "mapNumber": 2,
    "roundNumber": 1,
    "eventHash": "27210576cdedf727d4fb5c2c488a80c5",
    "timestamp": "2026-02-26T10:15:06.981Z"
  },
  {
    "id": "fe6ff1b9-2128-4214-8f70-3515a7c7854e",
    "matchId": "2390782",
    "logText": "NickyB bnox",
    "killerName": "NickyB",
    "victimName": "bnox",
    "assistName": null,
    "weapon": "hegrenade",
    "isHeadshot": false,
    "isWallbang": false,
    "isThroughSmoke": false,
    "isBlindKill": false,
    "isNoScope": false,
    "isSuicide": false,
    "eventType": "kill",
    "mapNumber": 2,
    "roundNumber": 1,
    "eventHash": "a90c9a49fa7df6881b8f2ecac1310da8",
    "timestamp": "2026-02-26T10:15:09.982Z"
  },
  {
    "id": "87cfe035-7536-4479-91ca-f1dfef3fcc38",
    "matchId": "2390782",
    "logText": "kraghen leakz",
    "killerName": "kraghen",
    "victimName": "leakz",
    "assistName": null,
    "weapon": "deagle",
    "isHeadshot": true,
    "isWallbang": false,
    "isThroughSmoke": false,
    "isBlindKill": false,
    "isNoScope": false,
    "isSuicide": false,
    "eventType": "kill",
    "mapNumber": 2,
    "roundNumber": 1,
    "eventHash": "daf66be8eb195af32b7c1bae42a7ab2b",
    "timestamp": "2026-02-26T10:15:09.991Z"
  },
  {
    "id": "d89fa8bc-1522-4d03-82a9-91c96eae9bd3",
    "matchId": "2390782",
    "logText": "Boye kraghen",
    "killerName": "Boye",
    "victimName": "kraghen",
    "assistName": null,
    "weapon": "deagle",
    "isHeadshot": true,
    "isWallbang": false,
    "isThroughSmoke": false,
    "isBlindKill": false,
    "isNoScope": false,
    "isSuicide": false,
    "eventType": "kill",
    "mapNumber": 2,
    "roundNumber": 1,
    "eventHash": "0cbd05dba78ab1e58988ffc0cd82a5b1",
    "timestamp": "2026-02-26T10:15:12.996Z"
  },
  {
    "id": "738edeaf-457e-4a0c-b9d8-867d5ba6c841",
    "matchId": "2390782",
    "logText": "cej0t NickyB",
    "killerName": "cej0t",
    "victimName": "NickyB",
    "assistName": null,
    "weapon": "ak47",
    "isHeadshot": false,
    "isWallbang": false,
    "isThroughSmoke": false,
    "isBlindKill": false,
    "isNoScope": false,
    "isSuicide": false,
    "eventType": "kill",
    "mapNumber": 2,
    "roundNumber": 2,
    "eventHash": "d6eb305b39747b3799eabbfb24be18cb",
    "timestamp": "2026-02-26T10:15:16.001Z"
  },
  {
    "id": "404e7a20-b03e-434e-a04c-bb61e359540b",
    "matchId": "2390782",
    "logText": "IceBerg + salazar cej0t",
    "killerName": "IceBerg",
    "victimName": "cej0t",
    "assistName": "salazar",
    "weapon": "awp",
    "isHeadshot": false,
    "isWallbang": false,
    "isThroughSmoke": false,
    "isBlindKill": false,
    "isNoScope": false,
    "isSuicide": false,
    "eventType": "kill",
    "mapNumber": 2,
    "roundNumber": 1,
    "eventHash": "1b4b678391eb7979aa484fa286a9c05e",
    "timestamp": "2026-02-26T10:15:19.012Z"
  },
  {
    "id": "b885be04-9701-4d59-8dfc-e1fad3ee2376",
    "matchId": "2390782",
    "logText": "bnox salazar",
    "killerName": "bnox",
    "victimName": "salazar",
    "assistName": null,
    "weapon": "p250",
    "isHeadshot": false,
    "isWallbang": false,
    "isThroughSmoke": false,
    "isBlindKill": false,
    "isNoScope": false,
    "isSuicide": false,
    "eventType": "kill",
    "mapNumber": 2,
    "roundNumber": 1,
    "eventHash": "70fed6e91918afc0cc8a9304f9ef59b9",
    "timestamp": "2026-02-26T10:15:22.018Z"
  },
  {
    "id": "d061e7cd-7b7a-4e73-a638-cec8f5ef4759",
    "matchId": "2390782",
    "logText": "bnox + kraghen leakz",
    "killerName": "bnox",
    "victimName": "leakz",
    "assistName": "kraghen",
    "weapon": "p250",
    "isHeadshot": true,
    "isWallbang": false,
    "isThroughSmoke": false,
    "isBlindKill": false,
    "isNoScope": false,
    "isSuicide": false,
    "eventType": "kill",
    "mapNumber": 2,
    "roundNumber": 1,
    "eventHash": "763c9e65a4a2504abbdcf0fbf40612ed",
    "timestamp": "2026-02-26T10:15:25.024Z"
  },
  {
    "id": "fd036dc0-cd7d-48cd-97da-eabe6e1e8bc9",
    "matchId": "2390782",
    "logText": "IceBerg + Boye bnox",
    "killerName": "IceBerg",
    "victimName": "bnox",
    "assistName": "Boye",
    "weapon": "awp",
    "isHeadshot": false,
    "isWallbang": false,
    "isThroughSmoke": false,
    "isBlindKill": false,
    "isNoScope": false,
    "isSuicide": false,
    "eventType": "kill",
    "mapNumber": 2,
    "roundNumber": 1,
    "eventHash": "853bff4cded34b17faf1addf66941d0d",
    "timestamp": "2026-02-26T10:15:28.057Z"
  },
  {
    "id": "a17c6252-c7eb-4ec9-b02b-6d5dc6aef762",
    "matchId": "2390782",
    "logText": "salazar + Boye kraghen",
    "killerName": "salazar",
    "victimName": "kraghen",
    "assistName": "Boye",
    "weapon": "awp",
    "isHeadshot": false,
    "isWallbang": false,
    "isThroughSmoke": false,
    "isBlindKill": false,
    "isNoScope": false,
    "isSuicide": false,
    "eventType": "kill",
    "mapNumber": 2,
    "roundNumber": 1,
    "eventHash": "f195ab9b449aef79ba4797780883bb66",
    "timestamp": "2026-02-26T10:15:37.037Z"
  },
  {
    "id": "26ae8677-77e6-4b60-9a7d-84ebeacacc60",
    "matchId": "2390782",
    "logText": "salazar kraghen",
    "killerName": "salazar",
    "victimName": "kraghen",
    "assistName": null,
    "weapon": "awp",
    "isHeadshot": false,
    "isWallbang": false,
    "isThroughSmoke": false,
    "isBlindKill": false,
    "isNoScope": true,
    "isSuicide": false,
    "eventType": "kill",
    "mapNumber": 2,
    "roundNumber": 1,
    "eventHash": "527df1c0b25a244d6bfbb015e903e215",
    "timestamp": "2026-02-26T10:15:49.074Z"
  },
  {
    "id": "88b64cee-39e3-4c66-967a-6d596b135c59",
    "matchId": "2390782",
    "logText": "NickyB + Boye bnox",
    "killerName": "NickyB",
    "victimName": "bnox",
    "assistName": "Boye",
    "weapon": "famas",
    "isHeadshot": false,
    "isWallbang": false,
    "isThroughSmoke": false,
    "isBlindKill": false,
    "isNoScope": false,
    "isSuicide": false,
    "eventType": "kill",
    "mapNumber": 2,
    "roundNumber": 1,
    "eventHash": "1ffea887a48493b14ee0dac7988dc196",
    "timestamp": "2026-02-26T10:15:49.084Z"
  },
  {
    "id": "53d40f16-575c-4eb0-8100-30d1845e579d",
    "matchId": "2390782",
    "logText": "raalz Boye",
    "killerName": "raalz",
    "victimName": "Boye",
    "assistName": null,
    "weapon": "ak47",
    "isHeadshot": true,
    "isWallbang": false,
    "isThroughSmoke": false,
    "isBlindKill": false,
    "isNoScope": false,
    "isSuicide": false,
    "eventType": "kill",
    "mapNumber": 2,
    "roundNumber": 1,
    "eventHash": "0cc7ea944cf4b89cb3b0699d70ed4b31",
    "timestamp": "2026-02-26T10:15:49.092Z"
  },
  {
    "id": "6272520b-0654-4e32-a2d3-aba67e634bc7",
    "matchId": "2390782",
    "logText": "leakz cej0t",
    "killerName": "leakz",
    "victimName": "cej0t",
    "assistName": null,
    "weapon": "m4a1",
    "isHeadshot": false,
    "isWallbang": false,
    "isThroughSmoke": false,
    "isBlindKill": false,
    "isNoScope": false,
    "isSuicide": false,
    "eventType": "kill",
    "mapNumber": 2,
    "roundNumber": 1,
    "eventHash": "651dc1cf60951e17b03f1eb298e4d886",
    "timestamp": "2026-02-26T10:15:52.062Z"
  },
  {
    "id": "c3c882cd-169e-40ec-b801-087cfe624202",
    "matchId": "2390782",
    "logText": "raalz NickyB",
    "killerName": "raalz",
    "victimName": "NickyB",
    "assistName": null,
    "weapon": "ak47",
    "isHeadshot": false,
    "isWallbang": false,
    "isThroughSmoke": false,
    "isBlindKill": false,
    "isNoScope": false,
    "isSuicide": false,
    "eventType": "kill",
    "mapNumber": 2,
    "roundNumber": 1,
    "eventHash": "dc43ffd2c289b554b0964c48de15877c",
    "timestamp": "2026-02-26T10:15:52.079Z"
  },
  {
    "id": "5c99cd81-def5-4f86-a062-41a89b525552",
    "matchId": "2390782",
    "logText": "kraghen salazar",
    "killerName": "kraghen",
    "victimName": "salazar",
    "assistName": null,
    "weapon": "galilar",
    "isHeadshot": true,
    "isWallbang": false,
    "isThroughSmoke": false,
    "isBlindKill": false,
    "isNoScope": false,
    "isSuicide": false,
    "eventType": "kill",
    "mapNumber": 2,
    "roundNumber": 1,
    "eventHash": "6a5225d5ba37dfbbba397929ee13ed75",
    "timestamp": "2026-02-26T10:15:55.067Z"
  },
  {
    "id": "be48939f-55ab-4e6a-94c5-90036bc5e5ca",
    "matchId": "2390782",
    "logText": "Boye raalz",
    "killerName": "Boye",
    "victimName": "raalz",
    "assistName": null,
    "weapon": "elite",
    "isHeadshot": false,
    "isWallbang": false,
    "isThroughSmoke": false,
    "isBlindKill": false,
    "isNoScope": false,
    "isSuicide": false,
    "eventType": "kill",
    "mapNumber": 2,
    "roundNumber": 1,
    "eventHash": "4722af19d414b897b1b7d595e937fcaa",
    "timestamp": "2026-02-26T10:15:55.076Z"
  },
  {
    "id": "43f2308b-490d-40ae-a6b0-942dffc86985",
    "matchId": "2390782",
    "logText": "Boye + IceBerg bnox",
    "killerName": "Boye",
    "victimName": "bnox",
    "assistName": "IceBerg",
    "weapon": "elite",
    "isHeadshot": true,
    "isWallbang": false,
    "isThroughSmoke": false,
    "isBlindKill": false,
    "isNoScope": false,
    "isSuicide": false,
    "eventType": "kill",
    "mapNumber": 2,
    "roundNumber": 1,
    "eventHash": "02c916c3e0b0e46574651e1ade5dac2c",
    "timestamp": "2026-02-26T10:16:04.086Z"
  },
  {
    "id": "91e4a929-8e5d-4cc0-ad86-e965c859b96f",
    "matchId": "2390782",
    "logText": "bnox leakz",
    "killerName": "bnox",
    "victimName": "leakz",
    "assistName": null,
    "weapon": "p250",
    "isHeadshot": true,
    "isWallbang": false,
    "isThroughSmoke": true,
    "isBlindKill": false,
    "isNoScope": false,
    "isSuicide": false,
    "eventType": "kill",
    "mapNumber": 2,
    "roundNumber": 1,
    "eventHash": "e8dfc1b3adc123747eb02486c5d026ca",
    "timestamp": "2026-02-26T10:16:04.095Z"
  },
  {
    "id": "53244aa9-2a27-4000-8213-74048e28aad5",
    "matchId": "2390782",
    "logText": "cej0t Boye",
    "killerName": "cej0t",
    "victimName": "Boye",
    "assistName": null,
    "weapon": "galilar",
    "isHeadshot": true,
    "isWallbang": false,
    "isThroughSmoke": true,
    "isBlindKill": false,
    "isNoScope": false,
    "isSuicide": false,
    "eventType": "kill",
    "mapNumber": 2,
    "roundNumber": 1,
    "eventHash": "961a741340e97607740a5271b31938ac",
    "timestamp": "2026-02-26T10:16:07.095Z"
  },
  {
    "id": "0d942d8d-9eca-48a1-b6a5-1553bf6eeefa",
    "matchId": "2390782",
    "logText": "cej0t Boye",
    "killerName": "cej0t",
    "victimName": "Boye",
    "assistName": null,
    "weapon": "glock",
    "isHeadshot": true,
    "isWallbang": false,
    "isThroughSmoke": false,
    "isBlindKill": false,
    "isNoScope": false,
    "isSuicide": false,
    "eventType": "kill",
    "mapNumber": 2,
    "roundNumber": 1,
    "eventHash": "2dc31c40dc79f28ec394205c33119651",
    "timestamp": "2026-02-26T10:16:49.177Z"
  },
  {
    "id": "96b42139-a354-4a19-8054-5013531acea3",
    "matchId": "2390782",
    "logText": "Boye bnox",
    "killerName": "Boye",
    "victimName": "bnox",
    "assistName": null,
    "weapon": "usp_silencer",
    "isHeadshot": true,
    "isWallbang": false,
    "isThroughSmoke": false,
    "isBlindKill": false,
    "isNoScope": false,
    "isSuicide": false,
    "eventType": "kill",
    "mapNumber": 2,
    "roundNumber": 1,
    "eventHash": "ce30f579ee9090a0e5dbfca93b8341cf",
    "timestamp": "2026-02-26T10:16:49.187Z"
  },
  {
    "id": "db1d3ec2-9c85-4df2-a873-dac9d1ed55fd",
    "matchId": "2390782",
    "logText": "cej0t planted the bomb on B (4on4)",
    "killerName": "cej0t",
    "victimName": null,
    "assistName": null,
    "weapon": "bomb",
    "isHeadshot": false,
    "isWallbang": false,
    "isThroughSmoke": false,
    "isBlindKill": false,
    "isNoScope": false,
    "isSuicide": false,
    "eventType": "bomb_plant",
    "mapNumber": 2,
    "roundNumber": 1,
    "eventHash": "f09298cf344ce9835b122eb14fca7e9a",
    "timestamp": "2026-02-26T10:17:01.184Z"
  },
  {
    "id": "063a9ea5-2fa9-4700-b86f-e8bc098123f1",
    "matchId": "2390782",
    "logText": "raalz leakz",
    "killerName": "raalz",
    "victimName": "leakz",
    "assistName": null,
    "weapon": "glock",
    "isHeadshot": true,
    "isWallbang": false,
    "isThroughSmoke": false,
    "isBlindKill": false,
    "isNoScope": false,
    "isSuicide": false,
    "eventType": "kill",
    "mapNumber": 2,
    "roundNumber": 1,
    "eventHash": "a6fea92df7c3f58e1a72bfebeb91a8c3",
    "timestamp": "2026-02-26T10:17:13.195Z"
  },
  {
    "id": "54328f5e-7295-440e-9966-1e19d4e83471",
    "matchId": "2390782",
    "logText": "raalz NickyB",
    "killerName": "raalz",
    "victimName": "NickyB",
    "assistName": null,
    "weapon": "glock",
    "isHeadshot": true,
    "isWallbang": false,
    "isThroughSmoke": false,
    "isBlindKill": false,
    "isNoScope": false,
    "isSuicide": false,
    "eventType": "kill",
    "mapNumber": 2,
    "roundNumber": 1,
    "eventHash": "2e3ff7aeb6eb3ad765b3a2057f291545",
    "timestamp": "2026-02-26T10:17:16.205Z"
  },
  {
    "id": "31eea9fe-95fb-48da-b975-bc915c8400f9",
    "matchId": "2390782",
    "logText": "kraghen IceBerg",
    "killerName": "kraghen",
    "victimName": "IceBerg",
    "assistName": null,
    "weapon": "glock",
    "isHeadshot": true,
    "isWallbang": false,
    "isThroughSmoke": false,
    "isBlindKill": false,
    "isNoScope": false,
    "isSuicide": false,
    "eventType": "kill",
    "mapNumber": 2,
    "roundNumber": 1,
    "eventHash": "a7edfbed3b913a307ed72f1fa57ea463",
    "timestamp": "2026-02-26T10:17:16.214Z"
  },
  {
    "id": "e88e1ab2-62a4-49f7-be94-7fbbfc542cac",
    "matchId": "2390782",
    "logText": "raalz salazar",
    "killerName": "raalz",
    "victimName": "salazar",
    "assistName": null,
    "weapon": "glock",
    "isHeadshot": true,
    "isWallbang": false,
    "isThroughSmoke": false,
    "isBlindKill": false,
    "isNoScope": false,
    "isSuicide": false,
    "eventType": "kill",
    "mapNumber": 2,
    "roundNumber": 1,
    "eventHash": "f066998dfdf713c0cfa518ef06382751",
    "timestamp": "2026-02-26T10:17:19.227Z"
  },
  {
    "id": "66e40ba6-4bd4-4b8b-8085-b52be57ee472",
    "matchId": "2390782",
    "logText": "shield + bnox IceBerg",
    "killerName": "shield",
    "victimName": "IceBerg",
    "assistName": "bnox",
    "weapon": "ak47",
    "isHeadshot": true,
    "isWallbang": false,
    "isThroughSmoke": false,
    "isBlindKill": false,
    "isNoScope": false,
    "isSuicide": false,
    "eventType": "kill",
    "mapNumber": 2,
    "roundNumber": 2,
    "eventHash": "17aedeca2cf7db9ce489504d2888f770",
    "timestamp": "2026-02-26T10:18:13.314Z"
  },
  {
    "id": "24b08fa8-cb60-44d7-af79-caeae0844228",
    "matchId": "2390782",
    "logText": "kraghen salazar",
    "killerName": "kraghen",
    "victimName": "salazar",
    "assistName": null,
    "weapon": "ak47",
    "isHeadshot": false,
    "isWallbang": false,
    "isThroughSmoke": false,
    "isBlindKill": false,
    "isNoScope": false,
    "isSuicide": false,
    "eventType": "kill",
    "mapNumber": 2,
    "roundNumber": 2,
    "eventHash": "e27055dca0363dfda937798f8eaa7ed2",
    "timestamp": "2026-02-26T10:18:19.331Z"
  },
  {
    "id": "6b18e4f0-97d0-4975-a63c-f86611f3f9b2",
    "matchId": "2390782",
    "logText": "salazar + Boye bnox",
    "killerName": "salazar",
    "victimName": "bnox",
    "assistName": "Boye",
    "weapon": "usp_silencer",
    "isHeadshot": true,
    "isWallbang": false,
    "isThroughSmoke": false,
    "isBlindKill": false,
    "isNoScope": false,
    "isSuicide": false,
    "eventType": "kill",
    "mapNumber": 2,
    "roundNumber": 2,
    "eventHash": "2ea8f9e1d118387b37f364699074e785",
    "timestamp": "2026-02-26T10:18:19.346Z"
  },
  {
    "id": "8ee8f1bf-1ac8-4e4b-9b35-49656fe43f25",
    "matchId": "2390782",
    "logText": "kraghen Boye",
    "killerName": "kraghen",
    "victimName": "Boye",
    "assistName": null,
    "weapon": "ak47",
    "isHeadshot": true,
    "isWallbang": false,
    "isThroughSmoke": false,
    "isBlindKill": false,
    "isNoScope": false,
    "isSuicide": false,
    "eventType": "kill",
    "mapNumber": 2,
    "roundNumber": 2,
    "eventHash": "f3258277b69025965d27018242c8a6b7",
    "timestamp": "2026-02-26T10:18:22.331Z"
  },
  {
    "id": "c35f893f-9abe-45bc-85e9-61df8a3264cb",
    "matchId": "2390782",
    "logText": "shield leakz",
    "killerName": "shield",
    "victimName": "leakz",
    "assistName": null,
    "weapon": "ak47",
    "isHeadshot": false,
    "isWallbang": false,
    "isThroughSmoke": false,
    "isBlindKill": false,
    "isNoScope": false,
    "isSuicide": false,
    "eventType": "kill",
    "mapNumber": 2,
    "roundNumber": 2,
    "eventHash": "05f503ff8ecc018083f5e19bf632492b",
    "timestamp": "2026-02-26T10:18:22.343Z"
  },
  {
    "id": "8856a685-119f-4cb6-8e9f-d2d28e826c67",
    "matchId": "2390782",
    "logText": "cej0t IceBerg",
    "killerName": "cej0t",
    "victimName": "IceBerg",
    "assistName": null,
    "weapon": "ak47",
    "isHeadshot": false,
    "isWallbang": false,
    "isThroughSmoke": false,
    "isBlindKill": false,
    "isNoScope": false,
    "isSuicide": false,
    "eventType": "kill",
    "mapNumber": 2,
    "roundNumber": 3,
    "eventHash": "80a9e0a59777477f38125916c97a806f",
    "timestamp": "2026-02-26T10:20:07.512Z"
  },
  {
    "id": "1bb71774-45f5-4b16-aa5b-27946e9b79d7",
    "matchId": "2390782",
    "logText": "kraghen NickyB",
    "killerName": "kraghen",
    "victimName": "NickyB",
    "assistName": null,
    "weapon": "ak47",
    "isHeadshot": true,
    "isWallbang": false,
    "isThroughSmoke": false,
    "isBlindKill": false,
    "isNoScope": false,
    "isSuicide": false,
    "eventType": "kill",
    "mapNumber": 2,
    "roundNumber": 3,
    "eventHash": "19f617dc37bd360e5da08849cc75f4b0",
    "timestamp": "2026-02-26T10:20:07.522Z"
  },
  {
    "id": "ea751f94-5786-4919-a68d-57abc2331910",
    "matchId": "2390782",
    "logText": "bnox leakz",
    "killerName": "bnox",
    "victimName": "leakz",
    "assistName": null,
    "weapon": "ak47",
    "isHeadshot": false,
    "isWallbang": false,
    "isThroughSmoke": false,
    "isBlindKill": false,
    "isNoScope": false,
    "isSuicide": false,
    "eventType": "kill",
    "mapNumber": 2,
    "roundNumber": 3,
    "eventHash": "72b851cd7440b5690f96f3d1a560e115",
    "timestamp": "2026-02-26T10:20:10.528Z"
  },
  {
    "id": "31d96e1c-8ebf-42a8-8c18-4084427bf313",
    "matchId": "2390782",
    "logText": "Boye kraghen",
    "killerName": "Boye",
    "victimName": "kraghen",
    "assistName": null,
    "weapon": "m4a1_silencer",
    "isHeadshot": false,
    "isWallbang": false,
    "isThroughSmoke": false,
    "isBlindKill": false,
    "isNoScope": false,
    "isSuicide": false,
    "eventType": "kill",
    "mapNumber": 2,
    "roundNumber": 3,
    "eventHash": "7431a29978fd80fbd4270af3eae10758",
    "timestamp": "2026-02-26T10:20:22.539Z"
  },
  {
    "id": "f9d7f6e4-e45b-4416-83b8-dd3a75d976a1",
    "matchId": "2390782",
    "logText": "Boye + IceBerg cej0t",
    "killerName": "Boye",
    "victimName": "cej0t",
    "assistName": "IceBerg",
    "weapon": "m4a1_silencer",
    "isHeadshot": false,
    "isWallbang": false,
    "isThroughSmoke": false,
    "isBlindKill": false,
    "isNoScope": false,
    "isSuicide": false,
    "eventType": "kill",
    "mapNumber": 2,
    "roundNumber": 3,
    "eventHash": "5ad24c78627486a18587fe9b173a4e4b",
    "timestamp": "2026-02-26T10:20:25.590Z"
  },
  {
    "id": "a342342a-b07c-470e-938f-19fa0624143f",
    "matchId": "2390782",
    "logText": "shield planted the bomb on B (3on2)",
    "killerName": "shield",
    "victimName": null,
    "assistName": null,
    "weapon": "bomb",
    "isHeadshot": false,
    "isWallbang": false,
    "isThroughSmoke": false,
    "isBlindKill": false,
    "isNoScope": false,
    "isSuicide": false,
    "eventType": "bomb_plant",
    "mapNumber": 2,
    "roundNumber": 3,
    "eventHash": "67574ee7046910281d843b130bbb7946",
    "timestamp": "2026-02-26T10:20:28.545Z"
  },
  {
    "id": "b1ad3f6b-a3e7-4b7c-8e84-8cb541fba8d1",
    "matchId": "2390782",
    "logText": "Boye + salazar shield",
    "killerName": "Boye",
    "victimName": "shield",
    "assistName": "salazar",
    "weapon": "ak47",
    "isHeadshot": true,
    "isWallbang": false,
    "isThroughSmoke": false,
    "isBlindKill": false,
    "isNoScope": false,
    "isSuicide": false,
    "eventType": "kill",
    "mapNumber": 2,
    "roundNumber": 3,
    "eventHash": "d64e320e2bb1d15c89663f861e01f90e",
    "timestamp": "2026-02-26T10:20:37.566Z"
  }
]