[
  {
    "id": "73c9eb51-4af5-4dd9-be77-5d7093451d78",
    "matchId": "2390877",
    "logText": "balencyy ALENNNCAR",
    "killerName": "balencyy",
    "victimName": "ALENNNCAR",
    "assistName": null,
    "weapon": "m4a1_silencer",
    "isHeadshot": true,
    "isWallbang": false,
    "isThroughSmoke": false,
    "isBlindKill": false,
    "isNoScope": false,
    "isSuicide": false,
    "eventType": "kill",
    "mapNumber": 1,
    "roundNumber": 1,
    "eventHash": "544e577b059534571f6f19e2bb30483d",
    "timestamp": "2026-02-27T15:14:09.245Z"
  },
  {
    "id": "125913b2-7484-42cb-9513-0e08f9c10e64",
    "matchId": "2390877",
    "logText": "balencyy phx",
    "killerName": "balencyy",
    "victimName": "phx",
    "assistName": null,
    "weapon": "m4a1_silencer",
    "isHeadshot": true,
    "isWallbang": false,
    "isThroughSmoke": false,
    "isBlindKill": false,
    "isNoScope": false,
    "isSuicide": false,
    "eventType": "kill",
    "mapNumber": 1,
    "roundNumber": 1,
    "eventHash": "43b1db87b0a5de3d5b1f16007d590a44",
    "timestamp": "2026-02-27T15:14:09.253Z"
  },
  {
    "id": "b718e258-b8f4-48c9-8896-7bc9eb955502",
    "matchId": "2390877",
    "logText": "balencyy space",
    "killerName": "balencyy",
    "victimName": "space",
    "assistName": null,
    "weapon": "m4a1_silencer",
    "isHeadshot": false,
    "isWallbang": false,
    "isThroughSmoke": false,
    "isBlindKill": false,
    "isNoScope": false,
    "isSuicide": false,
    "eventType": "kill",
    "mapNumber": 1,
    "roundNumber": 1,
    "eventHash": "4bd7a156c53da5baef1e6bfa0156cf8f",
    "timestamp": "2026-02-27T15:14:09.261Z"
  },
  {
    "id": "728cdd62-48e8-46eb-886b-b83cd2ba51a0",
    "matchId": "2390877",
    "logText": "space ianzin",
    "killerName": "space",
    "victimName": "ianzin",
    "assistName": null,
    "weapon": "glock",
    "isHeadshot": false,
    "isWallbang": false,
    "isThroughSmoke": false,
    "isBlindKill": false,
    "isNoScope": false,
    "isSuicide": false,
    "eventType": "kill",
    "mapNumber": 1,
    "roundNumber": 1,
    "eventHash": "605e4c39c12caa5a56764397706e1631",
    "timestamp": "2026-02-27T15:14:09.269Z"
  },
  {
    "id": "3b860550-d273-48d1-97e6-b0b6723fdd06",
    "matchId": "2390877",
    "logText": "ianzin Thuister",
    "killerName": "ianzin",
    "victimName": "Thuister",
    "assistName": null,
    "weapon": "m4a1_silencer",
    "isHeadshot": true,
    "isWallbang": false,
    "isThroughSmoke": false,
    "isBlindKill": false,
    "isNoScope": false,
    "isSuicide": false,
    "eventType": "kill",
    "mapNumber": 1,
    "roundNumber": 1,
    "eventHash": "b5006de74652f047a025d16138b17d32",
    "timestamp": "2026-02-27T15:14:09.281Z"
  },
  {
    "id": "88102b50-99e9-4b3f-a677-4f291d4e5d22",
    "matchId": "2390877",
    "logText": "ianzin space",
    "killerName": "ianzin",
    "victimName": "space",
    "assistName": null,
    "weapon": "m4a1_silencer",
    "isHeadshot": false,
    "isWallbang": false,
    "isThroughSmoke": false,
    "isBlindKill": false,
    "isNoScope": false,
    "isSuicide": false,
    "eventType": "kill",
    "mapNumber": 1,
    "roundNumber": 1,
    "eventHash": "b5f211aa25b67fc543416e15f915862e",
    "timestamp": "2026-02-27T15:14:09.290Z"
  },
  {
    "id": "93eac4df-a483-4bac-bb36-9b63a3096c16",
    "matchId": "2390877",
    "logText": "ianzin sakamoto",
    "killerName": "ianzin",
    "victimName": "sakamoto",
    "assistName": null,
    "weapon": "m4a1_silencer",
    "isHeadshot": true,
    "isWallbang": false,
    "isThroughSmoke": false,
    "isBlindKill": false,
    "isNoScope": false,
    "isSuicide": false,
    "eventType": "kill",
    "mapNumber": 1,
    "roundNumber": 4,
    "eventHash": "dd9cd9a5b42c71d1b0fc419e4004404b",
    "timestamp": "2026-02-27T15:14:09.298Z"
  },
  {
    "id": "a3e951c4-0276-41b8-b58f-a930a029e952",
    "matchId": "2390877",
    "logText": "BUSAN ALENNNCAR",
    "killerName": "BUSAN",
    "victimName": "ALENNNCAR",
    "assistName": null,
    "weapon": "deagle",
    "isHeadshot": true,
    "isWallbang": false,
    "isThroughSmoke": false,
    "isBlindKill": false,
    "isNoScope": false,
    "isSuicide": false,
    "eventType": "kill",
    "mapNumber": 1,
    "roundNumber": 1,
    "eventHash": "a9423b65ff00e2ace3b65c7119176146",
    "timestamp": "2026-02-27T15:14:09.307Z"
  },
  {
    "id": "9a7a14be-de60-4f23-9fd6-fcd8c28c591b",
    "matchId": "2390877",
    "logText": "ALENNNCAR balencyy",
    "killerName": "ALENNNCAR",
    "victimName": "balencyy",
    "assistName": null,
    "weapon": "ak47",
    "isHeadshot": true,
    "isWallbang": false,
    "isThroughSmoke": false,
    "isBlindKill": false,
    "isNoScope": false,
    "isSuicide": false,
    "eventType": "kill",
    "mapNumber": 1,
    "roundNumber": 1,
    "eventHash": "18036c00da34422e64bf354af54f567c",
    "timestamp": "2026-02-27T15:14:09.315Z"
  },
  {
    "id": "4e766730-94f2-4140-a7ea-42a4aa136f20",
    "matchId": "2390877",
    "logText": "balencyy phx",
    "killerName": "balencyy",
    "victimName": "phx",
    "assistName": null,
    "weapon": "awp",
    "isHeadshot": false,
    "isWallbang": false,
    "isThroughSmoke": false,
    "isBlindKill": false,
    "isNoScope": false,
    "isSuicide": false,
    "eventType": "kill",
    "mapNumber": 1,
    "roundNumber": 1,
    "eventHash": "7b9c741f8db4e6df2770bc5b9d68dcb9",
    "timestamp": "2026-02-27T15:14:09.324Z"
  },
  {
    "id": "60e6d428-5266-4a65-808e-44b7b2f5e149",
    "matchId": "2390877",
    "logText": "ALENNNCAR ianzin",
    "killerName": "ALENNNCAR",
    "victimName": "ianzin",
    "assistName": null,
    "weapon": "ak47",
    "isHeadshot": false,
    "isWallbang": false,
    "isThroughSmoke": false,
    "isBlindKill": false,
    "isNoScope": false,
    "isSuicide": false,
    "eventType": "kill",
    "mapNumber": 1,
    "roundNumber": 1,
    "eventHash": "8b911d1bfd9bf71c769b011b51eb0f24",
    "timestamp": "2026-02-27T15:14:09.333Z"
  },
  {
    "id": "d24a0fc4-5ac2-4025-8335-474cd80c4592",
    "matchId": "2390877",
    "logText": "ianzin ALENNNCAR",
    "killerName": "ianzin",
    "victimName": "ALENNNCAR",
    "assistName": null,
    "weapon": "m4a1_silencer",
    "isHeadshot": false,
    "isWallbang": false,
    "isThroughSmoke": false,
    "isBlindKill": false,
    "isNoScope": false,
    "isSuicide": false,
    "eventType": "kill",
    "mapNumber": 1,
    "roundNumber": 1,
    "eventHash": "2f235b7439112f215ffc13619f0f3dd1",
    "timestamp": "2026-02-27T15:14:09.341Z"
  },
  {
    "id": "32d4b80b-f8c9-4df5-a0a6-036243ccfea7",
    "matchId": "2390877",
    "logText": "ALENNNCAR + phx BUSAN",
    "killerName": "ALENNNCAR",
    "victimName": "BUSAN",
    "assistName": "phx",
    "weapon": "ak47",
    "isHeadshot": true,
    "isWallbang": false,
    "isThroughSmoke": false,
    "isBlindKill": false,
    "isNoScope": false,
    "isSuicide": false,
    "eventType": "kill",
    "mapNumber": 1,
    "roundNumber": 1,
    "eventHash": "75e7f499bbb423cdb6c184ab25c8611b",
    "timestamp": "2026-02-27T15:14:09.351Z"
  },
  {
    "id": "bab65509-ecac-4761-9f94-5a0671e0ed4d",
    "matchId": "2390877",
    "logText": "ianzin phx",
    "killerName": "ianzin",
    "victimName": "phx",
    "assistName": null,
    "weapon": "m4a1_silencer",
    "isHeadshot": true,
    "isWallbang": false,
    "isThroughSmoke": false,
    "isBlindKill": false,
    "isNoScope": false,
    "isSuicide": false,
    "eventType": "kill",
    "mapNumber": 1,
    "roundNumber": 1,
    "eventHash": "2c456ed814460fd5f15cf27a50fbe788",
    "timestamp": "2026-02-27T15:14:09.360Z"
  },
  {
    "id": "56bff3ca-b679-4303-831b-cd5f938e5277",
    "matchId": "2390877",
    "logText": "balencyy phx",
    "killerName": "balencyy",
    "victimName": "phx",
    "assistName": null,
    "weapon": "elite",
    "isHeadshot": true,
    "isWallbang": false,
    "isThroughSmoke": false,
    "isBlindKill": false,
    "isNoScope": false,
    "isSuicide": false,
    "eventType": "kill",
    "mapNumber": 1,
    "roundNumber": 1,
    "eventHash": "3b55033eaa183801682e0961d9865ba5",
    "timestamp": "2026-02-27T15:14:39.247Z"
  },
  {
    "id": "3dbfb129-ffe9-4a15-9a96-b4668134b763",
    "matchId": "2390877",
    "logText": "BUSAN sakamoto",
    "killerName": "BUSAN",
    "victimName": "sakamoto",
    "assistName": null,
    "weapon": "usp_silencer",
    "isHeadshot": true,
    "isWallbang": false,
    "isThroughSmoke": false,
    "isBlindKill": false,
    "isNoScope": false,
    "isSuicide": false,
    "eventType": "kill",
    "mapNumber": 1,
    "roundNumber": 1,
    "eventHash": "e2e1c097d628249fbad7ea3fa394c2e5",
    "timestamp": "2026-02-27T15:14:57.243Z"
  },
  {
    "id": "25efa846-8f29-4998-97e0-c3e6841c059b",
    "matchId": "2390877",
    "logText": "balencyy ALENNNCAR",
    "killerName": "balencyy",
    "victimName": "ALENNNCAR",
    "assistName": null,
    "weapon": "elite",
    "isHeadshot": false,
    "isWallbang": false,
    "isThroughSmoke": false,
    "isBlindKill": false,
    "isNoScope": false,
    "isSuicide": false,
    "eventType": "kill",
    "mapNumber": 1,
    "roundNumber": 1,
    "eventHash": "175a00ebb0289b7018e7bc1bd2146c04",
    "timestamp": "2026-02-27T15:15:00.244Z"
  },
  {
    "id": "0e44d34c-da39-479a-8606-ec71f8f9a9ac",
    "matchId": "2390877",
    "logText": "BUSAN space",
    "killerName": "BUSAN",
    "victimName": "space",
    "assistName": null,
    "weapon": "usp_silencer",
    "isHeadshot": true,
    "isWallbang": false,
    "isThroughSmoke": false,
    "isBlindKill": false,
    "isNoScope": false,
    "isSuicide": false,
    "eventType": "kill",
    "mapNumber": 1,
    "roundNumber": 1,
    "eventHash": "ba881266270b95f55a5ea4cc50ac7beb",
    "timestamp": "2026-02-27T15:15:06.243Z"
  },
  {
    "id": "c08d2608-bcf9-4e18-b07f-dc385740cf8b",
    "matchId": "2390877",
    "logText": "yeda + BUSAN Thuister",
    "killerName": "yeda",
    "victimName": "Thuister",
    "assistName": "BUSAN",
    "weapon": "usp_silencer",
    "isHeadshot": true,
    "isWallbang": false,
    "isThroughSmoke": false,
    "isBlindKill": false,
    "isNoScope": false,
    "isSuicide": false,
    "eventType": "kill",
    "mapNumber": 1,
    "roundNumber": 1,
    "eventHash": "5640901a5009e75c65a12baabf935fe5",
    "timestamp": "2026-02-27T15:15:21.248Z"
  },
  {
    "id": "40f0dd9c-8a8b-450a-af61-c4902ef7abdb",
    "matchId": "2390877",
    "logText": "yeda sakamoto",
    "killerName": "yeda",
    "victimName": "sakamoto",
    "assistName": null,
    "weapon": "mp9",
    "isHeadshot": false,
    "isWallbang": false,
    "isThroughSmoke": false,
    "isBlindKill": false,
    "isNoScope": false,
    "isSuicide": false,
    "eventType": "kill",
    "mapNumber": 1,
    "roundNumber": 2,
    "eventHash": "60760d86640227c03a212f8ac0871f10",
    "timestamp": "2026-02-27T15:16:15.251Z"
  },
  {
    "id": "7762a828-90c4-4d84-8d66-e2c279869c98",
    "matchId": "2390877",
    "logText": "ianzin ALENNNCAR",
    "killerName": "ianzin",
    "victimName": "ALENNNCAR",
    "assistName": null,
    "weapon": "mp7",
    "isHeadshot": false,
    "isWallbang": false,
    "isThroughSmoke": false,
    "isBlindKill": false,
    "isNoScope": false,
    "isSuicide": false,
    "eventType": "kill",
    "mapNumber": 1,
    "roundNumber": 2,
    "eventHash": "2c0529b3e3d240f749f59764a8515ef8",
    "timestamp": "2026-02-27T15:16:24.249Z"
  },
  {
    "id": "05d1f73f-c19b-4f52-ba0a-16a7d02e48de",
    "matchId": "2390877",
    "logText": "BUSAN phx",
    "killerName": "BUSAN",
    "victimName": "phx",
    "assistName": null,
    "weapon": "famas",
    "isHeadshot": true,
    "isWallbang": false,
    "isThroughSmoke": false,
    "isBlindKill": false,
    "isNoScope": false,
    "isSuicide": false,
    "eventType": "kill",
    "mapNumber": 1,
    "roundNumber": 2,
    "eventHash": "f7d6d08962087acf1ee30b666d2a8739",
    "timestamp": "2026-02-27T15:16:27.250Z"
  },
  {
    "id": "0cd343ca-fe67-42aa-b188-7fd2919e3e67",
    "matchId": "2390877",
    "logText": "BUSAN + yeda space",
    "killerName": "BUSAN",
    "victimName": "space",
    "assistName": "yeda",
    "weapon": "famas",
    "isHeadshot": false,
    "isWallbang": false,
    "isThroughSmoke": false,
    "isBlindKill": false,
    "isNoScope": false,
    "isSuicide": false,
    "eventType": "kill",
    "mapNumber": 1,
    "roundNumber": 2,
    "eventHash": "de720039b01c0190c882b04bd986ed62",
    "timestamp": "2026-02-27T15:16:30.253Z"
  },
  {
    "id": "22dbbbb3-b45d-45b1-beb4-f9df480f78b2",
    "matchId": "2390877",
    "logText": "BUSAN + balencyy Thuister",
    "killerName": "BUSAN",
    "victimName": "Thuister",
    "assistName": "balencyy",
    "weapon": "famas",
    "isHeadshot": false,
    "isWallbang": false,
    "isThroughSmoke": false,
    "isBlindKill": false,
    "isNoScope": false,
    "isSuicide": false,
    "eventType": "kill",
    "mapNumber": 1,
    "roundNumber": 2,
    "eventHash": "8f639ddb312874f93d4ab97cc5f371ad",
    "timestamp": "2026-02-27T15:16:30.261Z"
  },
  {
    "id": "cb6bad6d-fb72-4359-8c4c-9860801a7941",
    "matchId": "2390877",
    "logText": "ALENNNCAR + spaceyeda",
    "killerName": "ALENNNCAR",
    "victimName": "yeda",
    "assistName": null,
    "weapon": "ak47",
    "isHeadshot": true,
    "isWallbang": false,
    "isThroughSmoke": false,
    "isBlindKill": true,
    "isNoScope": false,
    "isSuicide": false,
    "eventType": "kill",
    "mapNumber": 1,
    "roundNumber": 1,
    "eventHash": "0be060432d37fc8e4d5788a954540c7a",
    "timestamp": "2026-02-27T15:20:11.215Z"
  },
  {
    "id": "660a53ff-a864-4846-b92b-fe2a77dd3e9b",
    "matchId": "2390877",
    "logText": "yeda space",
    "killerName": "yeda",
    "victimName": "space",
    "assistName": null,
    "weapon": "mp9",
    "isHeadshot": true,
    "isWallbang": false,
    "isThroughSmoke": false,
    "isBlindKill": false,
    "isNoScope": false,
    "isSuicide": false,
    "eventType": "kill",
    "mapNumber": 1,
    "roundNumber": 3,
    "eventHash": "6ee7b7aafa0b38faf32cd546f90e54dc",
    "timestamp": "2026-02-27T15:20:11.222Z"
  },
  {
    "id": "d817e7f3-8cb7-462e-9036-d291ad4ef01f",
    "matchId": "2390877",
    "logText": "ALENNNCAR ianzin",
    "killerName": "ALENNNCAR",
    "victimName": "ianzin",
    "assistName": null,
    "weapon": "ak47",
    "isHeadshot": true,
    "isWallbang": false,
    "isThroughSmoke": false,
    "isBlindKill": false,
    "isNoScope": false,
    "isSuicide": false,
    "eventType": "kill",
    "mapNumber": 1,
    "roundNumber": 3,
    "eventHash": "a067fec6e9170d7f53a00712881d36e7",
    "timestamp": "2026-02-27T15:20:15.289Z"
  },
  {
    "id": "3a2e567f-b5d3-497a-aa94-50cfc8a86a4f",
    "matchId": "2390877",
    "logText": "balencyy sakamoto",
    "killerName": "balencyy",
    "victimName": "sakamoto",
    "assistName": null,
    "weapon": "m4a1_silencer",
    "isHeadshot": false,
    "isWallbang": false,
    "isThroughSmoke": false,
    "isBlindKill": false,
    "isNoScope": false,
    "isSuicide": false,
    "eventType": "kill",
    "mapNumber": 1,
    "roundNumber": 3,
    "eventHash": "eb02a94c7efd878ccd759a50b55ff4cc",
    "timestamp": "2026-02-27T15:20:18.289Z"
  },
  {
    "id": "c14b62af-e617-4148-94ba-f45b92c224d0",
    "matchId": "2390877",
    "logText": "phx planted the bomb on A (3on3)",
    "killerName": "phx",
    "victimName": null,
    "assistName": null,
    "weapon": "bomb",
    "isHeadshot": false,
    "isWallbang": false,
    "isThroughSmoke": false,
    "isBlindKill": false,
    "isNoScope": false,
    "isSuicide": false,
    "eventType": "bomb_plant",
    "mapNumber": 1,
    "roundNumber": 3,
    "eventHash": "6aa17f40ff283617a98d87f7382bc67e",
    "timestamp": "2026-02-27T15:20:24.289Z"
  },
  {
    "id": "4fd5f9b1-2a20-4877-b22a-d6f5fec69020",
    "matchId": "2390877",
    "logText": "ALENNNCAR yeda",
    "killerName": "ALENNNCAR",
    "victimName": "yeda",
    "assistName": null,
    "weapon": "ak47",
    "isHeadshot": true,
    "isWallbang": false,
    "isThroughSmoke": false,
    "isBlindKill": false,
    "isNoScope": false,
    "isSuicide": false,
    "eventType": "kill",
    "mapNumber": 1,
    "roundNumber": 3,
    "eventHash": "22df0ae37bf8ee2519dbffa8121699a5",
    "timestamp": "2026-02-27T15:20:30.290Z"
  },
  {
    "id": "e73359b1-b011-4d47-ad74-21ab50cb0aa2",
    "matchId": "2390877",
    "logText": "balencyy + ianzin ALENNNCAR",
    "killerName": "balencyy",
    "victimName": "ALENNNCAR",
    "assistName": "ianzin",
    "weapon": "inferno",
    "isHeadshot": false,
    "isWallbang": false,
    "isThroughSmoke": false,
    "isBlindKill": false,
    "isNoScope": false,
    "isSuicide": false,
    "eventType": "kill",
    "mapNumber": 1,
    "roundNumber": 3,
    "eventHash": "f93f7218f4d27a3daacccb10eb43cb1b",
    "timestamp": "2026-02-27T15:20:36.292Z"
  },
  {
    "id": "ed376544-9929-42ae-923a-b79655a6b8db",
    "matchId": "2390877",
    "logText": "Thuister + sakamoto wallz1k",
    "killerName": "Thuister",
    "victimName": "wallz1k",
    "assistName": "sakamoto",
    "weapon": "mac10",
    "isHeadshot": false,
    "isWallbang": false,
    "isThroughSmoke": false,
    "isBlindKill": false,
    "isNoScope": false,
    "isSuicide": false,
    "eventType": "kill",
    "mapNumber": 1,
    "roundNumber": 3,
    "eventHash": "6fea3e7aec33fca7dc7d393aebadf456",
    "timestamp": "2026-02-27T15:20:42.294Z"
  },
  {
    "id": "beb4378c-263c-4768-95f8-9810e481e456",
    "matchId": "2390877",
    "logText": "phx balencyy",
    "killerName": "phx",
    "victimName": "balencyy",
    "assistName": null,
    "weapon": "ak47",
    "isHeadshot": true,
    "isWallbang": false,
    "isThroughSmoke": true,
    "isBlindKill": false,
    "isNoScope": false,
    "isSuicide": false,
    "eventType": "kill",
    "mapNumber": 1,
    "roundNumber": 3,
    "eventHash": "6c426eb33cf51b4ce5321dbac8e47693",
    "timestamp": "2026-02-27T15:20:42.301Z"
  },
  {
    "id": "646f1806-0d60-44ca-8422-769dd1a47456",
    "matchId": "2390877",
    "logText": "Round over - Winner: T (1 - 2) - Enemy eliminated",
    "killerName": null,
    "victimName": null,
    "assistName": null,
    "weapon": null,
    "isHeadshot": false,
    "isWallbang": false,
    "isThroughSmoke": false,
    "isBlindKill": false,
    "isNoScope": false,
    "isSuicide": false,
    "eventType": "round_end",
    "mapNumber": 1,
    "roundNumber": 3,
    "eventHash": "42b7ccadaf7353cdf84921bee2dc8ee9",
    "timestamp": "2026-02-27T15:20:45.295Z"
  },
  {
    "id": "aa9d2b78-c13b-4631-bc0e-efc6de6890e5",
    "matchId": "2390877",
    "logText": "phx + Thuister BUSAN",
    "killerName": "phx",
    "victimName": "BUSAN",
    "assistName": "Thuister",
    "weapon": "ak47",
    "isHeadshot": true,
    "isWallbang": false,
    "isThroughSmoke": false,
    "isBlindKill": false,
    "isNoScope": false,
    "isSuicide": false,
    "eventType": "kill",
    "mapNumber": 1,
    "roundNumber": 3,
    "eventHash": "00e9afb6d1d6a604c3a026cdfec9e65e",
    "timestamp": "2026-02-27T15:20:45.302Z"
  },
  {
    "id": "e5bf396c-d7a6-417d-9e22-3069f6030487",
    "matchId": "2390877",
    "logText": "sakamoto wallz1k",
    "killerName": "sakamoto",
    "victimName": "wallz1k",
    "assistName": null,
    "weapon": "ak47",
    "isHeadshot": true,
    "isWallbang": false,
    "isThroughSmoke": false,
    "isBlindKill": false,
    "isNoScope": false,
    "isSuicide": false,
    "eventType": "kill",
    "mapNumber": 1,
    "roundNumber": 4,
    "eventHash": "8710dc11b36d6f6fb064feb0839e0139",
    "timestamp": "2026-02-27T15:22:33.307Z"
  },
  {
    "id": "36cc8731-e00d-4ec4-a5e6-8ab1700c22b7",
    "matchId": "2390877",
    "logText": "phx + ALENNNCARbalencyy",
    "killerName": "phx",
    "victimName": "balencyy",
    "assistName": null,
    "weapon": "ak47",
    "isHeadshot": false,
    "isWallbang": false,
    "isThroughSmoke": true,
    "isBlindKill": true,
    "isNoScope": false,
    "isSuicide": false,
    "eventType": "kill",
    "mapNumber": 1,
    "roundNumber": 4,
    "eventHash": "ee5894dc73c3a9cdd2120255668a82ac",
    "timestamp": "2026-02-27T15:22:45.306Z"
  },
  {
    "id": "16c60480-1671-4043-9e54-d8d53bd1e9c5",
    "matchId": "2390877",
    "logText": "Thuister BUSAN",
    "killerName": "Thuister",
    "victimName": "BUSAN",
    "assistName": null,
    "weapon": "ak47",
    "isHeadshot": true,
    "isWallbang": false,
    "isThroughSmoke": false,
    "isBlindKill": false,
    "isNoScope": false,
    "isSuicide": false,
    "eventType": "kill",
    "mapNumber": 1,
    "roundNumber": 4,
    "eventHash": "6b50a3536e96aa176965a9bfac2e6117",
    "timestamp": "2026-02-27T15:22:45.315Z"
  },
  {
    "id": "f473053d-daec-4b50-bc61-dbe53b7bb7de",
    "matchId": "2390877",
    "logText": "ALENNNCAR planted the bomb on B (4on2)",
    "killerName": "ALENNNCAR",
    "victimName": null,
    "assistName": null,
    "weapon": "bomb",
    "isHeadshot": false,
    "isWallbang": false,
    "isThroughSmoke": false,
    "isBlindKill": false,
    "isNoScope": false,
    "isSuicide": false,
    "eventType": "bomb_plant",
    "mapNumber": 1,
    "roundNumber": 4,
    "eventHash": "67413b237c3f5438d40b37b5db320bb0",
    "timestamp": "2026-02-27T15:22:54.315Z"
  },
  {
    "id": "773a0aee-8c97-4a93-87b8-bd40445a21e8",
    "matchId": "2390877",
    "logText": "Round over - Winner: T (2 - 2) - Target bombed",
    "killerName": null,
    "victimName": null,
    "assistName": null,
    "weapon": null,
    "isHeadshot": false,
    "isWallbang": false,
    "isThroughSmoke": false,
    "isBlindKill": false,
    "isNoScope": false,
    "isSuicide": false,
    "eventType": "round_end",
    "mapNumber": 1,
    "roundNumber": 4,
    "eventHash": "f0546fa9b1ec12945286812ef11d8103",
    "timestamp": "2026-02-27T15:23:36.312Z"
  },
  {
    "id": "6d53b9b9-1dd5-4632-8cd5-26eb59fab208",
    "matchId": "2390877",
    "logText": "ianzin + wallz1kALENNNCAR",
    "killerName": "ianzin",
    "victimName": "ALENNNCAR",
    "assistName": null,
    "weapon": "m4a1_silencer",
    "isHeadshot": false,
    "isWallbang": false,
    "isThroughSmoke": false,
    "isBlindKill": true,
    "isNoScope": false,
    "isSuicide": false,
    "eventType": "kill",
    "mapNumber": 1,
    "roundNumber": 5,
    "eventHash": "76993604bd3c8aeabcf281e15e733b32",
    "timestamp": "2026-02-27T15:24:12.315Z"
  },
  {
    "id": "e9ccd738-84b7-4b93-9ff6-774757843d03",
    "matchId": "2390877",
    "logText": "yeda + ianzin space",
    "killerName": "yeda",
    "victimName": "space",
    "assistName": "ianzin",
    "weapon": "ak47",
    "isHeadshot": true,
    "isWallbang": false,
    "isThroughSmoke": false,
    "isBlindKill": false,
    "isNoScope": false,
    "isSuicide": false,
    "eventType": "kill",
    "mapNumber": 1,
    "roundNumber": 5,
    "eventHash": "5141dfadc9090cae37adc217b654e455",
    "timestamp": "2026-02-27T15:24:15.323Z"
  },
  {
    "id": "f5e46f05-40be-4232-b0c3-fb4210ba5562",
    "matchId": "2390877",
    "logText": "yeda + wallz1ksakamoto",
    "killerName": "yeda",
    "victimName": "sakamoto",
    "assistName": null,
    "weapon": "ak47",
    "isHeadshot": true,
    "isWallbang": false,
    "isThroughSmoke": false,
    "isBlindKill": true,
    "isNoScope": false,
    "isSuicide": false,
    "eventType": "kill",
    "mapNumber": 1,
    "roundNumber": 5,
    "eventHash": "6d913c262316ee0f229f931dbd976a6c",
    "timestamp": "2026-02-27T15:24:15.334Z"
  },
  {
    "id": "e973360c-e195-441b-a962-2b6e1b66118d",
    "matchId": "2390877",
    "logText": "Thuister BUSAN",
    "killerName": "Thuister",
    "victimName": "BUSAN",
    "assistName": null,
    "weapon": "ak47",
    "isHeadshot": false,
    "isWallbang": false,
    "isThroughSmoke": false,
    "isBlindKill": false,
    "isNoScope": false,
    "isSuicide": false,
    "eventType": "kill",
    "mapNumber": 1,
    "roundNumber": 5,
    "eventHash": "aeef3afe7ba596c1276a1904f06c5a12",
    "timestamp": "2026-02-27T15:24:24.337Z"
  },
  {
    "id": "4ff736e7-2c70-4841-bca8-3b393d374b73",
    "matchId": "2390877",
    "logText": "phx ianzin",
    "killerName": "phx",
    "victimName": "ianzin",
    "assistName": null,
    "weapon": "ak47",
    "isHeadshot": true,
    "isWallbang": false,
    "isThroughSmoke": false,
    "isBlindKill": false,
    "isNoScope": false,
    "isSuicide": false,
    "eventType": "kill",
    "mapNumber": 1,
    "roundNumber": 5,
    "eventHash": "b410e8577cea25df42bd6847356e1f29",
    "timestamp": "2026-02-27T15:24:33.319Z"
  },
  {
    "id": "3ece9ba7-154c-467c-ab1c-00c314f3aa24",
    "matchId": "2390877",
    "logText": "wallz1k + balencyy Thuister",
    "killerName": "wallz1k",
    "victimName": "Thuister",
    "assistName": "balencyy",
    "weapon": "ak47",
    "isHeadshot": false,
    "isWallbang": false,
    "isThroughSmoke": true,
    "isBlindKill": false,
    "isNoScope": false,
    "isSuicide": false,
    "eventType": "kill",
    "mapNumber": 1,
    "roundNumber": 5,
    "eventHash": "3de10d2da695987e1ca497f9899cb690",
    "timestamp": "2026-02-27T15:24:39.330Z"
  },
  {
    "id": "cfa32b3c-1cf7-45da-aa5d-f44088e66b59",
    "matchId": "2390877",
    "logText": "Round over - Winner: CT (2 - 3) - Enemy eliminated",
    "killerName": null,
    "victimName": null,
    "assistName": null,
    "weapon": null,
    "isHeadshot": false,
    "isWallbang": false,
    "isThroughSmoke": false,
    "isBlindKill": false,
    "isNoScope": false,
    "isSuicide": false,
    "eventType": "round_end",
    "mapNumber": 1,
    "roundNumber": 5,
    "eventHash": "c9b92a04ebfcd37a7c1b7d2097013fa3",
    "timestamp": "2026-02-27T15:25:21.318Z"
  },
  {
    "id": "3df33064-53a9-42b9-8e5a-137828fba4a6",
    "matchId": "2390877",
    "logText": "yeda phx",
    "killerName": "yeda",
    "victimName": "phx",
    "assistName": null,
    "weapon": "ak47",
    "isHeadshot": false,
    "isWallbang": false,
    "isThroughSmoke": false,
    "isBlindKill": false,
    "isNoScope": false,
    "isSuicide": false,
    "eventType": "kill",
    "mapNumber": 1,
    "roundNumber": 5,
    "eventHash": "77f70c9dd3e1a649f09db71b016c19a3",
    "timestamp": "2026-02-27T15:25:21.327Z"
  },
  {
    "id": "3ea019e2-11a1-4d58-9933-27bed850345e",
    "matchId": "2390877",
    "logText": "ALENNNCAR wallz1k",
    "killerName": "ALENNNCAR",
    "victimName": "wallz1k",
    "assistName": null,
    "weapon": "ak47",
    "isHeadshot": false,
    "isWallbang": false,
    "isThroughSmoke": false,
    "isBlindKill": false,
    "isNoScope": false,
    "isSuicide": false,
    "eventType": "kill",
    "mapNumber": 1,
    "roundNumber": 6,
    "eventHash": "265056198abe1c684a293fa8237c99b5",
    "timestamp": "2026-02-27T15:26:51.344Z"
  },
  {
    "id": "8725112f-7253-4820-a2a0-35fc46af086d",
    "matchId": "2390877",
    "logText": "Thuister balencyy",
    "killerName": "Thuister",
    "victimName": "balencyy",
    "assistName": null,
    "weapon": "mac10",
    "isHeadshot": true,
    "isWallbang": false,
    "isThroughSmoke": false,
    "isBlindKill": false,
    "isNoScope": false,
    "isSuicide": false,
    "eventType": "kill",
    "mapNumber": 1,
    "roundNumber": 6,
    "eventHash": "6d3034154ac0ec1b3213817b0fed3e1b",
    "timestamp": "2026-02-27T15:26:51.359Z"
  },
  {
    "id": "8c50f210-3f08-46b4-9135-104d3543ed11",
    "matchId": "2390877",
    "logText": "BUSAN + balencyy Thuister",
    "killerName": "BUSAN",
    "victimName": "Thuister",
    "assistName": "balencyy",
    "weapon": "inferno",
    "isHeadshot": false,
    "isWallbang": false,
    "isThroughSmoke": false,
    "isBlindKill": false,
    "isNoScope": false,
    "isSuicide": false,
    "eventType": "kill",
    "mapNumber": 1,
    "roundNumber": 6,
    "eventHash": "db7a45ffe393d024f5ea3d02a7ece92f",
    "timestamp": "2026-02-27T15:26:54.343Z"
  },
  {
    "id": "11d5f119-5322-4f0d-9cbe-acdd18465249",
    "matchId": "2390877",
    "logText": "ianzin sakamoto",
    "killerName": "ianzin",
    "victimName": "sakamoto",
    "assistName": null,
    "weapon": "m4a1_silencer",
    "isHeadshot": false,
    "isWallbang": false,
    "isThroughSmoke": false,
    "isBlindKill": false,
    "isNoScope": false,
    "isSuicide": false,
    "eventType": "kill",
    "mapNumber": 1,
    "roundNumber": 6,
    "eventHash": "657a596dd830e8bc8be4242703cdddc9",
    "timestamp": "2026-02-27T15:27:03.343Z"
  },
  {
    "id": "bcf16edf-bae7-4269-937d-4a599128103f",
    "matchId": "2390877",
    "logText": "yeda space",
    "killerName": "yeda",
    "victimName": "space",
    "assistName": null,
    "weapon": "ak47",
    "isHeadshot": true,
    "isWallbang": false,
    "isThroughSmoke": false,
    "isBlindKill": false,
    "isNoScope": false,
    "isSuicide": false,
    "eventType": "kill",
    "mapNumber": 1,
    "roundNumber": 6,
    "eventHash": "0ff921fe27b61176617156582c5ed2fc",
    "timestamp": "2026-02-27T15:27:09.350Z"
  },
  {
    "id": "08165b93-605b-45c3-a086-837545b12a7b",
    "matchId": "2390877",
    "logText": "yeda + ianzin ALENNNCAR",
    "killerName": "yeda",
    "victimName": "ALENNNCAR",
    "assistName": "ianzin",
    "weapon": "ak47",
    "isHeadshot": false,
    "isWallbang": false,
    "isThroughSmoke": false,
    "isBlindKill": false,
    "isNoScope": false,
    "isSuicide": false,
    "eventType": "kill",
    "mapNumber": 1,
    "roundNumber": 6,
    "eventHash": "33efaf276259e5e8c5962244b0db7494",
    "timestamp": "2026-02-27T15:27:09.359Z"
  },
  {
    "id": "17838716-bc80-44bd-9766-76fdcaceda02",
    "matchId": "2390877",
    "logText": "phx + space yeda",
    "killerName": "phx",
    "victimName": "yeda",
    "assistName": "space",
    "weapon": "ak47",
    "isHeadshot": true,
    "isWallbang": false,
    "isThroughSmoke": false,
    "isBlindKill": false,
    "isNoScope": false,
    "isSuicide": false,
    "eventType": "kill",
    "mapNumber": 1,
    "roundNumber": 6,
    "eventHash": "57c0bbec46d752dcd6a0b1078ec17b23",
    "timestamp": "2026-02-27T15:27:12.343Z"
  },
  {
    "id": "bfeb0959-9006-4d01-8a06-c01898c9d014",
    "matchId": "2390877",
    "logText": "phx planted the bomb on A (1on2)",
    "killerName": "phx",
    "victimName": null,
    "assistName": null,
    "weapon": "bomb",
    "isHeadshot": false,
    "isWallbang": false,
    "isThroughSmoke": false,
    "isBlindKill": false,
    "isNoScope": false,
    "isSuicide": false,
    "eventType": "bomb_plant",
    "mapNumber": 1,
    "roundNumber": 6,
    "eventHash": "f6b18eaeb8a9db7d6c1bcedd52371592",
    "timestamp": "2026-02-27T15:27:33.345Z"
  },
  {
    "id": "c2681252-dc28-494e-adc6-6195c302b2a6",
    "matchId": "2390877",
    "logText": "phx ianzin",
    "killerName": "phx",
    "victimName": "ianzin",
    "assistName": null,
    "weapon": "ak47",
    "isHeadshot": false,
    "isWallbang": false,
    "isThroughSmoke": false,
    "isBlindKill": false,
    "isNoScope": false,
    "isSuicide": false,
    "eventType": "kill",
    "mapNumber": 1,
    "roundNumber": 6,
    "eventHash": "b98a50a7a61953c84111abdd3d92937f",
    "timestamp": "2026-02-27T15:27:39.362Z"
  },
  {
    "id": "70b5e0b2-bf0d-4b31-ac09-149175d51f8c",
    "matchId": "2390877",
    "logText": "phx BUSAN",
    "killerName": "phx",
    "victimName": "BUSAN",
    "assistName": null,
    "weapon": "ak47",
    "isHeadshot": true,
    "isWallbang": false,
    "isThroughSmoke": false,
    "isBlindKill": false,
    "isNoScope": false,
    "isSuicide": false,
    "eventType": "kill",
    "mapNumber": 1,
    "roundNumber": 6,
    "eventHash": "4a5a67d0466680f2595f8218b8ea2ce1",
    "timestamp": "2026-02-27T15:27:42.346Z"
  }
]