[
  {
    "id": "687b144e-6dcc-4358-9229-d72d8379b0a4",
    "matchId": "2391006",
    "logText": "OCEANA + Diesen rhittacrit",
    "killerName": "OCEANA",
    "victimName": "rhittacrit",
    "assistName": "Diesen",
    "weapon": "ak47",
    "isHeadshot": false,
    "isWallbang": false,
    "isThroughSmoke": false,
    "isBlindKill": false,
    "isNoScope": false,
    "isSuicide": false,
    "eventType": "kill",
    "mapNumber": 2,
    "roundNumber": 17,
    "roundTimer": "0:00",
    "eventHash": "c693b13f094eb2871bc1671708c52029",
    "timestamp": "2026-02-26T10:11:14.110Z"
  },
  {
    "id": "0c004f7f-cc98-47ac-8f7d-0f89d273b1af",
    "matchId": "2391006",
    "logText": "rhittacrit AccuracyTG",
    "killerName": "rhittacrit",
    "victimName": "AccuracyTG",
    "assistName": null,
    "weapon": "awp",
    "isHeadshot": false,
    "isWallbang": false,
    "isThroughSmoke": false,
    "isBlindKill": false,
    "isNoScope": false,
    "isSuicide": false,
    "eventType": "kill",
    "mapNumber": 2,
    "roundNumber": 17,
    "roundTimer": "0:00",
    "eventHash": "022ceaff33569adbd46bd987a85926b1",
    "timestamp": "2026-02-26T10:11:14.118Z"
  },
  {
    "id": "88c2b75e-b15b-4e77-aa03-051f54e1dac7",
    "matchId": "2391006",
    "logText": "MagnumZ + fury5k + fury5kerkaSt",
    "killerName": "MagnumZ",
    "victimName": "erkaSt",
    "assistName": "fury5k",
    "weapon": "ak47",
    "isHeadshot": false,
    "isWallbang": false,
    "isThroughSmoke": true,
    "isBlindKill": true,
    "isNoScope": false,
    "isSuicide": false,
    "eventType": "kill",
    "mapNumber": 2,
    "roundNumber": 17,
    "roundTimer": "0:00",
    "eventHash": "3f9721dd572bf20074613aa279306503",
    "timestamp": "2026-02-26T10:11:14.127Z"
  },
  {
    "id": "ab9ba814-bdcc-4d23-bf95-8e1a8bb3f6e4",
    "matchId": "2391006",
    "logText": "Round over - Winner: CT (4 - 12) - Enemy eliminated",
    "killerName": null,
    "victimName": null,
    "assistName": null,
    "weapon": null,
    "isHeadshot": false,
    "isWallbang": false,
    "isThroughSmoke": false,
    "isBlindKill": false,
    "isNoScope": false,
    "isSuicide": false,
    "eventType": "round_end",
    "mapNumber": 2,
    "roundNumber": 16,
    "roundTimer": "0:00",
    "eventHash": "0ebdb3334250dfba7494157f556b4bc2",
    "timestamp": "2026-02-26T10:11:14.144Z"
  },
  {
    "id": "0b52b485-b613-45f2-8946-072fc959d5b9",
    "matchId": "2391006",
    "logText": "fury5k Zesta",
    "killerName": "fury5k",
    "victimName": "Zesta",
    "assistName": null,
    "weapon": "m4a1",
    "isHeadshot": true,
    "isWallbang": false,
    "isThroughSmoke": false,
    "isBlindKill": false,
    "isNoScope": false,
    "isSuicide": false,
    "eventType": "kill",
    "mapNumber": 2,
    "roundNumber": 16,
    "roundTimer": "0:00",
    "eventHash": "7ca238876db74269a48470be188c852e",
    "timestamp": "2026-02-26T10:11:14.152Z"
  },
  {
    "id": "49855218-4601-44f6-999d-64e5673ba9b0",
    "matchId": "2391006",
    "logText": "Zesta + AccuracyTG Wonderzce",
    "killerName": "Zesta",
    "victimName": "Wonderzce",
    "assistName": "AccuracyTG",
    "weapon": "ak47",
    "isHeadshot": false,
    "isWallbang": false,
    "isThroughSmoke": false,
    "isBlindKill": false,
    "isNoScope": false,
    "isSuicide": false,
    "eventType": "kill",
    "mapNumber": 2,
    "roundNumber": 16,
    "roundTimer": "0:00",
    "eventHash": "2d4a54b7e88ef77b011abcdab6530474",
    "timestamp": "2026-02-26T10:11:14.162Z"
  },
  {
    "id": "919861ed-5867-4fc3-90c0-dc4726aa35af",
    "matchId": "2391006",
    "logText": "Wonderzce erkaSt",
    "killerName": "Wonderzce",
    "victimName": "erkaSt",
    "assistName": null,
    "weapon": "ak47",
    "isHeadshot": true,
    "isWallbang": true,
    "isThroughSmoke": false,
    "isBlindKill": false,
    "isNoScope": false,
    "isSuicide": false,
    "eventType": "kill",
    "mapNumber": 2,
    "roundNumber": 16,
    "roundTimer": "0:00",
    "eventHash": "c0735bc6f733b6cffcf6c85d41aaef93",
    "timestamp": "2026-02-26T10:11:14.172Z"
  },
  {
    "id": "6898c98d-0446-4504-a7f3-6fca98bb271d",
    "matchId": "2391006",
    "logText": "MagnumZ + rhittacrit Diesen",
    "killerName": "MagnumZ",
    "victimName": "Diesen",
    "assistName": "rhittacrit",
    "weapon": "m4a1_silencer",
    "isHeadshot": false,
    "isWallbang": false,
    "isThroughSmoke": true,
    "isBlindKill": false,
    "isNoScope": false,
    "isSuicide": false,
    "eventType": "kill",
    "mapNumber": 2,
    "roundNumber": 16,
    "roundTimer": "0:00",
    "eventHash": "3c0666e7a1b1f5e0a2f6456d1aed4514",
    "timestamp": "2026-02-26T10:11:14.180Z"
  },
  {
    "id": "d136c04e-1f0d-4494-99b9-0f56a871eaaf",
    "matchId": "2391006",
    "logText": "me1o + Wonderzce + MagnumZOCEANA",
    "killerName": "me1o",
    "victimName": "OCEANA",
    "assistName": "Wonderzce",
    "weapon": "m4a1_silencer",
    "isHeadshot": false,
    "isWallbang": false,
    "isThroughSmoke": false,
    "isBlindKill": true,
    "isNoScope": false,
    "isSuicide": false,
    "eventType": "kill",
    "mapNumber": 2,
    "roundNumber": 16,
    "roundTimer": "0:00",
    "eventHash": "71a3da083a13b359e43f16b02c479d92",
    "timestamp": "2026-02-26T10:11:14.189Z"
  },
  {
    "id": "3624cee5-1586-4afa-bbac-762b9dbe8157",
    "matchId": "2391006",
    "logText": "OCEANA + Diesenrhittacrit",
    "killerName": "OCEANA",
    "victimName": "rhittacrit",
    "assistName": null,
    "weapon": "ak47",
    "isHeadshot": false,
    "isWallbang": false,
    "isThroughSmoke": false,
    "isBlindKill": true,
    "isNoScope": false,
    "isSuicide": false,
    "eventType": "kill",
    "mapNumber": 2,
    "roundNumber": 16,
    "roundTimer": "0:00",
    "eventHash": "aeaeaa3c99bec2eb68179305993f8ebf",
    "timestamp": "2026-02-26T10:11:14.197Z"
  },
  {
    "id": "01f1702b-4dd8-40f2-98de-73916ac7048b",
    "matchId": "2391006",
    "logText": "Wonderzce + me1o AccuracyTG",
    "killerName": "Wonderzce",
    "victimName": "AccuracyTG",
    "assistName": "me1o",
    "weapon": "mp7",
    "isHeadshot": false,
    "isWallbang": false,
    "isThroughSmoke": false,
    "isBlindKill": false,
    "isNoScope": false,
    "isSuicide": false,
    "eventType": "kill",
    "mapNumber": 2,
    "roundNumber": 16,
    "roundTimer": "0:00",
    "eventHash": "28ce34c0401e1b121f809d959e434717",
    "timestamp": "2026-02-26T10:11:14.205Z"
  },
  {
    "id": "e8b7f1f9-236e-42c3-a820-9b9d1996c49f",
    "matchId": "2391006",
    "logText": "me1o + fury5k OCEANA",
    "killerName": "me1o",
    "victimName": "OCEANA",
    "assistName": "fury5k",
    "weapon": "ak47",
    "isHeadshot": true,
    "isWallbang": false,
    "isThroughSmoke": false,
    "isBlindKill": false,
    "isNoScope": false,
    "isSuicide": false,
    "eventType": "kill",
    "mapNumber": 2,
    "roundNumber": 17,
    "roundTimer": "0:00",
    "eventHash": "9c9eda47c09c13d786cce4656eaeb904",
    "timestamp": "2026-02-26T10:11:23.110Z"
  },
  {
    "id": "6b595396-0376-41d7-b85d-529a34b5a9fc",
    "matchId": "2391006",
    "logText": "me1o Diesen",
    "killerName": "me1o",
    "victimName": "Diesen",
    "assistName": null,
    "weapon": "ak47",
    "isHeadshot": true,
    "isWallbang": false,
    "isThroughSmoke": false,
    "isBlindKill": false,
    "isNoScope": false,
    "isSuicide": false,
    "eventType": "kill",
    "mapNumber": 2,
    "roundNumber": 17,
    "roundTimer": "0:00",
    "eventHash": "92104a6e7b9ff3ce44c8cd063f6af39d",
    "timestamp": "2026-02-26T10:11:26.120Z"
  },
  {
    "id": "2d985590-38ef-4e5c-aa43-5f6a81b92177",
    "matchId": "2391006",
    "logText": "Round over - Winner: CT (4 - 13) - Enemy eliminated",
    "killerName": null,
    "victimName": null,
    "assistName": null,
    "weapon": null,
    "isHeadshot": false,
    "isWallbang": false,
    "isThroughSmoke": false,
    "isBlindKill": false,
    "isNoScope": false,
    "isSuicide": false,
    "eventType": "round_end",
    "mapNumber": 2,
    "roundNumber": 17,
    "roundTimer": "0:00",
    "eventHash": "e1af07e472f54be6a499b9b9bac3943d",
    "timestamp": "2026-02-26T10:11:32.126Z"
  },
  {
    "id": "62d37802-8b04-4265-9b73-fd26c555baf7",
    "matchId": "2391006",
    "logText": "MagnumZ + Wonderzce Zesta",
    "killerName": "MagnumZ",
    "victimName": "Zesta",
    "assistName": "Wonderzce",
    "weapon": "ak47",
    "isHeadshot": false,
    "isWallbang": false,
    "isThroughSmoke": false,
    "isBlindKill": false,
    "isNoScope": false,
    "isSuicide": false,
    "eventType": "kill",
    "mapNumber": 2,
    "roundNumber": 17,
    "roundTimer": "0:00",
    "eventHash": "88d5c9830e1c66596f9cfff420d0cac7",
    "timestamp": "2026-02-26T10:11:32.134Z"
  }
]